Workbook

Sheet Input
B2: Description | C2: Unit | D2: Value
B3: Project Reference | C3: Unique | D3: =D4&D29 -> 44059
B4: Date | C4: Calculation | D4: =TODAY() -> 44059 | G4: EAC
B5: Electricity Demand | C5: Annual kWh | D5: 100 | F5: Standard Model
B6: Price of Electricity | C6: Per kWh | D6: 100 | F6: Beds | G6: 2 | H6: 3 | I6: 4 | J6: 5 | K6: 6
B7: Standing Charge | C7: Per Day | D7: 100 | F7: Low User | G7: 2000 | H7: 3000 | I7: 4150 | J7: 4500 | K7: 4750
B8: Annual Cost of Electricity | C8: Calculation | D8: =(D5*D6)+(D7*365) -> 0 | F8: Std User | G8: 2500 | H8: 3500 | I8: 4650 | J8: 5000 | K8: 5250
B9: Quantity of Panels | C9: Number | D9: 10 | F9: High User | G9: 3500 | H9: 4500 | I9: 5650 | J9: 6000 | K9: 6250
B10: Panel Manufacturer | C10: Option | D10: Phonosolar (Preferred) | F10: Add Below to above EAC if Required
B11: Panel Wattage | C11: Option | D11: 270 | F11: Electric Car | G11: 2500
B12: System Size | C12: Calculated kW dc | D12: =(D9*D11)/1000 -> 2.7 | F12: Air Source Heating | G12: 3000
B13: Specific Yield | C13: Annual kWh per KW | F13: Swimming Pool (Electric) | G13: 3500
B14: Annual Yield | C14: Calculation | D14: =D13*D12 -> 0 | F14: Electricity Rates
B15: Irradience Zone | C15: As per MCS Guide | D15: =VLOOKUP(D22,'MCS Irradiation Zones'!AN2:AO370,2,0) -> 10 | G15: Rate | H15: VAT | I15: Total
B16: Roof Pitch (Degrees) | C16: ⁰ | D16: 30 | F16: Average UK Electricity Rate | G16: 0.1672 | H16: =G16*0.05 -> 0.00836 | I16: =G16+H16 -> 0.17556
B17: Azimuth(Degrees) | C17: ⁰ | D17: 3.2 | F17: Average UK Standing Charge | G17: 0.212 | H17: =G17*0.05 -> 0.0106 | I17: =G17+H17 -> 0.2226
B18: Roof Type | C18: Option | D18: In Roof | I18: Use Above if Unknown
B19: Panels | C19: Option | D19: Blue
B20: Scaffold Required | C20: Option | D20: No
B21: Storage Size | C21: kW dc | D21: 0
B22: Postcode (Short) | C22: Option | D22: CR
B23: Title | C23: Text | D23: Mr/s
B24: First Name | C24: Text | D24: Kilian Seifert
B25: Last Name | C25: Text
B26: House Number | C26: Text | D26: 34
B27: Street Name | C27: Text | D27: Manor Way
B28: Town | C28: Text | D28: Mitcham
B29: Postcode | C29: Text | D29: CR4 1EE
B30: Telephone Number | C30: Number | D30: 07731894329
B31: Salesman Discount | C31: Free Entry | E31: Manager Approval Required Over £500
B32: Margin | C32: % | D32: 0.325 | E32: Must remain at 33% unless agreed with Manager
B33: VAT Level | C33: % | D33: 0.05
B34: Additional Item | C34: Choice | D34: None
B35: Additional Item | C35: Choice | D35: None
B36: Additional Item | C36: Choice | D36: None
B37: Additional Item | C37: Choice | D37: None | F37: System Size Bigger than 4kW | G37: Grid Application
F38: System Size Bigger than 10kW | G38: Grid Application 2
F39: System Size Bigger > 4kW but <5kW | G39: Sofar Solar 4000 HYD Hybrid Inverter
F40: System Size Bigger > 5kW but <6kW | G40: Sofar Solar 5000 HYD Hybrid Inverter
F41: System Size Bigger > 6kW but <7kW | G41: Sofar Solar 6000 HYD Hybrid Inverter

Sheet Your Proposal
A2: Your Quotation (Inclusive of VAT)
A3: =Costing!L37 -> 4077.6146
A4: PAYMENT TERMS
A5: Payment 1 @ 60% 14 Days prior to Installation Date | H5: =A3*60% -> 2446.5688
A6: Payment 2 @ 40% 7 days post Completion of Installation | H6: =A3*40% -> 1631.0458
A7: Estimated Years to Payback | H7: ='Usage and Savings'!N12 -> 20
A8: System Size (kWdc) | H8: =Costing!C1 -> 2.7
A9: Quantity of Panels | H9: =Input!D9&" Panels" -> 10 Panels
A10: Battery Storage Size | H10: =Input!D21&" kWdc" -> 0 kWdc
A11: BREAKDOWN OF PERFORMANCE
A12: Description | B12: Jan | C12: Feb | D12: Mar | E12: Apr | F12: May | G12: Jun | H12: Jul | I12: Aug | J12: Sep | K12: Oct | L12: Nov | M12: Dec | N12: Total
A13: Grid Usage | B13: =Calculation!KM3 -> 0 | C13: =Calculation!KN3 -> 0 | D13: =Calculation!KO3 -> 0 | E13: =Calculation!KP3 -> 0 | F13: =Calculation!KQ3 -> 0 | G13: =Calculation!KR3 -> 0 | H13: =Calculation!KS3 -> 0 | I13: =Calculation!KT3 -> 0 | ... M13: =Calculation!KX3 -> 0 | N13: =SUM(B13:M13) -> 0
A14: Solar Generation | B14: =Calculation!KM4 -> 0 | C14: =Calculation!KN4 -> 0 | D14: =Calculation!KO4 -> 0 | E14: =Calculation!KP4 -> 0 | F14: =Calculation!KQ4 -> 0 | G14: =Calculation!KR4 -> 0 | H14: =Calculation!KS4 -> 0 | I14: =Calculation!KT4 -> 0 | ... M14: =Calculation!KX4 -> 0 | N14: =SUM(B14:M14) -> 0
A15: Solar being Exported to Grid without Battery | B15: =Calculation!KM5 -> 0 | C15: =Calculation!KN5 -> 0 | D15: =Calculation!KO5 -> 0 | E15: =Calculation!KP5 -> 0 | F15: =Calculation!KQ5 -> 0 | G15: =Calculation!KR5 -> 0 | H15: =Calculation!KS5 -> 0 | I15: =Calculation!KT5 -> 0 | ... M15: =Calculation!KX5 -> 0 | N15: =SUM(B15:M15) -> 0
A16: Solar Being Used by Home without Battery | B16: =Calculation!KM6 -> 0 | C16: =Calculation!KN6 -> 0 | D16: =Calculation!KO6 -> 0 | E16: =Calculation!KP6 -> 0 | F16: =Calculation!KQ6 -> 0 | G16: =Calculation!KR6 -> 0 | H16: =Calculation!KS6 -> 0 | I16: =Calculation!KT6 -> 0 | ... M16: =Calculation!KX6 -> 0 | N16: =SUM(B16:M16) -> 0
A17: Grid Usage After Solar | B17: =Calculation!KM7 -> 0 | C17: =Calculation!KN7 -> 0 | D17: =Calculation!KO7 -> 0 | E17: =Calculation!KP7 -> 0 | F17: =Calculation!KQ7 -> 0 | G17: =Calculation!KR7 -> 0 | H17: =Calculation!KS7 -> 0 | I17: =Calculation!KT7 -> 0 | ... M17: =Calculation!KX7 -> 0 | N17: =SUM(B17:M17) -> 0
A18: Solar Being Exported to Grid With Battery | B18: =Calculation!KM8 -> 0 | C18: =Calculation!KN8 -> 0 | D18: =Calculation!KO8 -> 0 | E18: =Calculation!KP8 -> 0 | F18: =Calculation!KQ8 -> 0 | G18: =Calculation!KR8 -> 0 | H18: =Calculation!KS8 -> 0 | I18: =Calculation!KT8 -> 0 | ... M18: =Calculation!KX8 -> 0 | N18: =SUM(B18:M18) -> 0
A19: Solar Being Used by Home with Battery | B19: =Calculation!KM9 -> 0 | C19: =Calculation!KN9 -> 0 | D19: =Calculation!KO9 -> 0 | E19: =Calculation!KP9 -> 0 | F19: =Calculation!KQ9 -> 0 | G19: =Calculation!KR9 -> 0 | H19: =Calculation!KS9 -> 0 | I19: =Calculation!KT9 -> 0 | ... M19: =Calculation!KX9 -> 0 | N19: =SUM(B19:M19) -> 0
A20: Grid Usage After Solar and Battery | B20: =Calculation!KM10 -> 0 | C20: =Calculation!KN10 -> 0 | D20: =Calculation!KO10 -> 0 | E20: =Calculation!KP10 -> 0 | F20: =Calculation!KQ10 -> 0 | G20: =Calculation!KR10 -> 0 | H20: =Calculation!KS10 -> 0 | I20: =Calculation!KT10 -> 0 | ... M20: =Calculation!KX10 -> 0 | N20: =SUM(B20:M20) -> 0
A21: YOUR PREDICTED SYSTEM PERFORMANCE
A22: The Assumptions we have made are based on… | F22: Environmental Impact… | J22: Address and Climate Data…
A23: Predicted System Output | C23: Assumed Annual Inflation | D23: Assumed On-Site Energy Consumption | F23: CO² Savings | J23: Project Reference | L23: Postcode | M23: Irradience Zone | N23: Roof Pitch
A24: ='Usage and Savings'!B7 -> 0 kWh/annum | C24: ='Usage and Savings'!C7 -> 0.03 | D24: =Calculation!KZ9 -> #DIV/0! | F24: ='Usage and Savings'!E7 -> 0.517kg saved per PV kWh | J24: ='Usage and Savings'!F7 -> 44059 | L24: ='Usage and Savings'!G7 | M24: ='Usage and Savings'!H7 -> 10 | N24: ='Usage and Savings'!I7 -> 30⁰
A25: Our Proposal Installation Cost | C25: Assumed Energy Unit Cost | D25: Assumed Annual Energy Inflation | F25: CO² Savings Over 20 Years | J25: Address | M25: Irradiation Level | N25: Degree's From South
A26: =A3 -> 4077.6146 | C26: ='Usage and Savings'!C9 | D26: ='Usage and Savings'!D9 -> 0.04 | F26: ='Usage and Savings'!E9 -> 0 tonnes | J26: ='Usage and Savings'!F9 -> , , | M26: ='Usage and Savings'!H9 | N26: ='Usage and Savings'!I9 -> 0⁰
A27: YOUR PREDICTED SYSTEM PERFORMANCE 20 YEAR OUTLOOK
A28: Year | B28: Estimated Yearly Energy (kWh) | C28: Predicted Unit Cost Plus Inflation | D28: Predicted Annual Bills before Installation of Solar and Storage | F28: Estimated Generation (kWh) Of Solar System | G28: Collector Efficiency of Solar System | H28: Electricity Used on Site (kWh) from Solar & Storage | I28: Saving from Energy Used From Solar Consumed following Solar & Storage | K28: Predicted Annual Bills After Installation of Solar | L28: Return On Investment based on Savings from Solar and Storage System | N28: Accumulative Total
A29: 1 | B29: ='Usage and Savings'!C13 -> kWh | C29: ='Usage and Savings'!D13 | D29: ='Usage and Savings'!E13 -> 0 | F29: ='Usage and Savings'!F13 -> 0 | G29: ='Usage and Savings'!G13 -> 1 | H29: ='Usage and Savings'!H13 -> 0 | I29: ='Usage and Savings'!I13 -> 0 | K29: ='Usage and Savings'!J13 -> 0 | L29: ='Usage and Savings'!K13 -> -4077.6146 | N29: ='Usage and Savings'!L13 -> 0
A30: 2 | B30: ='Usage and Savings'!C14 -> kWh | C30: ='Usage and Savings'!D14 -> 0 | D30: ='Usage and Savings'!E14 -> 0 | F30: ='Usage and Savings'!F14 -> 0 | G30: ='Usage and Savings'!G14 -> 0.995 | H30: ='Usage and Savings'!H14 -> 0 | I30: ='Usage and Savings'!I14 -> 0 | K30: ='Usage and Savings'!J14 -> 0 | L30: ='Usage and Savings'!K14 -> -4077.6146 | N30: ='Usage and Savings'!L14 -> 0
A31: 3 | B31: ='Usage and Savings'!C15 -> kWh | C31: ='Usage and Savings'!D15 -> 0 | D31: ='Usage and Savings'!E15 -> 0 | F31: ='Usage and Savings'!F15 -> 0 | G31: ='Usage and Savings'!G15 -> 0.99 | H31: ='Usage and Savings'!H15 -> 0 | I31: ='Usage and Savings'!I15 -> 0 | K31: ='Usage and Savings'!J15 -> 0 | L31: ='Usage and Savings'!K15 -> -4077.6146 | N31: ='Usage and Savings'!L15 -> 0
A32: 4 | B32: ='Usage and Savings'!C16 -> kWh | C32: ='Usage and Savings'!D16 -> 0 | D32: ='Usage and Savings'!E16 -> 0 | F32: ='Usage and Savings'!F16 -> 0 | G32: ='Usage and Savings'!G16 -> 0.985 | H32: ='Usage and Savings'!H16 -> 0 | I32: ='Usage and Savings'!I16 -> 0 | K32: ='Usage and Savings'!J16 -> 0 | L32: ='Usage and Savings'!K16 -> -4077.6146 | N32: ='Usage and Savings'!L16 -> 0
A33: 5 | B33: ='Usage and Savings'!C17 -> kWh | C33: ='Usage and Savings'!D17 -> 0 | D33: ='Usage and Savings'!E17 -> 0 | F33: ='Usage and Savings'!F17 -> 0 | G33: ='Usage and Savings'!G17 -> 0.98 | H33: ='Usage and Savings'!H17 -> 0 | I33: ='Usage and Savings'!I17 -> 0 | K33: ='Usage and Savings'!J17 -> 0 | L33: ='Usage and Savings'!K17 -> -4077.6146 | N33: ='Usage and Savings'!L17 -> 0
A34: 6 | B34: ='Usage and Savings'!C18 -> kWh | C34: ='Usage and Savings'!D18 -> 0 | D34: ='Usage and Savings'!E18 -> 0 | F34: ='Usage and Savings'!F18 -> 0 | G34: ='Usage and Savings'!G18 -> 0.975 | H34: ='Usage and Savings'!H18 -> 0 | I34: ='Usage and Savings'!I18 -> 0 | K34: ='Usage and Savings'!J18 -> 0 | L34: ='Usage and Savings'!K18 -> -4077.6146 | N34: ='Usage and Savings'!L18 -> 0
A35: 7 | B35: ='Usage and Savings'!C19 -> kWh | C35: ='Usage and Savings'!D19 -> 0 | D35: ='Usage and Savings'!E19 -> 0 | F35: ='Usage and Savings'!F19 -> 0 | G35: ='Usage and Savings'!G19 -> 0.97 | H35: ='Usage and Savings'!H19 -> 0 | I35: ='Usage and Savings'!I19 -> 0 | K35: ='Usage and Savings'!J19 -> 0 | L35: ='Usage and Savings'!K19 -> -4077.6146 | N35: ='Usage and Savings'!L19 -> 0
A36: 8 | B36: ='Usage and Savings'!C20 -> kWh | C36: ='Usage and Savings'!D20 -> 0 | D36: ='Usage and Savings'!E20 -> 0 | F36: ='Usage and Savings'!F20 -> 0 | G36: ='Usage and Savings'!G20 -> 0.965 | H36: ='Usage and Savings'!H20 -> 0 | I36: ='Usage and Savings'!I20 -> 0 | K36: ='Usage and Savings'!J20 -> 0 | L36: ='Usage and Savings'!K20 -> -4077.6146 | N36: ='Usage and Savings'!L20 -> 0
A37: 9 | B37: ='Usage and Savings'!C21 -> kWh | C37: ='Usage and Savings'!D21 -> 0 | D37: ='Usage and Savings'!E21 -> 0 | F37: ='Usage and Savings'!F21 -> 0 | G37: ='Usage and Savings'!G21 -> 0.96 | H37: ='Usage and Savings'!H21 -> 0 | I37: ='Usage and Savings'!I21 -> 0 | K37: ='Usage and Savings'!J21 -> 0 | L37: ='Usage and Savings'!K21 -> -4077.6146 | N37: ='Usage and Savings'!L21 -> 0
A38: 10 | B38: ='Usage and Savings'!C22 -> kWh | C38: ='Usage and Savings'!D22 -> 0 | D38: ='Usage and Savings'!E22 -> 0 | F38: ='Usage and Savings'!F22 -> 0 | G38: ='Usage and Savings'!G22 -> 0.955 | H38: ='Usage and Savings'!H22 -> 0 | I38: ='Usage and Savings'!I22 -> 0 | K38: ='Usage and Savings'!J22 -> 0 | L38: ='Usage and Savings'!K22 -> -4077.6146 | N38: ='Usage and Savings'!L22 -> 0
A39: 11 | B39: ='Usage and Savings'!C23 -> kWh | C39: ='Usage and Savings'!D23 -> 0 | D39: ='Usage and Savings'!E23 -> 0 | F39: ='Usage and Savings'!F23 -> 0 | G39: ='Usage and Savings'!G23 -> 0.95 | H39: ='Usage and Savings'!H23 -> 0 | I39: ='Usage and Savings'!I23 -> 0 | K39: ='Usage and Savings'!J23 -> 0 | L39: ='Usage and Savings'!K23 -> -4077.6146 | N39: ='Usage and Savings'!L23 -> 0
A40: 12 | B40: ='Usage and Savings'!C24 -> kWh | C40: ='Usage and Savings'!D24 -> 0 | D40: ='Usage and Savings'!E24 -> 0 | F40: ='Usage and Savings'!F24 -> 0 | G40: ='Usage and Savings'!G24 -> 0.945 | H40: ='Usage and Savings'!H24 -> 0 | I40: ='Usage and Savings'!I24 -> 0 | K40: ='Usage and Savings'!J24 -> 0 | L40: ='Usage and Savings'!K24 -> -4077.6146 | N40: ='Usage and Savings'!L24 -> 0
... A48: 20 | B48: ='Usage and Savings'!C32 -> kWh | C48: ='Usage and Savings'!D32 -> 0 | D48: ='Usage and Savings'!E32 -> 0 | F48: ='Usage and Savings'!F32 -> 0 | G48: ='Usage and Savings'!G32 -> 0.905 | H48: ='Usage and Savings'!H32 -> 0 | I48: ='Usage and Savings'!I32 -> 0 | K48: ='Usage and Savings'!J32 -> 0 | L48: ='Usage and Savings'!K32 -> -4077.6146 | N48: ='Usage and Savings'!L32 -> 0
A50: Order Acceptance Form
A51: Description of Goods and Services we will provide:
A52: Green Energy Together recommends the following price proposal based on the information reviewed and the suitability of your property.
A53: Quote Reference: | C53: =Input!D3 -> 44059
A54: Item | C54: Description
A55: 1 | C55: ="Suplly,Installation, Commissioning and Handover of Solar Photovoltaic System ( "&H8&" kWdc )" -> Suplly,Installation, Commissioning and Handover of Solar Photovoltaic System ( 2.7 kWdc )
A56: 2 | C56: ="Supply, Installation, Commissioning and Handover of Battery Storage System ( "&Input!D21&" kWdc )" -> Supply, Installation, Commissioning and Handover of Battery Storage System ( 0 kWdc )
A57: Item | C57: Additional Items
A58: 3 | C58: =Input!D34 -> None
A59: 4 | C59: =Input!D35 -> None
A60: 5 | C60: =Input!D36 -> None
A61: 6 | C61: =Input!D37 -> None
A62: VAT | B62: 0.05 | C62: =Costing!K37 -> 194.17212
A63: Total Price
A64: =Costing!L37 -> 4077.6146
A65: I can confirm that the product I am signing for has been explained to me and I understand that this will require the installation of Solar Panels onto my property and access to my property to carry out a suitability survey prior to formal acceptance of a contract for the works is required. I confirm that I am aware that I have 14 days to cancel this agreement if I decide I no longer wish to proceed with the products and services being offered. I can confirm that I own the property which the products and services are being quoted for or I have permission by the owner of the property to accept these products and services.
A66: Comments: | C66: 340W Canadian Solar Modules, Rosemary Roof Type, Sofarsolar 6KW Hybrid Inverter with 7.5KW DC Coupled Battery. Grid Application included.
A67: Address: | C67: =CONCATENATE(Input!D26, " ", Input!D27, ", ", Input!D28, ", ", Input!D29) -> , ,
A68: Name: | C68: =CONCATENATE(Input!D23, " ",Input!D24, " ", Input!D25)
A69: Signature:
A70: Date: | C70: =TODAY() -> 44059

Sheet Online Sales Pack
A1: Your Quotation (Inclusive of VAT)
A2: =Costing!L37 -> 4077.6146
A3: PAYMENT TERMS
A4: Payment 1 @ 60% 14 Days prior to Installation Date | H4: =A2*60% -> 2446.5688
A5: Payment 2 @ 40% 7 days post Completion of Installation | H5: =A2*40% -> 1631.0458
A6: Estimated Years to Payback | H6: ='Usage and Savings'!N12 -> 20
A7: System Size (kWdc) | H7: =Costing!C1 -> 2.7
A8: Quantity of Panels | H8: =Input!D9&" Panels" -> 10 Panels
A9: Battery Storage Size | H9: =Input!D21&" kWdc" -> 0 kWdc
A10: BREAKDOWN OF PERFORMANCE
A11: Description | B11: Jan | C11: Feb | D11: Mar | E11: Apr | F11: May | G11: Jun | H11: Jul | I11: Aug | J11: Sep | K11: Oct | L11: Nov | M11: Dec | N11: Total
A12: Grid Usage | B12: =Calculation!KM3 -> 0 | C12: =Calculation!KN3 -> 0 | D12: =Calculation!KO3 -> 0 | E12: =Calculation!KP3 -> 0 | F12: =Calculation!KQ3 -> 0 | G12: =Calculation!KR3 -> 0 | H12: =Calculation!KS3 -> 0 | I12: =Calculation!KT3 -> 0 | ... M12: =Calculation!KX3 -> 0 | N12: =SUM(B12:M12) -> 0
A13: Solar Generation | B13: =Calculation!KM4 -> 0 | C13: =Calculation!KN4 -> 0 | D13: =Calculation!KO4 -> 0 | E13: =Calculation!KP4 -> 0 | F13: =Calculation!KQ4 -> 0 | G13: =Calculation!KR4 -> 0 | H13: =Calculation!KS4 -> 0 | I13: =Calculation!KT4 -> 0 | ... M13: =Calculation!KX4 -> 0 | N13: =SUM(B13:M13) -> 0
A14: Solar being Exported to Grid without Battery | B14: =Calculation!KM5 -> 0 | C14: =Calculation!KN5 -> 0 | D14: =Calculation!KO5 -> 0 | E14: =Calculation!KP5 -> 0 | F14: =Calculation!KQ5 -> 0 | G14: =Calculation!KR5 -> 0 | H14: =Calculation!KS5 -> 0 | I14: =Calculation!KT5 -> 0 | ... M14: =Calculation!KX5 -> 0 | N14: =SUM(B14:M14) -> 0
A15: Solar Being Used by Home without Battery | B15: =Calculation!KM6 -> 0 | C15: =Calculation!KN6 -> 0 | D15: =Calculation!KO6 -> 0 | E15: =Calculation!KP6 -> 0 | F15: =Calculation!KQ6 -> 0 | G15: =Calculation!KR6 -> 0 | H15: =Calculation!KS6 -> 0 | I15: =Calculation!KT6 -> 0 | ... M15: =Calculation!KX6 -> 0 | N15: =SUM(B15:M15) -> 0
A16: Grid Usage After Solar | B16: =Calculation!KM7 -> 0 | C16: =Calculation!KN7 -> 0 | D16: =Calculation!KO7 -> 0 | E16: =Calculation!KP7 -> 0 | F16: =Calculation!KQ7 -> 0 | G16: =Calculation!KR7 -> 0 | H16: =Calculation!KS7 -> 0 | I16: =Calculation!KT7 -> 0 | ... M16: =Calculation!KX7 -> 0 | N16: =SUM(B16:M16) -> 0
A17: Solar Being Exported to Grid With Battery | B17: =Calculation!KM8 -> 0 | C17: =Calculation!KN8 -> 0 | D17: =Calculation!KO8 -> 0 | E17: =Calculation!KP8 -> 0 | F17: =Calculation!KQ8 -> 0 | G17: =Calculation!KR8 -> 0 | H17: =Calculation!KS8 -> 0 | I17: =Calculation!KT8 -> 0 | ... M17: =Calculation!KX8 -> 0 | N17: =SUM(B17:M17) -> 0
A18: Solar Being Used by Home with Battery | B18: =Calculation!KM9 -> 0 | C18: =Calculation!KN9 -> 0 | D18: =Calculation!KO9 -> 0 | E18: =Calculation!KP9 -> 0 | F18: =Calculation!KQ9 -> 0 | G18: =Calculation!KR9 -> 0 | H18: =Calculation!KS9 -> 0 | I18: =Calculation!KT9 -> 0 | ... M18: =Calculation!KX9 -> 0 | N18: =SUM(B18:M18) -> 0
A19: Grid Usage After Solar and Battery | B19: =Calculation!KM10 -> 0 | C19: =Calculation!KN10 -> 0 | D19: =Calculation!KO10 -> 0 | E19: =Calculation!KP10 -> 0 | F19: =Calculation!KQ10 -> 0 | G19: =Calculation!KR10 -> 0 | H19: =Calculation!KS10 -> 0 | I19: =Calculation!KT10 -> 0 | ... M19: =Calculation!KX10 -> 0 | N19: =SUM(B19:M19) -> 0
A20: YOUR PREDICTED SYSTEM PERFORMANCE
A21: The Assumptions we have made are based on… | F21: Environmental Impact… | J21: Address and Climate Data…
A22: Predicted System Output | C22: Assumed Annual Inflation | D22: Assumed On-Site Energy Consumption | F22: CO² Savings | J22: Project Reference | L22: Postcode | M22: Irradience Zone | N22: Roof Pitch
A23: ='Usage and Savings'!B7 -> 0 kWh/annum | C23: ='Usage and Savings'!C7 -> 0.03 | D23: =Calculation!KZ9 -> #DIV/0! | F23: ='Usage and Savings'!E7 -> 0.517kg saved per PV kWh | J23: ='Usage and Savings'!F7 -> 44059 | L23: ='Usage and Savings'!G7 | M23: ='Usage and Savings'!H7 -> 10 | N23: ='Usage and Savings'!I7 -> 30⁰
A24: Our Proposal Installation Cost | C24: Assumed Energy Unit Cost | D24: Assumed Annual Energy Inflation | F24: CO² Savings Over 20 Years | J24: Address | M24: Irradiation Level | N24: Degree's From South
A25: =A2 -> 4077.6146 | C25: ='Usage and Savings'!C9 | D25: ='Usage and Savings'!D9 -> 0.04 | F25: ='Usage and Savings'!E9 -> 0 tonnes | J25: ='Usage and Savings'!F9 -> , , | M25: ='Usage and Savings'!H9 | N25: ='Usage and Savings'!I9 -> 0⁰
A26: YOUR PREDICTED SYSTEM PERFORMANCE 20 YEAR OUTLOOK
A27: Year | B27: Estimated Yearly Energy (kWh) | C27: Predicted Unit Cost Plus Inflation | D27: Predicted Annual Bills before Installation of Solar and Storage | F27: Estimated Generation (kWh) Of Solar System | G27: Collector Efficiency of Solar System | H27: Electricity Used on Site (kWh) from Solar & Storage | I27: Saving from Energy Used From Solar Consumed following Solar & Storage | K27: Predicted Annual Bills After Installation of Solar | L27: Return On Investment based on Savings from Solar and Storage System | N27: Accumulative Total
A28: 1 | B28: ='Usage and Savings'!C13 -> kWh | C28: ='Usage and Savings'!D13 | D28: ='Usage and Savings'!E13 -> 0 | F28: ='Usage and Savings'!F13 -> 0 | G28: ='Usage and Savings'!G13 -> 1 | H28: ='Usage and Savings'!H13 -> 0 | I28: ='Usage and Savings'!I13 -> 0 | K28: ='Usage and Savings'!J13 -> 0 | L28: ='Usage and Savings'!K13 -> -4077.6146 | N28: ='Usage and Savings'!L13 -> 0
A29: 2 | B29: ='Usage and Savings'!C14 -> kWh | C29: ='Usage and Savings'!D14 -> 0 | D29: ='Usage and Savings'!E14 -> 0 | F29: ='Usage and Savings'!F14 -> 0 | G29: ='Usage and Savings'!G14 -> 0.995 | H29: ='Usage and Savings'!H14 -> 0 | I29: ='Usage and Savings'!I14 -> 0 | K29: ='Usage and Savings'!J14 -> 0 | L29: ='Usage and Savings'!K14 -> -4077.6146 | N29: ='Usage and Savings'!L14 -> 0
A30: 3 | B30: ='Usage and Savings'!C15 -> kWh | C30: ='Usage and Savings'!D15 -> 0 | D30: ='Usage and Savings'!E15 -> 0 | F30: ='Usage and Savings'!F15 -> 0 | G30: ='Usage and Savings'!G15 -> 0.99 | H30: ='Usage and Savings'!H15 -> 0 | I30: ='Usage and Savings'!I15 -> 0 | K30: ='Usage and Savings'!J15 -> 0 | L30: ='Usage and Savings'!K15 -> -4077.6146 | N30: ='Usage and Savings'!L15 -> 0
A31: 4 | B31: ='Usage and Savings'!C16 -> kWh | C31: ='Usage and Savings'!D16 -> 0 | D31: ='Usage and Savings'!E16 -> 0 | F31: ='Usage and Savings'!F16 -> 0 | G31: ='Usage and Savings'!G16 -> 0.985 | H31: ='Usage and Savings'!H16 -> 0 | I31: ='Usage and Savings'!I16 -> 0 | K31: ='Usage and Savings'!J16 -> 0 | L31: ='Usage and Savings'!K16 -> -4077.6146 | N31: ='Usage and Savings'!L16 -> 0
A32: 5 | B32: ='Usage and Savings'!C17 -> kWh | C32: ='Usage and Savings'!D17 -> 0 | D32: ='Usage and Savings'!E17 -> 0 | F32: ='Usage and Savings'!F17 -> 0 | G32: ='Usage and Savings'!G17 -> 0.98 | H32: ='Usage and Savings'!H17 -> 0 | I32: ='Usage and Savings'!I17 -> 0 | K32: ='Usage and Savings'!J17 -> 0 | L32: ='Usage and Savings'!K17 -> -4077.6146 | N32: ='Usage and Savings'!L17 -> 0
A33: 6 | B33: ='Usage and Savings'!C18 -> kWh | C33: ='Usage and Savings'!D18 -> 0 | D33: ='Usage and Savings'!E18 -> 0 | F33: ='Usage and Savings'!F18 -> 0 | G33: ='Usage and Savings'!G18 -> 0.975 | H33: ='Usage and Savings'!H18 -> 0 | I33: ='Usage and Savings'!I18 -> 0 | K33: ='Usage and Savings'!J18 -> 0 | L33: ='Usage and Savings'!K18 -> -4077.6146 | N33: ='Usage and Savings'!L18 -> 0
A34: 7 | B34: ='Usage and Savings'!C19 -> kWh | C34: ='Usage and Savings'!D19 -> 0 | D34: ='Usage and Savings'!E19 -> 0 | F34: ='Usage and Savings'!F19 -> 0 | G34: ='Usage and Savings'!G19 -> 0.97 | H34: ='Usage and Savings'!H19 -> 0 | I34: ='Usage and Savings'!I19 -> 0 | K34: ='Usage and Savings'!J19 -> 0 | L34: ='Usage and Savings'!K19 -> -4077.6146 | N34: ='Usage and Savings'!L19 -> 0
A35: 8 | B35: ='Usage and Savings'!C20 -> kWh | C35: ='Usage and Savings'!D20 -> 0 | D35: ='Usage and Savings'!E20 -> 0 | F35: ='Usage and Savings'!F20 -> 0 | G35: ='Usage and Savings'!G20 -> 0.965 | H35: ='Usage and Savings'!H20 -> 0 | I35: ='Usage and Savings'!I20 -> 0 | K35: ='Usage and Savings'!J20 -> 0 | L35: ='Usage and Savings'!K20 -> -4077.6146 | N35: ='Usage and Savings'!L20 -> 0
A36: 9 | B36: ='Usage and Savings'!C21 -> kWh | C36: ='Usage and Savings'!D21 -> 0 | D36: ='Usage and Savings'!E21 -> 0 | F36: ='Usage and Savings'!F21 -> 0 | G36: ='Usage and Savings'!G21 -> 0.96 | H36: ='Usage and Savings'!H21 -> 0 | I36: ='Usage and Savings'!I21 -> 0 | K36: ='Usage and Savings'!J21 -> 0 | L36: ='Usage and Savings'!K21 -> -4077.6146 | N36: ='Usage and Savings'!L21 -> 0
A37: 10 | B37: ='Usage and Savings'!C22 -> kWh | C37: ='Usage and Savings'!D22 -> 0 | D37: ='Usage and Savings'!E22 -> 0 | F37: ='Usage and Savings'!F22 -> 0 | G37: ='Usage and Savings'!G22 -> 0.955 | H37: ='Usage and Savings'!H22 -> 0 | I37: ='Usage and Savings'!I22 -> 0 | K37: ='Usage and Savings'!J22 -> 0 | L37: ='Usage and Savings'!K22 -> -4077.6146 | N37: ='Usage and Savings'!L22 -> 0
A38: 11 | B38: ='Usage and Savings'!C23 -> kWh | C38: ='Usage and Savings'!D23 -> 0 | D38: ='Usage and Savings'!E23 -> 0 | F38: ='Usage and Savings'!F23 -> 0 | G38: ='Usage and Savings'!G23 -> 0.95 | H38: ='Usage and Savings'!H23 -> 0 | I38: ='Usage and Savings'!I23 -> 0 | K38: ='Usage and Savings'!J23 -> 0 | L38: ='Usage and Savings'!K23 -> -4077.6146 | N38: ='Usage and Savings'!L23 -> 0
A39: 12 | B39: ='Usage and Savings'!C24 -> kWh | C39: ='Usage and Savings'!D24 -> 0 | D39: ='Usage and Savings'!E24 -> 0 | F39: ='Usage and Savings'!F24 -> 0 | G39: ='Usage and Savings'!G24 -> 0.945 | H39: ='Usage and Savings'!H24 -> 0 | I39: ='Usage and Savings'!I24 -> 0 | K39: ='Usage and Savings'!J24 -> 0 | L39: ='Usage and Savings'!K24 -> -4077.6146 | N39: ='Usage and Savings'!L24 -> 0
... A47: 20 | B47: ='Usage and Savings'!C32 -> kWh | C47: ='Usage and Savings'!D32 -> 0 | D47: ='Usage and Savings'!E32 -> 0 | F47: ='Usage and Savings'!F32 -> 0 | G47: ='Usage and Savings'!G32 -> 0.905 | H47: ='Usage and Savings'!H32 -> 0 | I47: ='Usage and Savings'!I32 -> 0 | K47: ='Usage and Savings'!J32 -> 0 | L47: ='Usage and Savings'!K32 -> -4077.6146 | N47: ='Usage and Savings'!L32 -> 0
A48: Order Acceptance Form
A49: Description of Goods and Services we will provide:
A50: Solarplicity Smart Systems Ltd. t/a Green Energy Together recommends the following price proposal based on the information reviewed and the suitability of your property.
A51: Quote Reference: | C51: =Input!D3 -> 44059
A52: Item | C52: Description
A53: 1 | C53: ="Suplly,Installation, Commissioning and Handover of Solar Photovoltaic System ( "&H7&" kWdc )" -> Suplly,Installation, Commissioning and Handover of Solar Photovoltaic System ( 2.7 kWdc )
A54: 2 | C54: ="Supply, Installation, Commissioning and Handover of Battery Storage System ( "&Input!D21&" kWdc )" -> Supply, Installation, Commissioning and Handover of Battery Storage System ( 0 kWdc )
A55: Item | C55: Additional Items
A56: 3 | C56: =Input!D34 -> None
A57: 4 | C57: =Input!D35 -> None
A58: 5 | C58: =Input!D36 -> None
A59: 6 | C59: =Input!D37 -> None
A60: VAT | B60: 0.05 | C60: =Costing!K37 -> 194.17212
A61: Total Price
A62: =Costing!L37 -> 4077.6146
A63: ='Your Proposal'!A67:B67 -> Address: | C63: ='Your Proposal'!C67:N67 -> , ,
A64: ='Your Proposal'!A68:B68 -> Name: | C64: ='Your Proposal'!C68:N68

Sheet Costing
A1: Solar kW dc | C1: =Input!D12 -> 2.7 | D1: Roof Type | E1: =Input!D18 -> In Roof | F1: Scaffold Required | G1: =Input!D20 -> No | H1: Battery Size | I1: =Input!D21 -> 0 | J1: Margin | K1: =Input!D32 -> 0.325 | L1: VAT | M1: =Input!D33 -> 0.05 | N1: Discount | O1: =Input!D31
B2: Panel Quantity | C2: =Input!D9 -> 10 | D2: Panel Type | E2: =Input!D19 -> Blue | M2: =H27/($C$1*1000) -> 1.438312
A3: DO NOT EDIT THIS SECTION | B3: Description | C3: Type | D3: Cost Per KW | E3: Cost | F3: Cost Applied | G3: Margin | H3: Total Sale | I3: Pence Per W | J3: VAT | K3: Total Sale Inc VAT | M3: =K27/($C$1*1000) -> 1.5102276
B4: Concrete Roof | C4: Concrete | D4: 75.59 | E4: =D4*$C$1 -> 204.093 | F4: =SUMIFS(E4,C4,$E$1) -> 0 | G4: =F4*$K$1 -> 0 | H4: =SUM(F4:G4) -> 0 | I4: =H4/($C$1*1000) -> 0 | J4: =H4*$M$1 -> 0 | K4: =J4+H4 -> 0 | M4: =F27/($C$1*1000) -> 1.0855185
B5: Slate Roof | C5: Slate | D5: 90.59 | E5: =D5*$C$1 -> 244.593 | F5: =SUMIFS(E5,C5,$E$1) -> 0 | G5: =F5*$K$1 -> 0 | H5: =SUM(F5:G5) -> 0 | I5: =H5/($C$1*1000) -> 0 | J5: =H5*$M$1 -> 0 | K5: =J5+H5 -> 0
B6: Rosemary Roof | C6: Rosemary | D6: 90.59 | E6: =D6*$C$1 -> 244.593 | F6: =SUMIFS(E6,C6,$E$1) -> 0 | G6: =F6*$K$1 -> 0 | H6: =SUM(F6:G6) -> 0 | I6: =H6/($C$1*1000) -> 0 | J6: =H6*$M$1 -> 0 | K6: =J6+H6 -> 0
B7: Flat Roof | C7: Flat Roof | D7: 125 | E7: =D7*$C$1 -> 337.5 | F7: =SUMIFS(E7,C7,$E$1) -> 0 | G7: =F7*$K$1 -> 0 | H7: =SUM(F7:G7) -> 0 | I7: =H7/($C$1*1000) -> 0 | J7: =H7*$M$1 -> 0 | K7: =J7+H7 -> 0
B8: Ground Mounted | C8: Ground Mounted | D8: 130 | E8: =D8*$C$1 -> 351 | F8: =SUMIFS(E8,C8,$E$1) -> 0 | G8: =F8*$K$1 -> 0 | H8: =SUM(F8:G8) -> 0 | I8: =H8/($C$1*1000) -> 0 | J8: =H8*$M$1 -> 0 | K8: =J8+H8 -> 0
B9: In Roof | C9: In Roof | D9: 60 | E9: =D9*C2 -> 600 | F9: =SUMIFS(E9,C9,$E$1) -> 600 | G9: =F9*$K$1 -> 195 | H9: =SUM(F9:G9) -> 795 | I9: =H9/($C$1*1000) -> 0.29444444 | J9: =H9*$M$1 -> 39.75 | K9: =J9+H9 -> 834.75
B10: Dekra Roof | C10: Dekra | D10: 80.59 | E10: =D10*$C$1 -> 217.593 | F10: =SUMIFS(E10,C10,$E$1) -> 0 | G10: =F10*$K$1 -> 0 | H10: =SUM(F10:G10) -> 0 | I10: =H10/($C$1*1000) -> 0 | J10: =H10*$M$1 -> 0 | K10: =J10+H10 -> 0
B11: Ancillary Materials | C11: Per KW | D11: 40 | E11: =D11*$C$1 -> 108 | F11: =E11 -> 108 | G11: =F11*$K$1 -> 35.1 | H11: =SUM(F11:G11) -> 143.1 | I11: =H11/($C$1*1000) -> 0.053 | J11: =H11*$M$1 -> 7.155 | K11: =J11+H11 -> 150.255 | M11: Module Cost
B12: Solar Modules Blue | C12: Blue | D12: 210 | E12: =D12*$C$1 -> 567 | F12: =SUMIFS(E12,C12,$E$2) -> 567 | G12: =F12*$K$1 -> 184.275 | H12: =SUM(F12:G12) -> 751.275 | I12: =H12/($C$1*1000) -> 0.27825 | J12: =H12*$M$1 -> 37.56375 | K12: =J12+H12 -> 788.83875 | M12: =E12/C$2 -> 56.7
B13: Solar Modules Black | C13: Black | D13: 260 | E13: =D13*$C$1 -> 702 | F13: =SUMIFS(E13,C13,$E$2) -> 0 | G13: =F13*$K$1 -> 0 | H13: =SUM(F13:G13) -> 0 | I13: =H13/($C$1*1000) -> 0 | J13: =H13*$M$1 -> 0 | K13: =J13+H13 -> 0 | M13: =E13/C$2 -> 70.2
B14: Inverter | C14: Per KW | D14: 92 | E14: =D14*$C$1 -> 248.4 | F14: =E14 -> 248.4 | G14: =F14*$K$1 -> 80.73 | H14: =SUM(F14:G14) -> 329.13 | I14: =H14/($C$1*1000) -> 0.1219 | J14: =H14*$M$1 -> 16.4565 | K14: =J14+H14 -> 345.5865
B15: Metering Equipment | C15: Per Job | D15: N/A | E15: 120.5 | F15: =E15 -> 120.5 | G15: =F15*$K$1 -> 39.1625 | H15: =SUM(F15:G15) -> 159.6625 | I15: =H15/($C$1*1000) -> 0.059134259 | J15: =H15*$M$1 -> 7.983125 | K15: =J15+H15 -> 167.64562
B16: Battery Equipment 3KW | C16: 2.5 | D16: N/A | E16: =480+370 -> 850 | F16: =SUMIFS(E16,C16,$I$1) -> 0 | G16: =F16*$K$1 -> 0 | H16: =SUM(F16:G16) -> 0 | I16: =H16/($C$1*1000) -> 0 | J16: =H16*$M$1 -> 0 | K16: =J16+H16 -> 0
B17: Battery Equipment 5KW | C17: 5 | D17: N/A | E17: =960+370 -> 1330 | F17: =SUMIFS(E17,C17,$I$1) -> 0 | G17: =F17*$K$1 -> 0 | H17: =SUM(F17:G17) -> 0 | I17: =H17/($C$1*1000) -> 0 | J17: =H17*$M$1 -> 0 | K17: =J17+H17 -> 0
B18: Battery Equipment 7.5KW | C18: 7.5 | D18: N/A | E18: =1480+370 -> 1850 | F18: =SUMIFS(E18,C18,$I$1) -> 0 | G18: =F18*$K$1 -> 0 | H18: =SUM(F18:G18) -> 0 | I18: =H18/($C$1*1000) -> 0 | J18: =H18*$M$1 -> 0 | K18: =J18+H18 -> 0
B19: Battery Equipment 10KW | C19: 10 | D19: N/A | E19: =1960+370 -> 2330 | F19: =SUMIFS(E19,C19,$I$1) -> 0 | G19: =F19*$K$1 -> 0 | H19: =SUM(F19:G19) -> 0 | I19: =H19/($C$1*1000) -> 0 | J19: =H19*$M$1 -> 0 | K19: =J19+H19 -> 0
B20: Labour | C20: Per KW | D20: 160 | E20: =D20*$C$1 -> 432 | F20: =E20 -> 432 | G20: =F20*$K$1 -> 140.4 | H20: =SUM(F20:G20) -> 572.4 | I20: =H20/($C$1*1000) -> 0.212 | J20: =H20*$M$1 -> 28.62 | K20: =J20+H20 -> 601.02
B21: Scaffold | C21: Per Job | D21: N/A | E21: 500 | F21: =SUMIFS(E21,G1,"Yes") -> 0 | G21: =F21*$K$1 -> 0 | H21: =SUM(F21:G21) -> 0 | I21: =H21/($C$1*1000) -> 0 | J21: =H21*$M$1 -> 0 | K21: =J21+H21 -> 0
B22: H&S and Project Management | C22: Per Job | D22: N/A | E22: 50 | F22: =E22 -> 50 | G22: =F22*$K$1 -> 16.25 | H22: =SUM(F22:G22) -> 66.25 | I22: =H22/($C$1*1000) -> 0.024537037 | J22: =H22*$M$1 -> 3.3125 | K22: =(J22+H22) -> 69.5625
B23: Commissioning | C23: Per Job | D23: N/A | E23: =50 -> 50 | F23: =E23 -> 50 | G23: =F23*$K$1 -> 16.25 | H23: =SUM(F23:G23) -> 66.25 | I23: =H23/($C$1*1000) -> 0.024537037 | J23: =H23*$M$1 -> 3.3125 | K23: =(J23+H23) -> 69.5625
B24: Packaging and Delivery | C24: Per Job | D24: N/A | E24: =150 -> 150 | F24: =E24 -> 150 | G24: =F24*$K$1 -> 48.75 | H24: =SUM(F24:G24) -> 198.75 | I24: =H24/($C$1*1000) -> 0.073611111 | J24: =H24*$M$1 -> 9.9375 | K24: =(J24+H24) -> 208.6875
B25: Administration / Lead Fees | C25: Per Job | D25: N/A | E25: 500 | F25: =E25 -> 500 | G25: =F25*$K$1 -> 162.5 | H25: =SUM(F25:G25) -> 662.5 | I25: =H25/($C$1*1000) -> 0.24537037 | J25: =H25*$M$1 -> 33.125 | K25: =(J25+H25) -> 695.625
B26: Registrations | C26: Per Job | D26: N/A | E26: =35+70 -> 105 | F26: =E26 -> 105 | G26: =F26*$K$1 -> 34.125 | H26: =SUM(F26:G26) -> 139.125 | I26: =H26/($C$1*1000) -> 0.051527778 | J26: =H26*$M$1 -> 6.95625 | K26: =(J26+H26) -> 146.08125
F27: =SUM(F4:F26) -> 2930.9 | G27: =SUM(G4:G26) -> 952.5425 | H27: =SUM(H4:H26) -> 3883.4425 | I27: =H27/($C$1*1000) -> 1.438312 | J27: =SUM(J4:J26) -> 194.17212 | K27: =SUM(K4:K26) -> 4077.6146
A29: ADD UPLIFT AND ADDITIONAL ITEMS IN YELLOW ONLY | B29: Additional Items | C29: Type | E29: Cost | G29: Margin | H29: Total Sale | I29: VAT Rate | K29: VAT | L29: Total Sale Inc VAT
B30: =Input!D34 -> None | C30: =VLOOKUP(B30,'Lookup Data'!A:B,2,0) -> None | E30: =VLOOKUP(B30,'Lookup Data'!A:C,3,0) -> 0 | G30: =E30*$K$1 -> 0 | H30: =G30+E30 -> 0 | I30: 0.05 | K30: =H30*I30 -> 0 | L30: =I30+H30 -> 0.05
B31: =Input!D35 -> None | C31: =VLOOKUP(B31,'Lookup Data'!A:B,2,0) -> None | E31: =VLOOKUP(B31,'Lookup Data'!A:C,3,0) -> 0 | G31: =E31*$K$1 -> 0 | H31: =G31+E31 -> 0 | I31: =VLOOKUP(B31,'Lookup Data'!A:D,4,0) -> 0 | K31: =H31*I31 -> 0 | L31: =I31+H31 -> 0
B32: =Input!D36 -> None | C32: =VLOOKUP(B32,'Lookup Data'!A:B,2,0) -> None | E32: =VLOOKUP(B32,'Lookup Data'!A:C,3,0) -> 0 | G32: =E32*$K$1 -> 0 | H32: =G32+E32 -> 0 | I32: =VLOOKUP(B32,'Lookup Data'!A:D,4,0) -> 0 | K32: =H32*I32 -> 0 | L32: =I32+H32 -> 0
B33: =Input!D37 -> None | C33: =VLOOKUP(B33,'Lookup Data'!A:B,2,0) -> None | E33: =VLOOKUP(B33,'Lookup Data'!A:C,3,0) -> 0 | G33: =E33*$K$1 -> 0 | H33: =G33+E33 -> 0 | I33: =VLOOKUP(B33,'Lookup Data'!A:D,4,0) -> 0 | K33: =H33*I33 -> 0 | L33: =I33+H33 -> 0
E34: =SUM(E30:E33) -> 0 | G34: =SUM(G30:G33) -> 0 | H34: =SUM(H30:H33) -> 0 | I34: 0 | K34: =SUM(K30:K33) -> 0 | L34: =I34+H34 -> 0
E35: Total Cost | G35: Total Margin | H35: Total Sale | K35: Total VAT | L35: Total Sale Inc VAT
E36: Places for People Fee | H36: =-Input!D31 -> 0
E37: =F27+F34 -> 2930.9 | G37: =G27+G34-G36 -> 952.5425 | H37: =H27+H34+H36 -> 3883.4425 | K37: =H37*5% -> 194.17212 | L37: =K37+H37 -> 4077.6146

Sheet Usage and Savings
B2: Predicted System Performance
B4: The Assumptions we have made are based on… | E4: Environmental Impact… | F4: Address and Climate Data…
B6: Predicted System Output | C6: Assumed Annual Inflation (RPI) | D6: Assumed On-Site Energy Consumption | E6: CO² Savings | F6: Project Reference | G6: Postcode | H6: Irradience Zone | I6: Roof Pitch
B7: =Input!D14&" "&"kWh/annum" -> 0 kWh/annum | C7: 0.03 | D7: =H13 -> 0 | E7: 0.517kg saved per PV kWh | F7: =Input!D3 -> 44059 | G7: =Input!D29 | H7: =Input!D15 -> 10 | I7: =Input!D16&Input!C16 -> 30⁰
B8: Our Proposal Installation Cost | C8: Assumed Energy Unit Cost | D8: Assumed Annual Energy Inflation | E8: CO² Savings Over 20 Years | F8: Address | H8: Irradiation Level | I8: Degrees From South
B9: ="£"&(ROUNDUP(#REF!,2))&" Inc VAT" -> #REF! | C9: =Input!D6 | D9: 0.04 | E9: =(ROUND(((SUM(F13:F32)*0.517)/1000),2)&" tonnes") -> 0 tonnes | F9: =Input!D26&Input!E25&Input!D27&", "&Input!D28&", "&Input!D29 -> , , | H9: =Input!D13 | I9: =Input!D17&Input!C17 -> 0⁰
B11: Your predicted system performance 20 year outlook
B12: Year | C12: Estimated Yearly Energy (kWh) | D12: Predicted Unit Cost Plus Inflation | E12: Predicted Annual Bills before Installation of Solar and Storage | F12: Estimated Generation (kWh) Of Solar System | G12: Collector Efficiency of Solar System | H12: Electricity Used on Site (kWh) from Solar & Storage | I12: Saving from Energy Used From Solar Consumed following Solar & Storage | J12: Predicted Annual Bills After Installation of Solar | K12: Return On Investment based on Savings from Solar and Storage System | L12: Accumulative Total | N12: =COUNTIF(K13:K32,"<0.00001") -> 20
B13: 1 | C13: =Input!D5&" kWh" -> kWh | D13: =Input!D6 | E13: =(D13*Input!$D$5)+(365*Input!$D$7) -> 0 | F13: =Input!$D$14*G13 -> 0 | G13: 1 | H13: =Calculation!$KY$9 -> 0 | I13: =H13*D13 -> 0 | J13: =E13-I13 -> 0 | K13: =-Costing!L37+I13 -> -4077.6146 | L13: =I13 -> 0
B14: 2 | C14: =C13 -> kWh | D14: =(D13+(D13*$D$9)) -> 0 | E14: =(D14*Input!$D$5)+(365*Input!$D$7) -> 0 | F14: =Input!$D$14*G14 -> 0 | G14: =G13-0.005 -> 0.995 | H14: =Calculation!$KY$9 -> 0 | I14: =H14*D14 -> 0 | J14: =E14-I14 -> 0 | K14: =K13+I14 -> -4077.6146 | L14: =L13+I14 -> 0
B15: 3 | C15: =C14 -> kWh | D15: =(D14+(D14*$D$9)) -> 0 | E15: =(D15*Input!$D$5)+(365*Input!$D$7) -> 0 | F15: =Input!$D$14*G15 -> 0 | G15: =G14-0.005 -> 0.99 | H15: =Calculation!$KY$9 -> 0 | I15: =H15*D15 -> 0 | J15: =E15-I15 -> 0 | K15: =K14+I15 -> -4077.6146 | L15: =L14+I15 -> 0
B16: 4 | C16: =C15 -> kWh | D16: =(D15+(D15*$D$9)) -> 0 | E16: =(D16*Input!$D$5)+(365*Input!$D$7) -> 0 | F16: =Input!$D$14*G16 -> 0 | G16: =G15-0.005 -> 0.985 | H16: =Calculation!$KY$9 -> 0 | I16: =H16*D16 -> 0 | J16: =E16-I16 -> 0 | K16: =K15+I16 -> -4077.6146 | L16: =L15+I16 -> 0
B17: 5 | C17: =C16 -> kWh | D17: =(D16+(D16*$D$9)) -> 0 | E17: =(D17*Input!$D$5)+(365*Input!$D$7) -> 0 | F17: =Input!$D$14*G17 -> 0 | G17: =G16-0.005 -> 0.98 | H17: =Calculation!$KY$9 -> 0 | I17: =H17*D17 -> 0 | J17: =E17-I17 -> 0 | K17: =K16+I17 -> -4077.6146 | L17: =L16+I17 -> 0
B18: 6 | C18: =C17 -> kWh | D18: =(D17+(D17*$D$9)) -> 0 | E18: =(D18*Input!$D$5)+(365*Input!$D$7) -> 0 | F18: =Input!$D$14*G18 -> 0 | G18: =G17-0.005 -> 0.975 | H18: =Calculation!$KY$9 -> 0 | I18: =H18*D18 -> 0 | J18: =E18-I18 -> 0 | K18: =K17+I18 -> -4077.6146 | L18: =L17+I18 -> 0
B19: 7 | C19: =C18 -> kWh | D19: =(D18+(D18*$D$9)) -> 0 | E19: =(D19*Input!$D$5)+(365*Input!$D$7) -> 0 | F19: =Input!$D$14*G19 -> 0 | G19: =G18-0.005 -> 0.97 | H19: =Calculation!$KY$9 -> 0 | I19: =H19*D19 -> 0 | J19: =E19-I19 -> 0 | K19: =K18+I19 -> -4077.6146 | L19: =L18+I19 -> 0
B20: 8 | C20: =C19 -> kWh | D20: =(D19+(D19*$D$9)) -> 0 | E20: =(D20*Input!$D$5)+(365*Input!$D$7) -> 0 | F20: =Input!$D$14*G20 -> 0 | G20: =G19-0.005 -> 0.965 | H20: =Calculation!$KY$9 -> 0 | I20: =H20*D20 -> 0 | J20: =E20-I20 -> 0 | K20: =K19+I20 -> -4077.6146 | L20: =L19+I20 -> 0
B21: 9 | C21: =C20 -> kWh | D21: =(D20+(D20*$D$9)) -> 0 | E21: =(D21*Input!$D$5)+(365*Input!$D$7) -> 0 | F21: =Input!$D$14*G21 -> 0 | G21: =G20-0.005 -> 0.96 | H21: =Calculation!$KY$9 -> 0 | I21: =H21*D21 -> 0 | J21: =E21-I21 -> 0 | K21: =K20+I21 -> -4077.6146 | L21: =L20+I21 -> 0
B22: 10 | C22: =C21 -> kWh | D22: =(D21+(D21*$D$9)) -> 0 | E22: =(D22*Input!$D$5)+(365*Input!$D$7) -> 0 | F22: =Input!$D$14*G22 -> 0 | G22: =G21-0.005 -> 0.955 | H22: =Calculation!$KY$9 -> 0 | I22: =H22*D22 -> 0 | J22: =E22-I22 -> 0 | K22: =K21+I22 -> -4077.6146 | L22: =L21+I22 -> 0
B23: 11 | C23: =C22 -> kWh | D23: =(D22+(D22*$D$9)) -> 0 | E23: =(D23*Input!$D$5)+(365*Input!$D$7) -> 0 | F23: =Input!$D$14*G23 -> 0 | G23: =G22-0.005 -> 0.95 | H23: =Calculation!$KY$9 -> 0 | I23: =H23*D23 -> 0 | J23: =E23-I23 -> 0 | K23: =K22+I23 -> -4077.6146 | L23: =L22+I23 -> 0
B24: 12 | C24: =C23 -> kWh | D24: =(D23+(D23*$D$9)) -> 0 | E24: =(D24*Input!$D$5)+(365*Input!$D$7) -> 0 | F24: =Input!$D$14*G24 -> 0 | G24: =G23-0.005 -> 0.945 | H24: =Calculation!$KY$9 -> 0 | I24: =H24*D24 -> 0 | J24: =E24-I24 -> 0 | K24: =K23+I24 -> -4077.6146 | L24: =L23+I24 -> 0
B25: 13 | C25: =C24 -> kWh | D25: =(D24+(D24*$D$9)) -> 0 | E25: =(D25*Input!$D$5)+(365*Input!$D$7) -> 0 | F25: =Input!$D$14*G25 -> 0 | G25: =G24-0.005 -> 0.94 | H25: =Calculation!$KY$9 -> 0 | I25: =H25*D25 -> 0 | J25: =E25-I25 -> 0 | K25: =K24+I25 -> -4077.6146 | L25: =L24+I25 -> 0
... B32: 20 | C32: =C31 -> kWh | D32: =(D31+(D31*$D$9)) -> 0 | E32: =(D32*Input!$D$5)+(365*Input!$D$7) -> 0 | F32: =Input!$D$14*G32 -> 0 | G32: =G31-0.005 -> 0.905 | H32: =Calculation!$KY$9 -> 0 | I32: =H32*D32 -> 0 | J32: =E32-I32 -> 0 | K32: =K31+I32 -> -4077.6146 | L32: =L31+I32 -> 0

Sheet Profile
A1: Date | B1: Day | C1: Half Hour | D1: HH Period | E1: Solar Coefficient | F1: Consumption Coefficient
A2: 43466 | B2: 1 | C2: 1 | D2: 0 | E2: 0 | F2: 6.0793852e-05
A3: 43466 | B3: 1 | C3: 2 | D3: 0.020833333 | E3: 0 | F3: 5.5385503e-05
A4: 43466 | B4: 1 | C4: 3 | D4: 0.041666667 | E4: 0 | F4: 5.2881637e-05
A5: 43466 | B5: 1 | C5: 4 | D5: 0.0625 | E5: 0 | F5: 4.9876999e-05
A6: 43466 | B6: 1 | C6: 5 | D6: 0.083333333 | E6: 0 | F6: 4.9075762e-05
A7: 43466 | B7: 1 | C7: 6 | D7: 0.10416667 | E7: 0 | F7: 4.1764475e-05
A8: 43466 | B8: 1 | C8: 7 | D8: 0.125 | E8: 0 | F8: 3.8960146e-05
A9: 43466 | B9: 1 | C9: 8 | D9: 0.14583333 | E9: 0 | F9: 3.5955507e-05
A10: 43466 | B10: 1 | C10: 9 | D10: 0.16666667 | E10: 0 | F10: 3.4653497e-05
A11: 43466 | B11: 1 | C11: 10 | D11: 0.1875 | E11: 0 | F11: 3.4152724e-05
A12: 43466 | B12: 1 | C12: 11 | D12: 0.20833333 | E12: 0 | F12: 3.4553343e-05
A13: 43466 | B13: 1 | C13: 12 | D13: 0.22916667 | E13: 0 | F13: 3.5054116e-05
... A17521: 43830 | B17521: 365 | C17521: 48 | D17521: 0.97916667 | E17521: 0 | F17521: 5.5685967e-05

Sheet Calculation
KM1: 1 | KN1: 2 | KO1: 3 | KP1: 4 | KQ1: 5 | KR1: 6 | KS1: 7 | KT1: 8 | KU1: 9 | KV1: 10 | KW1: 11 | KX1: 12
KM2: Jan | KN2: Feb | KO2: Mar | KP2: Apr | KQ2: May | KR2: Jun | KS2: Jul | KT2: Aug | KU2: Sep | KV2: Oct | KW2: Nov | KX2: Dec | KY2: Total
KL3: Demand | KM3: =SUMIF($A$11:$A$375,KM$1,$D$11:$D$375) -> 0 | KN3: =SUMIF($A$11:$A$375,KN$1,$D$11:$D$375) -> 0 | KO3: =SUMIF($A$11:$A$375,KO$1,$D$11:$D$375) -> 0 | KP3: =SUMIF($A$11:$A$375,KP$1,$D$11:$D$375) -> 0 | KQ3: =SUMIF($A$11:$A$375,KQ$1,$D$11:$D$375) -> 0 | KR3: =SUMIF($A$11:$A$375,KR$1,$D$11:$D$375) -> 0 | KS3: =SUMIF($A$11:$A$375,KS$1,$D$11:$D$375) -> 0 | KT3: =SUMIF($A$11:$A$375,KT$1,$D$11:$D$375) -> 0 | ... KX3: =SUMIF($A$11:$A$375,KX$1,$D$11:$D$375) -> 0 | KY3: =SUM(KM3:KX3) -> 0
KL4: Solar | KM4: =SUMIF($A$11:$A$375,KM$1,$BA$11:$BA$375) -> 0 | KN4: =SUMIF($A$11:$A$375,KN$1,$BA$11:$BA$375) -> 0 | KO4: =SUMIF($A$11:$A$375,KO$1,$BA$11:$BA$375) -> 0 | KP4: =SUMIF($A$11:$A$375,KP$1,$BA$11:$BA$375) -> 0 | KQ4: =SUMIF($A$11:$A$375,KQ$1,$BA$11:$BA$375) -> 0 | KR4: =SUMIF($A$11:$A$375,KR$1,$BA$11:$BA$375) -> 0 | KS4: =SUMIF($A$11:$A$375,KS$1,$BA$11:$BA$375) -> 0 | KT4: =SUMIF($A$11:$A$375,KT$1,$BA$11:$BA$375) -> 0 | ... KX4: =SUMIF($A$11:$A$375,KX$1,$BA$11:$BA$375) -> 0 | KY4: =SUM(KM4:KX4) -> 0
BA5: Total Self Consumption without Battery | CX5: =EU8 -> 0 | EU5: =CX5/BA8 -> #DIV/0! | KL5: Export | KM5: =SUMIF($A$11:$A$375,KM$1,$CX$11:$CX$375) -> 0 | KN5: =SUMIF($A$11:$A$375,KN$1,$CX$11:$CX$375) -> 0 | KO5: =SUMIF($A$11:$A$375,KO$1,$CX$11:$CX$375) -> 0 | KP5: =SUMIF($A$11:$A$375,KP$1,$CX$11:$CX$375) -> 0 | KQ5: =SUMIF($A$11:$A$375,KQ$1,$CX$11:$CX$375) -> 0 | KR5: =SUMIF($A$11:$A$375,KR$1,$CX$11:$CX$375) -> 0 | KS5: =SUMIF($A$11:$A$375,KS$1,$CX$11:$CX$375) -> 0 | KT5: =SUMIF($A$11:$A$375,KT$1,$CX$11:$CX$375) -> 0 | ... KX5: =SUMIF($A$11:$A$375,KX$1,$CX$11:$CX$375) -> 0 | KY5: =SUM(KM5:KX5) -> 0
B6: Demand (Annual kWh) | C6: =Input!D5 | BA6: Total Self Consumption With Battery | CX6: =CX5+IO8 -> 0 | EU6: =CX6/BA8 -> #DIV/0! | KL6: Self Consumption Without Battery | KM6: =SUMIF($A$11:$A$375,KM$1,$EU$11:$EU$375) -> 0 | KN6: =SUMIF($A$11:$A$375,KN$1,$EU$11:$EU$375) -> 0 | KO6: =SUMIF($A$11:$A$375,KO$1,$EU$11:$EU$375) -> 0 | KP6: =SUMIF($A$11:$A$375,KP$1,$EU$11:$EU$375) -> 0 | KQ6: =SUMIF($A$11:$A$375,KQ$1,$EU$11:$EU$375) -> 0 | KR6: =SUMIF($A$11:$A$375,KR$1,$EU$11:$EU$375) -> 0 | KS6: =SUMIF($A$11:$A$375,KS$1,$EU$11:$EU$375) -> 0 | KT6: =SUMIF($A$11:$A$375,KT$1,$EU$11:$EU$375) -> 0 | ... KX6: =SUMIF($A$11:$A$375,KX$1,$EU$11:$EU$375) -> 0 | KY6: =SUM(KM6:KX6) -> 0 | KZ6: =KY6/KY4 -> #DIV/0!
B7: System Size (kWdc) | C7: =Input!D12 -> 2.7 | BA7: Export After Battery | CX7: =IO8 -> 0 | EU7: =CX7/BA8 -> #DIV/0! | GR7: Battery Size | IO7: =Input!D21 -> 0 | KL7: Demand After Solar | KM7: =SUMIF($A$11:$A$375,KM$1,$GR$11:$GR$375) -> 0 | KN7: =SUMIF($A$11:$A$375,KN$1,$GR$11:$GR$375) -> 0 | KO7: =SUMIF($A$11:$A$375,KO$1,$GR$11:$GR$375) -> 0 | KP7: =SUMIF($A$11:$A$375,KP$1,$GR$11:$GR$375) -> 0 | KQ7: =SUMIF($A$11:$A$375,KQ$1,$GR$11:$GR$375) -> 0 | KR7: =SUMIF($A$11:$A$375,KR$1,$GR$11:$GR$375) -> 0 | KS7: =SUMIF($A$11:$A$375,KS$1,$GR$11:$GR$375) -> 0 | KT7: =SUMIF($A$11:$A$375,KT$1,$GR$11:$GR$375) -> 0 | ... KX7: =SUMIF($A$11:$A$375,KX$1,$GR$11:$GR$375) -> 0 | KY7: =SUM(KM7:KX7) -> 0
B8: Yield (kWhac Per kWdc) | C8: =Input!D13 | D8: =SUM(D11:D375) -> 0 | E8: 1 | F8: 2 | G8: 3 | H8: 4 | I8: 5 | J8: 6 | K8: 7 | L8: 8 | M8: 9 | N8: 10 | O8: 11 | P8: 12 | Q8: 13 | R8: 14 | S8: 15 | T8: 16 | U8: 17 | V8: 18 | W8: 19 | X8: 20 | Y8: 21 | Z8: 22 | AA8: 23 | AB8: 24 | AC8: 25 | AD8: 26 | AE8: 27 | AF8: 28 | AG8: 29 | AH8: 30 | AI8: 31 | AJ8: 32 | AK8: 33 | AL8: 34 | AM8: 35 | AN8: 36 | AO8: 37 | AP8: 38 | AQ8: 39 | AR8: 40 | AS8: 41 | AT8: 42 | AU8: 43 | AV8: 44 | AW8: 45 | AX8: 46 | AY8: 47 | AZ8: 48 | BA8: =SUM(BA11:BA375) -> 0 | BB8: 1 | BC8: 2 | BD8: 3 | BE8: 4 | BF8: 5 | BG8: 6 | BH8: 7 | BI8: 8 | BJ8: 9 | BK8: 10 | BL8: 11 | BM8: 12 | BN8: 13 | BO8: 14 | BP8: 15 | BQ8: 16 | BR8: 17 | BS8: 18 | BT8: 19 | BU8: 20 | BV8: 21 | BW8: 22 | BX8: 23 | BY8: 24 | BZ8: 25 | CA8: 26 | CB8: 27 | CC8: 28 | CD8: 29 | CE8: 30 | CF8: 31 | CG8: 32 | CH8: 33 | CI8: 34 | CJ8: 35 | CK8: 36 | CL8: 37 | CM8: 38 | CN8: 39 | CO8: 40 | CP8: 41 | CQ8: 42 | CR8: 43 | CS8: 44 | CT8: 45 | CU8: 46 | CV8: 47 | CW8: 48 | CX8: =SUM(CX11:CX375) -> 0 | CY8: 1 | CZ8: 2 | DA8: 3 | DB8: 4 | DC8: 5 | DD8: 6 | DE8: 7 | DF8: 8 | DG8: 9 | DH8: 10 | DI8: 11 | DJ8: 12 | DK8: 13 | DL8: 14 | DM8: 15 | DN8: 16 | DO8: 17 | DP8: 18 | DQ8: 19 | DR8: 20 | DS8: 21 | DT8: 22 | DU8: 23 | DV8: 24 | DW8: 25 | DX8: 26 | DY8: 27 | DZ8: 28 | EA8: 29 | EB8: 30 | EC8: 31 | ED8: 32 | EE8: 33 | EF8: 34 | EG8: 35 | EH8: 36 | EI8: 37 | EJ8: 38 | EK8: 39 | EL8: 40 | EM8: 41 | EN8: 42 | EO8: 43 | EP8: 44 | EQ8: 45 | ER8: 46 | ES8: 47 | ET8: 48 | EU8: =SUM(EU11:EU375) -> 0 | EV8: 1 | EW8: 2 | EX8: 3 | EY8: 4 | EZ8: 5 | FA8: 6 | FB8: 7 | FC8: 8 | FD8: 9 | FE8: 10 | FF8: 11 | FG8: 12 | FH8: 13 | FI8: 14 | FJ8: 15 | FK8: 16 | FL8: 17 | FM8: 18 | FN8: 19 | FO8: 20 | FP8: 21 | FQ8: 22 | FR8: 23 | FS8: 24 | FT8: 25 | FU8: 26 | FV8: 27 | FW8: 28 | FX8: 29 | FY8: 30 | FZ8: 31 | GA8: 32 | GB8: 33 | GC8: 34 | GD8: 35 | GE8: 36 | GF8: 37 | GG8: 38 | GH8: 39 | GI8: 40 | GJ8: 41 | GK8: 42 | GL8: 43 | GM8: 44 | GN8: 45 | GO8: 46 | GP8: 47 | GQ8: 48 | GR8: =SUM(GR11:GR375) -> 0 | GS8: 1 | GT8: 2 | GU8: 3 | GV8: 4 | GW8: 5 | GX8: 6 | GY8: 7 | GZ8: 8 | HA8: 9 | HB8: 10 | HC8: 11 | HD8: 12 | HE8: 13 | HF8: 14 | HG8: 15 | HH8: 16 | HI8: 17 | HJ8: 18 | HK8: 19 | HL8: 20 | HM8: 21 | HN8: 22 | HO8: 23 | HP8: 24 | HQ8: 25 | HR8: 26 | HS8: 27 | HT8: 28 | HU8: 29 | HV8: 30 | HW8: 31 | HX8: 32 | HY8: 33 | HZ8: 34 | IA8: 35 | IB8: 36 | IC8: 37 | ID8: 38 | IE8: 39 | IF8: 40 | IG8: 41 | IH8: 42 | II8: 43 | IJ8: 44 | IK8: 45 | IL8: 46 | IM8: 47 | IN8: 48 | IO8: =SUM(IO11:IO375) -> 0 | IP8: 1 | IQ8: 2 | IR8: 3 | IS8: 4 | IT8: 5 | IU8: 6 | IV8: 7 | IW8: 8 | IX8: 9 | IY8: 10 | IZ8: 11 | JA8: 12 | JB8: 13 | JC8: 14 | JD8: 15 | JE8: 16 | JF8: 17 | JG8: 18 | JH8: 19 | JI8: 20 | JJ8: 21 | JK8: 22 | JL8: 23 | JM8: 24 | JN8: 25 | JO8: 26 | JP8: 27 | JQ8: 28 | JR8: 29 | JS8: 30 | JT8: 31 | JU8: 32 | JV8: 33 | JW8: 34 | JX8: 35 | JY8: 36 | JZ8: 37 | KA8: 38 | KB8: 39 | KC8: 40 | KD8: 41 | KE8: 42 | KF8: 43 | KG8: 44 | KH8: 45 | KI8: 46 | KJ8: 47 | KK8: 48 | KL8: Export After Battery | KM8: =SUMIF($A$11:$A$375,KM$1,$IO$11:$IO$375) -> 0 | KN8: =SUMIF($A$11:$A$375,KN$1,$IO$11:$IO$375) -> 0 | KO8: =SUMIF($A$11:$A$375,KO$1,$IO$11:$IO$375) -> 0 | KP8: =SUMIF($A$11:$A$375,KP$1,$IO$11:$IO$375) -> 0 | KQ8: =SUMIF($A$11:$A$375,KQ$1,$IO$11:$IO$375) -> 0 | KR8: =SUMIF($A$11:$A$375,KR$1,$IO$11:$IO$375) -> 0 | KS8: =SUMIF($A$11:$A$375,KS$1,$IO$11:$IO$375) -> 0 | KT8: =SUMIF($A$11:$A$375,KT$1,$IO$11:$IO$375) -> 0 | ... KX8: =SUMIF($A$11:$A$375,KX$1,$IO$11:$IO$375) -> 0 | KY8: =SUM(KM8:KX8) -> 0
B9: Annual Generation (Annual kWhac) | C9: =Input!D14 -> 0 | D9: Total | E9: 0.020833333 | F9: 0.041666667 | G9: 0.0625 | H9: 0.083333333 | I9: 0.10416667 | J9: 0.125 | K9: 0.14583333 | L9: 0.16666667 | M9: 0.1875 | N9: 0.20833333 | O9: 0.22916667 | P9: 0.25 | Q9: 0.27083333 | R9: 0.29166667 | S9: 0.3125 | T9: 0.33333333 | U9: 0.35416667 | V9: 0.375 | W9: 0.39583333 | X9: 0.41666667 | Y9: 0.4375 | Z9: 0.45833333 | AA9: 0.47916667 | AB9: 0.5 | AC9: 0.52083333 | AD9: 0.54166667 | AE9: 0.5625 | AF9: 0.58333333 | AG9: 0.60416667 | AH9: 0.625 | AI9: 0.64583333 | AJ9: 0.66666667 | AK9: 0.6875 | AL9: 0.70833333 | AM9: 0.72916667 | AN9: 0.75 | AO9: 0.77083333 | AP9: 0.79166667 | AQ9: 0.8125 | AR9: 0.83333333 | AS9: 0.85416667 | AT9: 0.875 | AU9: 0.89583333 | AV9: 0.91666667 | AW9: 0.9375 | AX9: 0.95833333 | AY9: 0.97916667 | AZ9: 1 | BA9: Total | BB9: 0.020833333 | BC9: 0.041666667 | BD9: 0.0625 | BE9: 0.083333333 | BF9: 0.10416667 | BG9: 0.125 | BH9: 0.14583333 | BI9: 0.16666667 | BJ9: 0.1875 | BK9: 0.20833333 | BL9: 0.22916667 | BM9: 0.25 | BN9: 0.27083333 | BO9: 0.29166667 | BP9: 0.3125 | BQ9: 0.33333333 | BR9: 0.35416667 | BS9: 0.375 | BT9: 0.39583333 | BU9: 0.41666667 | BV9: 0.4375 | BW9: 0.45833333 | BX9: 0.47916667 | BY9: 0.5 | BZ9: 0.52083333 | CA9: 0.54166667 | CB9: 0.5625 | CC9: 0.58333333 | CD9: 0.60416667 | CE9: 0.625 | CF9: 0.64583333 | CG9: 0.66666667 | CH9: 0.6875 | CI9: 0.70833333 | CJ9: 0.72916667 | CK9: 0.75 | CL9: 0.77083333 | CM9: 0.79166667 | CN9: 0.8125 | CO9: 0.83333333 | CP9: 0.85416667 | CQ9: 0.875 | CR9: 0.89583333 | CS9: 0.91666667 | CT9: 0.9375 | CU9: 0.95833333 | CV9: 0.97916667 | CW9: 1 | CX9: Total | CY9: 0.020833333 | CZ9: 0.041666667 | DA9: 0.0625 | DB9: 0.083333333 | DC9: 0.10416667 | DD9: 0.125 | DE9: 0.14583333 | DF9: 0.16666667 | DG9: 0.1875 | DH9: 0.20833333 | DI9: 0.22916667 | DJ9: 0.25 | DK9: 0.27083333 | DL9: 0.29166667 | DM9: 0.3125 | DN9: 0.33333333 | DO9: 0.35416667 | DP9: 0.375 | DQ9: 0.39583333 | DR9: 0.41666667 | DS9: 0.4375 | DT9: 0.45833333 | DU9: 0.47916667 | DV9: 0.5 | DW9: 0.52083333 | DX9: 0.54166667 | DY9: 0.5625 | DZ9: 0.58333333 | EA9: 0.60416667 | EB9: 0.625 | EC9: 0.64583333 | ED9: 0.66666667 | EE9: 0.6875 | EF9: 0.70833333 | EG9: 0.72916667 | EH9: 0.75 | EI9: 0.77083333 | EJ9: 0.79166667 | EK9: 0.8125 | EL9: 0.83333333 | EM9: 0.85416667 | EN9: 0.875 | EO9: 0.89583333 | EP9: 0.91666667 | EQ9: 0.9375 | ER9: 0.95833333 | ES9: 0.97916667 | ET9: 1 | EU9: Total | EV9: 0.020833333 | EW9: 0.041666667 | EX9: 0.0625 | EY9: 0.083333333 | EZ9: 0.10416667 | FA9: 0.125 | FB9: 0.14583333 | FC9: 0.16666667 | FD9: 0.1875 | FE9: 0.20833333 | FF9: 0.22916667 | FG9: 0.25 | FH9: 0.27083333 | FI9: 0.29166667 | FJ9: 0.3125 | FK9: 0.33333333 | FL9: 0.35416667 | FM9: 0.375 | FN9: 0.39583333 | FO9: 0.41666667 | FP9: 0.4375 | FQ9: 0.45833333 | FR9: 0.47916667 | FS9: 0.5 | FT9: 0.52083333 | FU9: 0.54166667 | FV9: 0.5625 | FW9: 0.58333333 | FX9: 0.60416667 | FY9: 0.625 | FZ9: 0.64583333 | GA9: 0.66666667 | GB9: 0.6875 | GC9: 0.70833333 | GD9: 0.72916667 | GE9: 0.75 | GF9: 0.77083333 | GG9: 0.79166667 | GH9: 0.8125 | GI9: 0.83333333 | GJ9: 0.85416667 | GK9: 0.875 | GL9: 0.89583333 | GM9: 0.91666667 | GN9: 0.9375 | GO9: 0.95833333 | GP9: 0.97916667 | GQ9: 1 | GR9: Total | GS9: 0.020833333 | GT9: 0.041666667 | GU9: 0.0625 | GV9: 0.083333333 | GW9: 0.10416667 | GX9: 0.125 | GY9: 0.14583333 | GZ9: 0.16666667 | HA9: 0.1875 | HB9: 0.20833333 | HC9: 0.22916667 | HD9: 0.25 | HE9: 0.27083333 | HF9: 0.29166667 | HG9: 0.3125 | HH9: 0.33333333 | HI9: 0.35416667 | HJ9: 0.375 | HK9: 0.39583333 | HL9: 0.41666667 | HM9: 0.4375 | HN9: 0.45833333 | HO9: 0.47916667 | HP9: 0.5 | HQ9: 0.52083333 | HR9: 0.54166667 | HS9: 0.5625 | HT9: 0.58333333 | HU9: 0.60416667 | HV9: 0.625 | HW9: 0.64583333 | HX9: 0.66666667 | HY9: 0.6875 | HZ9: 0.70833333 | IA9: 0.72916667 | IB9: 0.75 | IC9: 0.77083333 | ID9: 0.79166667 | IE9: 0.8125 | IF9: 0.83333333 | IG9: 0.85416667 | IH9: 0.875 | II9: 0.89583333 | IJ9: 0.91666667 | IK9: 0.9375 | IL9: 0.95833333 | IM9: 0.97916667 | IN9: 1 | IO9: Total | IP9: 0.020833333 | IQ9: 0.041666667 | IR9: 0.0625 | IS9: 0.083333333 | IT9: 0.10416667 | IU9: 0.125 | IV9: 0.14583333 | IW9: 0.16666667 | IX9: 0.1875 | IY9: 0.20833333 | IZ9: 0.22916667 | JA9: 0.25 | JB9: 0.27083333 | JC9: 0.29166667 | JD9: 0.3125 | JE9: 0.33333333 | JF9: 0.35416667 | JG9: 0.375 | JH9: 0.39583333 | JI9: 0.41666667 | JJ9: 0.4375 | JK9: 0.45833333 | JL9: 0.47916667 | JM9: 0.5 | JN9: 0.52083333 | JO9: 0.54166667 | JP9: 0.5625 | JQ9: 0.58333333 | JR9: 0.60416667 | JS9: 0.625 | JT9: 0.64583333 | JU9: 0.66666667 | JV9: 0.6875 | JW9: 0.70833333 | JX9: 0.72916667 | JY9: 0.75 | JZ9: 0.77083333 | KA9: 0.79166667 | KB9: 0.8125 | KC9: 0.83333333 | KD9: 0.85416667 | KE9: 0.875 | KF9: 0.89583333 | KG9: 0.91666667 | KH9: 0.9375 | KI9: 0.95833333 | KJ9: 0.97916667 | KK9: 1 | KL9: Total Self Consumption With Battery | KM9: =SUMIF($A$11:$A$375,KM$1,$IO$11:$IO$375)+KM6 -> 0 | KN9: =SUMIF($A$11:$A$375,KN$1,$IO$11:$IO$375)+KN6 -> 0 | KO9: =SUMIF($A$11:$A$375,KO$1,$IO$11:$IO$375)+KO6 -> 0 | KP9: =SUMIF($A$11:$A$375,KP$1,$IO$11:$IO$375)+KP6 -> 0 | KQ9: =SUMIF($A$11:$A$375,KQ$1,$IO$11:$IO$375)+KQ6 -> 0 | KR9: =SUMIF($A$11:$A$375,KR$1,$IO$11:$IO$375)+KR6 -> 0 | KS9: =SUMIF($A$11:$A$375,KS$1,$IO$11:$IO$375)+KS6 -> 0 | KT9: =SUMIF($A$11:$A$375,KT$1,$IO$11:$IO$375)+KT6 -> 0 | ... KX9: =SUMIF($A$11:$A$375,KX$1,$IO$11:$IO$375)+KX6 -> 0 | KY9: =SUM(KM9:KX9) -> 0 | KZ9: =KY9/KY4 -> #DIV/0!
A10: Count (Month) | B10: Count (Day) | C10: Date | D10: Demand | E10: Demand | F10: Demand | G10: Demand | H10: Demand | I10: Demand | J10: Demand | K10: Demand | L10: Demand | M10: Demand | N10: Demand | O10: Demand | P10: Demand | Q10: Demand | R10: Demand | S10: Demand | T10: Demand | U10: Demand | V10: Demand | W10: Demand | X10: Demand | Y10: Demand | Z10: Demand | AA10: Demand | AB10: Demand | AC10: Demand | AD10: Demand | AE10: Demand | AF10: Demand | AG10: Demand | AH10: Demand | AI10: Demand | AJ10: Demand | AK10: Demand | AL10: Demand | AM10: Demand | AN10: Demand | AO10: Demand | AP10: Demand | AQ10: Demand | AR10: Demand | AS10: Demand | AT10: Demand | AU10: Demand | AV10: Demand | AW10: Demand | AX10: Demand | AY10: Demand | AZ10: Demand | BA10: Solar | BB10: Solar | BC10: Solar | BD10: Solar | BE10: Solar | BF10: Solar | BG10: Solar | BH10: Solar | BI10: Solar | BJ10: Solar | BK10: Solar | BL10: Solar | BM10: Solar | BN10: Solar | BO10: Solar | BP10: Solar | BQ10: Solar | BR10: Solar | BS10: Solar | BT10: Solar | BU10: Solar | BV10: Solar | BW10: Solar | BX10: Solar | BY10: Solar | BZ10: Solar | CA10: Solar | CB10: Solar | CC10: Solar | CD10: Solar | CE10: Solar | CF10: Solar | CG10: Solar | CH10: Solar | CI10: Solar | CJ10: Solar | CK10: Solar | CL10: Solar | CM10: Solar | CN10: Solar | CO10: Solar | CP10: Solar | CQ10: Solar | CR10: Solar | CS10: Solar | CT10: Solar | CU10: Solar | CV10: Solar | CW10: Solar | CX10: Export | CY10: Export | CZ10: Export | DA10: Export | DB10: Export | DC10: Export | DD10: Export | DE10: Export | DF10: Export | DG10: Export | DH10: Export | DI10: Export | DJ10: Export | DK10: Export | DL10: Export | DM10: Export | DN10: Export | DO10: Export | DP10: Export | DQ10: Export | DR10: Export | DS10: Export | DT10: Export | DU10: Export | DV10: Export | DW10: Export | DX10: Export | DY10: Export | DZ10: Export | EA10: Export | EB10: Export | EC10: Export | ED10: Export | EE10: Export | EF10: Export | EG10: Export | EH10: Export | EI10: Export | EJ10: Export | EK10: Export | EL10: Export | EM10: Export | EN10: Export | EO10: Export | EP10: Export | EQ10: Export | ER10: Export | ES10: Export | ET10: Export | EU10: Self Consumption | EV10: Self Consumption | EW10: Self Consumption | EX10: Self Consumption | EY10: Self Consumption | EZ10: Self Consumption | FA10: Self Consumption | FB10: Self Consumption | FC10: Self Consumption | FD10: Self Consumption | FE10: Self Consumption | FF10: Self Consumption | FG10: Self Consumption | FH10: Self Consumption | FI10: Self Consumption | FJ10: Self Consumption | FK10: Self Consumption | FL10: Self Consumption | FM10: Self Consumption | FN10: Self Consumption | FO10: Self Consumption | FP10: Self Consumption | FQ10: Self Consumption | FR10: Self Consumption | FS10: Self Consumption | FT10: Self Consumption | FU10: Self Consumption | FV10: Self Consumption | FW10: Self Consumption | FX10: Self Consumption | FY10: Self Consumption | FZ10: Self Consumption | GA10: Self Consumption | GB10: Self Consumption | GC10: Self Consumption | GD10: Self Consumption | GE10: Self Consumption | GF10: Self Consumption | GG10: Self Consumption | GH10: Self Consumption | GI10: Self Consumption | GJ10: Self Consumption | GK10: Self Consumption | GL10: Self Consumption | GM10: Self Consumption | GN10: Self Consumption | GO10: Self Consumption | GP10: Self Consumption | GQ10: Self Consumption | GR10: Demand After Solar | GS10: Demand After Self Consumption of Solar | GT10: Demand After Self Consumption of Solar | GU10: Demand After Self Consumption of Solar | GV10: Demand After Self Consumption of Solar | GW10: Demand After Self Consumption of Solar | GX10: Demand After Self Consumption of Solar | GY10: Demand After Self Consumption of Solar | GZ10: Demand After Self Consumption of Solar | HA10: Demand After Self Consumption of Solar | HB10: Demand After Self Consumption of Solar | HC10: Demand After Self Consumption of Solar | HD10: Demand After Self Consumption of Solar | HE10: Demand After Self Consumption of Solar | HF10: Demand After Self Consumption of Solar | HG10: Demand After Self Consumption of Solar | HH10: Demand After Self Consumption of Solar | HI10: Demand After Self Consumption of Solar | HJ10: Demand After Self Consumption of Solar | HK10: Demand After Self Consumption of Solar | HL10: Demand After Self Consumption of Solar | HM10: Demand After Self Consumption of Solar | HN10: Demand After Self Consumption of Solar | HO10: Demand After Self Consumption of Solar | HP10: Demand After Self Consumption of Solar | HQ10: Demand After Self Consumption of Solar | HR10: Demand After Self Consumption of Solar | HS10: Demand After Self Consumption of Solar | HT10: Demand After Self Consumption of Solar | HU10: Demand After Self Consumption of Solar | HV10: Demand After Self Consumption of Solar | HW10: Demand After Self Consumption of Solar | HX10: Demand After Self Consumption of Solar | HY10: Demand After Self Consumption of Solar | HZ10: Demand After Self Consumption of Solar | IA10: Demand After Self Consumption of Solar | IB10: Demand After Self Consumption of Solar | IC10: Demand After Self Consumption of Solar | ID10: Demand After Self Consumption of Solar | IE10: Demand After Self Consumption of Solar | IF10: Demand After Self Consumption of Solar | IG10: Demand After Self Consumption of Solar | IH10: Demand After Self Consumption of Solar | II10: Demand After Self Consumption of Solar | IJ10: Demand After Self Consumption of Solar | IK10: Demand After Self Consumption of Solar | IL10: Demand After Self Consumption of Solar | IM10: Demand After Self Consumption of Solar | IN10: Demand After Self Consumption of Solar | IO10: Battery Use | IP10: Battey Charge / Discharge | IQ10: Battey Charge / Discharge | IR10: Battey Charge / Discharge | IS10: Battey Charge / Discharge | IT10: Battey Charge / Discharge | IU10: Battey Charge / Discharge | IV10: Battey Charge / Discharge | IW10: Battey Charge / Discharge | IX10: Battey Charge / Discharge | IY10: Battey Charge / Discharge | IZ10: Battey Charge / Discharge | JA10: Battey Charge / Discharge | JB10: Battey Charge / Discharge | JC10: Battey Charge / Discharge | JD10: Battey Charge / Discharge | JE10: Battey Charge / Discharge | JF10: Battey Charge / Discharge | JG10: Battey Charge / Discharge | JH10: Battey Charge / Discharge | JI10: Battey Charge / Discharge | JJ10: Battey Charge / Discharge | JK10: Battey Charge / Discharge | JL10: Battey Charge / Discharge | JM10: Battey Charge / Discharge | JN10: Battey Charge / Discharge | JO10: Battey Charge / Discharge | JP10: Battey Charge / Discharge | JQ10: Battey Charge / Discharge | JR10: Battey Charge / Discharge | JS10: Battey Charge / Discharge | JT10: Battey Charge / Discharge | JU10: Battey Charge / Discharge | JV10: Battey Charge / Discharge | JW10: Battey Charge / Discharge | JX10: Battey Charge / Discharge | JY10: Battey Charge / Discharge | JZ10: Battey Charge / Discharge | KA10: Battey Charge / Discharge | KB10: Battey Charge / Discharge | KC10: Battey Charge / Discharge | KD10: Battey Charge / Discharge | KE10: Battey Charge / Discharge | KF10: Battey Charge / Discharge | KG10: Battey Charge / Discharge | KH10: Battey Charge / Discharge | KI10: Battey Charge / Discharge | KJ10: Battey Charge / Discharge | KK10: Battey Charge / Discharge | KL10: Demand After Solar and Storage | KM10: =KM3-KM9 -> 0 | KN10: =KN3-KN9 -> 0 | KO10: =KO3-KO9 -> 0 | KP10: =KP3-KP9 -> 0 | KQ10: =KQ3-KQ9 -> 0 | KR10: =KR3-KR9 -> 0 | KS10: =KS3-KS9 -> 0 | KT10: =KT3-KT9 -> 0 | ... KX10: =KX3-KX9 -> 0 | KY10: =SUM(KM10:KX10) -> 0
A11: 1 | B11: =VLOOKUP(C11,Profile!A2:B17521,2,0) -> 1 | C11: 43466 | D11: =SUM(E11:AZ11) -> 0 | E11: =(SUMIFS(Profile!$F$2:$F$17521,Profile!$B$2:$B$17521,$B11,Profile!$C$2:$C$17521,E$8))*$C$6 -> 0 | F11: =(SUMIFS(Profile!$F$2:$F$17521,Profile!$B$2:$B$17521,$B11,Profile!$C$2:$C$17521,F$8))*$C$6 -> 0 | G11: =(SUMIFS(Profile!$F$2:$F$17521,Profile!$B$2:$B$17521,$B11,Profile!$C$2:$C$17521,G$8))*$C$6 -> 0 | H11: =(SUMIFS(Profile!$F$2:$F$17521,Profile!$B$2:$B$17521,$B11,Profile!$C$2:$C$17521,H$8))*$C$6 -> 0 | I11: =(SUMIFS(Profile!$F$2:$F$17521,Profile!$B$2:$B$17521,$B11,Profile!$C$2:$C$17521,I$8))*$C$6 -> 0 | J11: =(SUMIFS(Profile!$F$2:$F$17521,Profile!$B$2:$B$17521,$B11,Profile!$C$2:$C$17521,J$8))*$C$6 -> 0 | K11: =(SUMIFS(Profile!$F$2:$F$17521,Profile!$B$2:$B$17521,$B11,Profile!$C$2:$C$17521,K$8))*$C$6 -> 0 | L11: =(SUMIFS(Profile!$F$2:$F$17521,Profile!$B$2:$B$17521,$B11,Profile!$C$2:$C$17521,L$8))*$C$6 -> 0 | ... AZ11: =(SUMIFS(Profile!$F$2:$F$17521,Profile!$B$2:$B$17521,$B11,Profile!$C$2:$C$17521,AZ$8))*$C$6 -> 0 | BA11: =SUM(BB11:CW11) -> 0 | BB11: =(SUMIFS(Profile!$E$2:$E$17521,Profile!$B$2:$B$17521,$B11,Profile!$C$2:$C$17521,BB$8))*$C$9 -> 0 | BC11: =(SUMIFS(Profile!$E$2:$E$17521,Profile!$B$2:$B$17521,$B11,Profile!$C$2:$C$17521,BC$8))*$C$9 -> 0 | BD11: =(SUMIFS(Profile!$E$2:$E$17521,Profile!$B$2:$B$17521,$B11,Profile!$C$2:$C$17521,BD$8))*$C$9 -> 0 | BE11: =(SUMIFS(Profile!$E$2:$E$17521,Profile!$B$2:$B$17521,$B11,Profile!$C$2:$C$17521,BE$8))*$C$9 -> 0 | BF11: =(SUMIFS(Profile!$E$2:$E$17521,Profile!$B$2:$B$17521,$B11,Profile!$C$2:$C$17521,BF$8))*$C$9 -> 0 | BG11: =(SUMIFS(Profile!$E$2:$E$17521,Profile!$B$2:$B$17521,$B11,Profile!$C$2:$C$17521,BG$8))*$C$9 -> 0 | BH11: =(SUMIFS(Profile!$E$2:$E$17521,Profile!$B$2:$B$17521,$B11,Profile!$C$2:$C$17521,BH$8))*$C$9 -> 0 | BI11: =(SUMIFS(Profile!$E$2:$E$17521,Profile!$B$2:$B$17521,$B11,Profile!$C$2:$C$17521,BI$8))*$C$9 -> 0 | ... CW11: =(SUMIFS(Profile!$E$2:$E$17521,Profile!$B$2:$B$17521,$B11,Profile!$C$2:$C$17521,CW$8))*$C$9 -> 0 | CX11: =SUM(CY11:ET11) -> 0 | CY11: =MAX(BB11-E11,0) -> 0 | CZ11: =MAX(BC11-F11,0) -> 0 | DA11: =MAX(BD11-G11,0) -> 0 | DB11: =MAX(BE11-H11,0) -> 0 | DC11: =MAX(BF11-I11,0) -> 0 | DD11: =MAX(BG11-J11,0) -> 0 | DE11: =MAX(BH11-K11,0) -> 0 | DF11: =MAX(BI11-L11,0) -> 0 | ... ET11: =MAX(CW11-AZ11,0) -> 0 | EU11: =SUM(EV11:GQ11) -> 0 | EV11: =BB11-CY11 -> 0 | EW11: =BC11-CZ11 -> 0 | EX11: =BD11-DA11 -> 0 | EY11: =BE11-DB11 -> 0 | EZ11: =BF11-DC11 -> 0 | FA11: =BG11-DD11 -> 0 | FB11: =BH11-DE11 -> 0 | FC11: =BI11-DF11 -> 0 | ... GQ11: =CW11-ET11 -> 0 | GR11: =SUM(GS11:IN11) -> 0 | GS11: =E11-EV11 -> 0 | GT11: =F11-EW11 -> 0 | GU11: =G11-EX11 -> 0 | GV11: =H11-EY11 -> 0 | GW11: =I11-EZ11 -> 0 | GX11: =J11-FA11 -> 0 | GY11: =K11-FB11 -> 0 | GZ11: =L11-FC11 -> 0 | ... IN11: =AZ11-GQ11 -> 0 | IO11: =MAX(IP11:KK11)-IF(KK11<>0,KK11,MIN(IP11:KK11)) -> 0 | IP11: =MIN(CY11,$IO$7) -> 0 | IQ11: =MAX((MIN(CZ11+IP11,$IO$7))-GT11,0) -> 0 | IR11: =MAX((MIN(DA11+IQ11,$IO$7))-GU11,0) -> 0 | IS11: =MAX((MIN(DB11+IR11,$IO$7))-GV11,0) -> 0 | IT11: =MAX((MIN(DC11+IS11,$IO$7))-GW11,0) -> 0 | IU11: =MAX((MIN(DD11+IT11,$IO$7))-GX11,0) -> 0 | IV11: =MAX((MIN(DE11+IU11,$IO$7))-GY11,0) -> 0 | IW11: =MAX((MIN(DF11+IV11,$IO$7))-GZ11,0) -> 0 | IX11: =MAX((MIN(DG11+IW11,$IO$7))-HA11,0) -> 0 | ... KK11: =MAX((MIN(ET11+KJ11,$IO$7))-IN11,0) -> 0
A12: 1 | B12: =B11+1 -> 2 | C12: =C11+1 -> 43467 | D12: =SUM(E12:AZ12) -> 0 | E12: =(SUMIFS(Profile!$F$2:$F$17521,Profile!$B$2:$B$17521,$B12,Profile!$C$2:$C$17521,E$8))*$C$6 -> 0 | F12: =(SUMIFS(Profile!$F$2:$F$17521,Profile!$B$2:$B$17521,$B12,Profile!$C$2:$C$17521,F$8))*$C$6 -> 0 | G12: =(SUMIFS(Profile!$F$2:$F$17521,Profile!$B$2:$B$17521,$B12,Profile!$C$2:$C$17521,G$8))*$C$6 -> 0 | H12: =(SUMIFS(Profile!$F$2:$F$17521,Profile!$B$2:$B$17521,$B12,Profile!$C$2:$C$17521,H$8))*$C$6 -> 0 | I12: =(SUMIFS(Profile!$F$2:$F$17521,Profile!$B$2:$B$17521,$B12,Profile!$C$2:$C$17521,I$8))*$C$6 -> 0 | J12: =(SUMIFS(Profile!$F$2:$F$17521,Profile!$B$2:$B$17521,$B12,Profile!$C$2:$C$17521,J$8))*$C$6 -> 0 | K12: =(SUMIFS(Profile!$F$2:$F$17521,Profile!$B$2:$B$17521,$B12,Profile!$C$2:$C$17521,K$8))*$C$6 -> 0 | L12: =(SUMIFS(Profile!$F$2:$F$17521,Profile!$B$2:$B$17521,$B12,Profile!$C$2:$C$17521,L$8))*$C$6 -> 0 | ... AZ12: =(SUMIFS(Profile!$F$2:$F$17521,Profile!$B$2:$B$17521,$B12,Profile!$C$2:$C$17521,AZ$8))*$C$6 -> 0 | BA12: =SUM(BB12:CW12) -> 0 | BB12: =(SUMIFS(Profile!$E$2:$E$17521,Profile!$B$2:$B$17521,$B12,Profile!$C$2:$C$17521,BB$8))*$C$9 -> 0 | BC12: =(SUMIFS(Profile!$E$2:$E$17521,Profile!$B$2:$B$17521,$B12,Profile!$C$2:$C$17521,BC$8))*$C$9 -> 0 | BD12: =(SUMIFS(Profile!$E$2:$E$17521,Profile!$B$2:$B$17521,$B12,Profile!$C$2:$C$17521,BD$8))*$C$9 -> 0 | BE12: =(SUMIFS(Profile!$E$2:$E$17521,Profile!$B$2:$B$17521,$B12,Profile!$C$2:$C$17521,BE$8))*$C$9 -> 0 | BF12: =(SUMIFS(Profile!$E$2:$E$17521,Profile!$B$2:$B$17521,$B12,Profile!$C$2:$C$17521,BF$8))*$C$9 -> 0 | BG12: =(SUMIFS(Profile!$E$2:$E$17521,Profile!$B$2:$B$17521,$B12,Profile!$C$2:$C$17521,BG$8))*$C$9 -> 0 | BH12: =(SUMIFS(Profile!$E$2:$E$17521,Profile!$B$2:$B$17521,$B12,Profile!$C$2:$C$17521,BH$8))*$C$9 -> 0 | BI12: =(SUMIFS(Profile!$E$2:$E$17521,Profile!$B$2:$B$17521,$B12,Profile!$C$2:$C$17521,BI$8))*$C$9 -> 0 | ... CW12: =(SUMIFS(Profile!$E$2:$E$17521,Profile!$B$2:$B$17521,$B12,Profile!$C$2:$C$17521,CW$8))*$C$9 -> 0 | CX12: =SUM(CY12:ET12) -> 0 | CY12: =MAX(BB12-E12,0) -> 0 | CZ12: =MAX(BC12-F12,0) -> 0 | DA12: =MAX(BD12-G12,0) -> 0 | DB12: =MAX(BE12-H12,0) -> 0 | DC12: =MAX(BF12-I12,0) -> 0 | DD12: =MAX(BG12-J12,0) -> 0 | DE12: =MAX(BH12-K12,0) -> 0 | DF12: =MAX(BI12-L12,0) -> 0 | ... ET12: =MAX(CW12-AZ12,0) -> 0 | EU12: =SUM(EV12:GQ12) -> 0 | EV12: =BB12-CY12 -> 0 | EW12: =BC12-CZ12 -> 0 | EX12: =BD12-DA12 -> 0 | EY12: =BE12-DB12 -> 0 | EZ12: =BF12-DC12 -> 0 | FA12: =BG12-DD12 -> 0 | FB12: =BH12-DE12 -> 0 | FC12: =BI12-DF12 -> 0 | ... GQ12: =CW12-ET12 -> 0 | GR12: =SUM(GS12:IN12) -> 0 | GS12: =E12-EV12 -> 0 | GT12: =F12-EW12 -> 0 | GU12: =G12-EX12 -> 0 | GV12: =H12-EY12 -> 0 | GW12: =I12-EZ12 -> 0 | GX12: =J12-FA12 -> 0 | GY12: =K12-FB12 -> 0 | GZ12: =L12-FC12 -> 0 | ... IN12: =AZ12-GQ12 -> 0 | IO12: =MAX(IP12:KK12)-IF(KK12<>0,KK12,MIN(IP12:KK12)) -> 0 | IP12: =MAX((MIN(CY12+KK11,$IO$7))-GS12,0) -> 0 | IQ12: =MAX((MIN(CZ12+IP12,$IO$7))-GT12,0) -> 0 | IR12: =MAX((MIN(DA12+IQ12,$IO$7))-GU12,0) -> 0 | IS12: =MAX((MIN(DB12+IR12,$IO$7))-GV12,0) -> 0 | IT12: =MAX((MIN(DC12+IS12,$IO$7))-GW12,0) -> 0 | IU12: =MAX((MIN(DD12+IT12,$IO$7))-GX12,0) -> 0 | IV12: =MAX((MIN(DE12+IU12,$IO$7))-GY12,0) -> 0 | IW12: =MAX((MIN(DF12+IV12,$IO$7))-GZ12,0) -> 0 | IX12: =MAX((MIN(DG12+IW12,$IO$7))-HA12,0) -> 0 | ... KK12: =MAX((MIN(ET12+KJ12,$IO$7))-IN12,0) -> 0
A13: 1 | B13: =B12+1 -> 3 | C13: =C12+1 -> 43468 | D13: =SUM(E13:AZ13) -> 0 | E13: =(SUMIFS(Profile!$F$2:$F$17521,Profile!$B$2:$B$17521,$B13,Profile!$C$2:$C$17521,E$8))*$C$6 -> 0 | F13: =(SUMIFS(Profile!$F$2:$F$17521,Profile!$B$2:$B$17521,$B13,Profile!$C$2:$C$17521,F$8))*$C$6 -> 0 | G13: =(SUMIFS(Profile!$F$2:$F$17521,Profile!$B$2:$B$17521,$B13,Profile!$C$2:$C$17521,G$8))*$C$6 -> 0 | H13: =(SUMIFS(Profile!$F$2:$F$17521,Profile!$B$2:$B$17521,$B13,Profile!$C$2:$C$17521,H$8))*$C$6 -> 0 | I13: =(SUMIFS(Profile!$F$2:$F$17521,Profile!$B$2:$B$17521,$B13,Profile!$C$2:$C$17521,I$8))*$C$6 -> 0 | J13: =(SUMIFS(Profile!$F$2:$F$17521,Profile!$B$2:$B$17521,$B13,Profile!$C$2:$C$17521,J$8))*$C$6 -> 0 | K13: =(SUMIFS(Profile!$F$2:$F$17521,Profile!$B$2:$B$17521,$B13,Profile!$C$2:$C$17521,K$8))*$C$6 -> 0 | L13: =(SUMIFS(Profile!$F$2:$F$17521,Profile!$B$2:$B$17521,$B13,Profile!$C$2:$C$17521,L$8))*$C$6 -> 0 | ... AZ13: =(SUMIFS(Profile!$F$2:$F$17521,Profile!$B$2:$B$17521,$B13,Profile!$C$2:$C$17521,AZ$8))*$C$6 -> 0 | BA13: =SUM(BB13:CW13) -> 0 | BB13: =(SUMIFS(Profile!$E$2:$E$17521,Profile!$B$2:$B$17521,$B13,Profile!$C$2:$C$17521,BB$8))*$C$9 -> 0 | BC13: =(SUMIFS(Profile!$E$2:$E$17521,Profile!$B$2:$B$17521,$B13,Profile!$C$2:$C$17521,BC$8))*$C$9 -> 0 | BD13: =(SUMIFS(Profile!$E$2:$E$17521,Profile!$B$2:$B$17521,$B13,Profile!$C$2:$C$17521,BD$8))*$C$9 -> 0 | BE13: =(SUMIFS(Profile!$E$2:$E$17521,Profile!$B$2:$B$17521,$B13,Profile!$C$2:$C$17521,BE$8))*$C$9 -> 0 | BF13: =(SUMIFS(Profile!$E$2:$E$17521,Profile!$B$2:$B$17521,$B13,Profile!$C$2:$C$17521,BF$8))*$C$9 -> 0 | BG13: =(SUMIFS(Profile!$E$2:$E$17521,Profile!$B$2:$B$17521,$B13,Profile!$C$2:$C$17521,BG$8))*$C$9 -> 0 | BH13: =(SUMIFS(Profile!$E$2:$E$17521,Profile!$B$2:$B$17521,$B13,Profile!$C$2:$C$17521,BH$8))*$C$9 -> 0 | BI13: =(SUMIFS(Profile!$E$2:$E$17521,Profile!$B$2:$B$17521,$B13,Profile!$C$2:$C$17521,BI$8))*$C$9 -> 0 | ... CW13: =(SUMIFS(Profile!$E$2:$E$17521,Profile!$B$2:$B$17521,$B13,Profile!$C$2:$C$17521,CW$8))*$C$9 -> 0 | CX13: =SUM(CY13:ET13) -> 0 | CY13: =MAX(BB13-E13,0) -> 0 | CZ13: =MAX(BC13-F13,0) -> 0 | DA13: =MAX(BD13-G13,0) -> 0 | DB13: =MAX(BE13-H13,0) -> 0 | DC13: =MAX(BF13-I13,0) -> 0 | DD13: =MAX(BG13-J13,0) -> 0 | DE13: =MAX(BH13-K13,0) -> 0 | DF13: =MAX(BI13-L13,0) -> 0 | ... ET13: =MAX(CW13-AZ13,0) -> 0 | EU13: =SUM(EV13:GQ13) -> 0 | EV13: =BB13-CY13 -> 0 | EW13: =BC13-CZ13 -> 0 | EX13: =BD13-DA13 -> 0 | EY13: =BE13-DB13 -> 0 | EZ13: =BF13-DC13 -> 0 | FA13: =BG13-DD13 -> 0 | FB13: =BH13-DE13 -> 0 | FC13: =BI13-DF13 -> 0 | ... GQ13: =CW13-ET13 -> 0 | GR13: =SUM(GS13:IN13) -> 0 | GS13: =E13-EV13 -> 0 | GT13: =F13-EW13 -> 0 | GU13: =G13-EX13 -> 0 | GV13: =H13-EY13 -> 0 | GW13: =I13-EZ13 -> 0 | GX13: =J13-FA13 -> 0 | GY13: =K13-FB13 -> 0 | GZ13: =L13-FC13 -> 0 | ... IN13: =AZ13-GQ13 -> 0 | IO13: =MAX(IP13:KK13)-IF(KK13<>0,KK13,MIN(IP13:KK13)) -> 0 | IP13: =MAX((MIN(CY13+KK12,$IO$7))-GS13,0) -> 0 | IQ13: =MAX((MIN(CZ13+IP13,$IO$7))-GT13,0) -> 0 | IR13: =MAX((MIN(DA13+IQ13,$IO$7))-GU13,0) -> 0 | IS13: =MAX((MIN(DB13+IR13,$IO$7))-GV13,0) -> 0 | IT13: =MAX((MIN(DC13+IS13,$IO$7))-GW13,0) -> 0 | IU13: =MAX((MIN(DD13+IT13,$IO$7))-GX13,0) -> 0 | IV13: =MAX((MIN(DE13+IU13,$IO$7))-GY13,0) -> 0 | IW13: =MAX((MIN(DF13+IV13,$IO$7))-GZ13,0) -> 0 | IX13: =MAX((MIN(DG13+IW13,$IO$7))-HA13,0) -> 0 | ... KK13: =MAX((MIN(ET13+KJ13,$IO$7))-IN13,0) -> 0
A14: 1 | B14: =B13+1 -> 4 | C14: =C13+1 -> 43469 | D14: =SUM(E14:AZ14) -> 0 | E14: =(SUMIFS(Profile!$F$2:$F$17521,Profile!$B$2:$B$17521,$B14,Profile!$C$2:$C$17521,E$8))*$C$6 -> 0 | F14: =(SUMIFS(Profile!$F$2:$F$17521,Profile!$B$2:$B$17521,$B14,Profile!$C$2:$C$17521,F$8))*$C$6 -> 0 | G14: =(SUMIFS(Profile!$F$2:$F$17521,Profile!$B$2:$B$17521,$B14,Profile!$C$2:$C$17521,G$8))*$C$6 -> 0 | H14: =(SUMIFS(Profile!$F$2:$F$17521,Profile!$B$2:$B$17521,$B14,Profile!$C$2:$C$17521,H$8))*$C$6 -> 0 | I14: =(SUMIFS(Profile!$F$2:$F$17521,Profile!$B$2:$B$17521,$B14,Profile!$C$2:$C$17521,I$8))*$C$6 -> 0 | J14: =(SUMIFS(Profile!$F$2:$F$17521,Profile!$B$2:$B$17521,$B14,Profile!$C$2:$C$17521,J$8))*$C$6 -> 0 | K14: =(SUMIFS(Profile!$F$2:$F$17521,Profile!$B$2:$B$17521,$B14,Profile!$C$2:$C$17521,K$8))*$C$6 -> 0 | L14: =(SUMIFS(Profile!$F$2:$F$17521,Profile!$B$2:$B$17521,$B14,Profile!$C$2:$C$17521,L$8))*$C$6 -> 0 | ... AZ14: =(SUMIFS(Profile!$F$2:$F$17521,Profile!$B$2:$B$17521,$B14,Profile!$C$2:$C$17521,AZ$8))*$C$6 -> 0 | BA14: =SUM(BB14:CW14) -> 0 | BB14: =(SUMIFS(Profile!$E$2:$E$17521,Profile!$B$2:$B$17521,$B14,Profile!$C$2:$C$17521,BB$8))*$C$9 -> 0 | BC14: =(SUMIFS(Profile!$E$2:$E$17521,Profile!$B$2:$B$17521,$B14,Profile!$C$2:$C$17521,BC$8))*$C$9 -> 0 | BD14: =(SUMIFS(Profile!$E$2:$E$17521,Profile!$B$2:$B$17521,$B14,Profile!$C$2:$C$17521,BD$8))*$C$9 -> 0 | BE14: =(SUMIFS(Profile!$E$2:$E$17521,Profile!$B$2:$B$17521,$B14,Profile!$C$2:$C$17521,BE$8))*$C$9 -> 0 | BF14: =(SUMIFS(Profile!$E$2:$E$17521,Profile!$B$2:$B$17521,$B14,Profile!$C$2:$C$17521,BF$8))*$C$9 -> 0 | BG14: =(SUMIFS(Profile!$E$2:$E$17521,Profile!$B$2:$B$17521,$B14,Profile!$C$2:$C$17521,BG$8))*$C$9 -> 0 | BH14: =(SUMIFS(Profile!$E$2:$E$17521,Profile!$B$2:$B$17521,$B14,Profile!$C$2:$C$17521,BH$8))*$C$9 -> 0 | BI14: =(SUMIFS(Profile!$E$2:$E$17521,Profile!$B$2:$B$17521,$B14,Profile!$C$2:$C$17521,BI$8))*$C$9 -> 0 | ... CW14: =(SUMIFS(Profile!$E$2:$E$17521,Profile!$B$2:$B$17521,$B14,Profile!$C$2:$C$17521,CW$8))*$C$9 -> 0 | CX14: =SUM(CY14:ET14) -> 0 | CY14: =MAX(BB14-E14,0) -> 0 | CZ14: =MAX(BC14-F14,0) -> 0 | DA14: =MAX(BD14-G14,0) -> 0 | DB14: =MAX(BE14-H14,0) -> 0 | DC14: =MAX(BF14-I14,0) -> 0 | DD14: =MAX(BG14-J14,0) -> 0 | DE14: =MAX(BH14-K14,0) -> 0 | DF14: =MAX(BI14-L14,0) -> 0 | ... ET14: =MAX(CW14-AZ14,0) -> 0 | EU14: =SUM(EV14:GQ14) -> 0 | EV14: =BB14-CY14 -> 0 | EW14: =BC14-CZ14 -> 0 | EX14: =BD14-DA14 -> 0 | EY14: =BE14-DB14 -> 0 | EZ14: =BF14-DC14 -> 0 | FA14: =BG14-DD14 -> 0 | FB14: =BH14-DE14 -> 0 | FC14: =BI14-DF14 -> 0 | ... GQ14: =CW14-ET14 -> 0 | GR14: =SUM(GS14:IN14) -> 0 | GS14: =E14-EV14 -> 0 | GT14: =F14-EW14 -> 0 | GU14: =G14-EX14 -> 0 | GV14: =H14-EY14 -> 0 | GW14: =I14-EZ14 -> 0 | GX14: =J14-FA14 -> 0 | GY14: =K14-FB14 -> 0 | GZ14: =L14-FC14 -> 0 | ... IN14: =AZ14-GQ14 -> 0 | IO14: =MAX(IP14:KK14)-IF(KK14<>0,KK14,MIN(IP14:KK14)) -> 0 | IP14: =MAX((MIN(CY14+KK13,$IO$7))-GS14,0) -> 0 | IQ14: =MAX((MIN(CZ14+IP14,$IO$7))-GT14,0) -> 0 | IR14: =MAX((MIN(DA14+IQ14,$IO$7))-GU14,0) -> 0 | IS14: =MAX((MIN(DB14+IR14,$IO$7))-GV14,0) -> 0 | IT14: =MAX((MIN(DC14+IS14,$IO$7))-GW14,0) -> 0 | IU14: =MAX((MIN(DD14+IT14,$IO$7))-GX14,0) -> 0 | IV14: =MAX((MIN(DE14+IU14,$IO$7))-GY14,0) -> 0 | IW14: =MAX((MIN(DF14+IV14,$IO$7))-GZ14,0) -> 0 | IX14: =MAX((MIN(DG14+IW14,$IO$7))-HA14,0) -> 0 | ... KK14: =MAX((MIN(ET14+KJ14,$IO$7))-IN14,0) -> 0
A15: 1 | B15: =B14+1 -> 5 | C15: =C14+1 -> 43470 | D15: =SUM(E15:AZ15) -> 0 | E15: =(SUMIFS(Profile!$F$2:$F$17521,Profile!$B$2:$B$17521,$B15,Profile!$C$2:$C$17521,E$8))*$C$6 -> 0 | F15: =(SUMIFS(Profile!$F$2:$F$17521,Profile!$B$2:$B$17521,$B15,Profile!$C$2:$C$17521,F$8))*$C$6 -> 0 | G15: =(SUMIFS(Profile!$F$2:$F$17521,Profile!$B$2:$B$17521,$B15,Profile!$C$2:$C$17521,G$8))*$C$6 -> 0 | H15: =(SUMIFS(Profile!$F$2:$F$17521,Profile!$B$2:$B$17521,$B15,Profile!$C$2:$C$17521,H$8))*$C$6 -> 0 | I15: =(SUMIFS(Profile!$F$2:$F$17521,Profile!$B$2:$B$17521,$B15,Profile!$C$2:$C$17521,I$8))*$C$6 -> 0 | J15: =(SUMIFS(Profile!$F$2:$F$17521,Profile!$B$2:$B$17521,$B15,Profile!$C$2:$C$17521,J$8))*$C$6 -> 0 | K15: =(SUMIFS(Profile!$F$2:$F$17521,Profile!$B$2:$B$17521,$B15,Profile!$C$2:$C$17521,K$8))*$C$6 -> 0 | L15: =(SUMIFS(Profile!$F$2:$F$17521,Profile!$B$2:$B$17521,$B15,Profile!$C$2:$C$17521,L$8))*$C$6 -> 0 | ... AZ15: =(SUMIFS(Profile!$F$2:$F$17521,Profile!$B$2:$B$17521,$B15,Profile!$C$2:$C$17521,AZ$8))*$C$6 -> 0 | BA15: =SUM(BB15:CW15) -> 0 | BB15: =(SUMIFS(Profile!$E$2:$E$17521,Profile!$B$2:$B$17521,$B15,Profile!$C$2:$C$17521,BB$8))*$C$9 -> 0 | BC15: =(SUMIFS(Profile!$E$2:$E$17521,Profile!$B$2:$B$17521,$B15,Profile!$C$2:$C$17521,BC$8))*$C$9 -> 0 | BD15: =(SUMIFS(Profile!$E$2:$E$17521,Profile!$B$2:$B$17521,$B15,Profile!$C$2:$C$17521,BD$8))*$C$9 -> 0 | BE15: =(SUMIFS(Profile!$E$2:$E$17521,Profile!$B$2:$B$17521,$B15,Profile!$C$2:$C$17521,BE$8))*$C$9 -> 0 | BF15: =(SUMIFS(Profile!$E$2:$E$17521,Profile!$B$2:$B$17521,$B15,Profile!$C$2:$C$17521,BF$8))*$C$9 -> 0 | BG15: =(SUMIFS(Profile!$E$2:$E$17521,Profile!$B$2:$B$17521,$B15,Profile!$C$2:$C$17521,BG$8))*$C$9 -> 0 | BH15: =(SUMIFS(Profile!$E$2:$E$17521,Profile!$B$2:$B$17521,$B15,Profile!$C$2:$C$17521,BH$8))*$C$9 -> 0 | BI15: =(SUMIFS(Profile!$E$2:$E$17521,Profile!$B$2:$B$17521,$B15,Profile!$C$2:$C$17521,BI$8))*$C$9 -> 0 | ... CW15: =(SUMIFS(Profile!$E$2:$E$17521,Profile!$B$2:$B$17521,$B15,Profile!$C$2:$C$17521,CW$8))*$C$9 -> 0 | CX15: =SUM(CY15:ET15) -> 0 | CY15: =MAX(BB15-E15,0) -> 0 | CZ15: =MAX(BC15-F15,0) -> 0 | DA15: =MAX(BD15-G15,0) -> 0 | DB15: =MAX(BE15-H15,0) -> 0 | DC15: =MAX(BF15-I15,0) -> 0 | DD15: =MAX(BG15-J15,0) -> 0 | DE15: =MAX(BH15-K15,0) -> 0 | DF15: =MAX(BI15-L15,0) -> 0 | ... ET15: =MAX(CW15-AZ15,0) -> 0 | EU15: =SUM(EV15:GQ15) -> 0 | EV15: =BB15-CY15 -> 0 | EW15: =BC15-CZ15 -> 0 | EX15: =BD15-DA15 -> 0 | EY15: =BE15-DB15 -> 0 | EZ15: =BF15-DC15 -> 0 | FA15: =BG15-DD15 -> 0 | FB15: =BH15-DE15 -> 0 | FC15: =BI15-DF15 -> 0 | ... GQ15: =CW15-ET15 -> 0 | GR15: =SUM(GS15:IN15) -> 0 | GS15: =E15-EV15 -> 0 | GT15: =F15-EW15 -> 0 | GU15: =G15-EX15 -> 0 | GV15: =H15-EY15 -> 0 | GW15: =I15-EZ15 -> 0 | GX15: =J15-FA15 -> 0 | GY15: =K15-FB15 -> 0 | GZ15: =L15-FC15 -> 0 | ... IN15: =AZ15-GQ15 -> 0 | IO15: =MAX(IP15:KK15)-IF(KK15<>0,KK15,MIN(IP15:KK15)) -> 0 | IP15: =MAX((MIN(CY15+KK14,$IO$7))-GS15,0) -> 0 | IQ15: =MAX((MIN(CZ15+IP15,$IO$7))-GT15,0) -> 0 | IR15: =MAX((MIN(DA15+IQ15,$IO$7))-GU15,0) -> 0 | IS15: =MAX((MIN(DB15+IR15,$IO$7))-GV15,0) -> 0 | IT15: =MAX((MIN(DC15+IS15,$IO$7))-GW15,0) -> 0 | IU15: =MAX((MIN(DD15+IT15,$IO$7))-GX15,0) -> 0 | IV15: =MAX((MIN(DE15+IU15,$IO$7))-GY15,0) -> 0 | IW15: =MAX((MIN(DF15+IV15,$IO$7))-GZ15,0) -> 0 | IX15: =MAX((MIN(DG15+IW15,$IO$7))-HA15,0) -> 0 | ... KK15: =MAX((MIN(ET15+KJ15,$IO$7))-IN15,0) -> 0
A16: 1 | B16: =B15+1 -> 6 | C16: =C15+1 -> 43471 | D16: =SUM(E16:AZ16) -> 0 | E16: =(SUMIFS(Profile!$F$2:$F$17521,Profile!$B$2:$B$17521,$B16,Profile!$C$2:$C$17521,E$8))*$C$6 -> 0 | F16: =(SUMIFS(Profile!$F$2:$F$17521,Profile!$B$2:$B$17521,$B16,Profile!$C$2:$C$17521,F$8))*$C$6 -> 0 | G16: =(SUMIFS(Profile!$F$2:$F$17521,Profile!$B$2:$B$17521,$B16,Profile!$C$2:$C$17521,G$8))*$C$6 -> 0 | H16: =(SUMIFS(Profile!$F$2:$F$17521,Profile!$B$2:$B$17521,$B16,Profile!$C$2:$C$17521,H$8))*$C$6 -> 0 | I16: =(SUMIFS(Profile!$F$2:$F$17521,Profile!$B$2:$B$17521,$B16,Profile!$C$2:$C$17521,I$8))*$C$6 -> 0 | J16: =(SUMIFS(Profile!$F$2:$F$17521,Profile!$B$2:$B$17521,$B16,Profile!$C$2:$C$17521,J$8))*$C$6 -> 0 | K16: =(SUMIFS(Profile!$F$2:$F$17521,Profile!$B$2:$B$17521,$B16,Profile!$C$2:$C$17521,K$8))*$C$6 -> 0 | L16: =(SUMIFS(Profile!$F$2:$F$17521,Profile!$B$2:$B$17521,$B16,Profile!$C$2:$C$17521,L$8))*$C$6 -> 0 | ... AZ16: =(SUMIFS(Profile!$F$2:$F$17521,Profile!$B$2:$B$17521,$B16,Profile!$C$2:$C$17521,AZ$8))*$C$6 -> 0 | BA16: =SUM(BB16:CW16) -> 0 | BB16: =(SUMIFS(Profile!$E$2:$E$17521,Profile!$B$2:$B$17521,$B16,Profile!$C$2:$C$17521,BB$8))*$C$9 -> 0 | BC16: =(SUMIFS(Profile!$E$2:$E$17521,Profile!$B$2:$B$17521,$B16,Profile!$C$2:$C$17521,BC$8))*$C$9 -> 0 | BD16: =(SUMIFS(Profile!$E$2:$E$17521,Profile!$B$2:$B$17521,$B16,Profile!$C$2:$C$17521,BD$8))*$C$9 -> 0 | BE16: =(SUMIFS(Profile!$E$2:$E$17521,Profile!$B$2:$B$17521,$B16,Profile!$C$2:$C$17521,BE$8))*$C$9 -> 0 | BF16: =(SUMIFS(Profile!$E$2:$E$17521,Profile!$B$2:$B$17521,$B16,Profile!$C$2:$C$17521,BF$8))*$C$9 -> 0 | BG16: =(SUMIFS(Profile!$E$2:$E$17521,Profile!$B$2:$B$17521,$B16,Profile!$C$2:$C$17521,BG$8))*$C$9 -> 0 | BH16: =(SUMIFS(Profile!$E$2:$E$17521,Profile!$B$2:$B$17521,$B16,Profile!$C$2:$C$17521,BH$8))*$C$9 -> 0 | BI16: =(SUMIFS(Profile!$E$2:$E$17521,Profile!$B$2:$B$17521,$B16,Profile!$C$2:$C$17521,BI$8))*$C$9 -> 0 | ... CW16: =(SUMIFS(Profile!$E$2:$E$17521,Profile!$B$2:$B$17521,$B16,Profile!$C$2:$C$17521,CW$8))*$C$9 -> 0 | CX16: =SUM(CY16:ET16) -> 0 | CY16: =MAX(BB16-E16,0) -> 0 | CZ16: =MAX(BC16-F16,0) -> 0 | DA16: =MAX(BD16-G16,0) -> 0 | DB16: =MAX(BE16-H16,0) -> 0 | DC16: =MAX(BF16-I16,0) -> 0 | DD16: =MAX(BG16-J16,0) -> 0 | DE16: =MAX(BH16-K16,0) -> 0 | DF16: =MAX(BI16-L16,0) -> 0 | ... ET16: =MAX(CW16-AZ16,0) -> 0 | EU16: =SUM(EV16:GQ16) -> 0 | EV16: =BB16-CY16 -> 0 | EW16: =BC16-CZ16 -> 0 | EX16: =BD16-DA16 -> 0 | EY16: =BE16-DB16 -> 0 | EZ16: =BF16-DC16 -> 0 | FA16: =BG16-DD16 -> 0 | FB16: =BH16-DE16 -> 0 | FC16: =BI16-DF16 -> 0 | ... GQ16: =CW16-ET16 -> 0 | GR16: =SUM(GS16:IN16) -> 0 | GS16: =E16-EV16 -> 0 | GT16: =F16-EW16 -> 0 | GU16: =G16-EX16 -> 0 | GV16: =H16-EY16 -> 0 | GW16: =I16-EZ16 -> 0 | GX16: =J16-FA16 -> 0 | GY16: =K16-FB16 -> 0 | GZ16: =L16-FC16 -> 0 | ... IN16: =AZ16-GQ16 -> 0 | IO16: =MAX(IP16:KK16)-IF(KK16<>0,KK16,MIN(IP16:KK16)) -> 0 | IP16: =MAX((MIN(CY16+KK15,$IO$7))-GS16,0) -> 0 | IQ16: =MAX((MIN(CZ16+IP16,$IO$7))-GT16,0) -> 0 | IR16: =MAX((MIN(DA16+IQ16,$IO$7))-GU16,0) -> 0 | IS16: =MAX((MIN(DB16+IR16,$IO$7))-GV16,0) -> 0 | IT16: =MAX((MIN(DC16+IS16,$IO$7))-GW16,0) -> 0 | IU16: =MAX((MIN(DD16+IT16,$IO$7))-GX16,0) -> 0 | IV16: =MAX((MIN(DE16+IU16,$IO$7))-GY16,0) -> 0 | IW16: =MAX((MIN(DF16+IV16,$IO$7))-GZ16,0) -> 0 | IX16: =MAX((MIN(DG16+IW16,$IO$7))-HA16,0) -> 0 | ... KK16: =MAX((MIN(ET16+KJ16,$IO$7))-IN16,0) -> 0
A17: 1 | B17: =B16+1 -> 7 | C17: =C16+1 -> 43472 | D17: =SUM(E17:AZ17) -> 0 | E17: =(SUMIFS(Profile!$F$2:$F$17521,Profile!$B$2:$B$17521,$B17,Profile!$C$2:$C$17521,E$8))*$C$6 -> 0 | F17: =(SUMIFS(Profile!$F$2:$F$17521,Profile!$B$2:$B$17521,$B17,Profile!$C$2:$C$17521,F$8))*$C$6 -> 0 | G17: =(SUMIFS(Profile!$F$2:$F$17521,Profile!$B$2:$B$17521,$B17,Profile!$C$2:$C$17521,G$8))*$C$6 -> 0 | H17: =(SUMIFS(Profile!$F$2:$F$17521,Profile!$B$2:$B$17521,$B17,Profile!$C$2:$C$17521,H$8))*$C$6 -> 0 | I17: =(SUMIFS(Profile!$F$2:$F$17521,Profile!$B$2:$B$17521,$B17,Profile!$C$2:$C$17521,I$8))*$C$6 -> 0 | J17: =(SUMIFS(Profile!$F$2:$F$17521,Profile!$B$2:$B$17521,$B17,Profile!$C$2:$C$17521,J$8))*$C$6 -> 0 | K17: =(SUMIFS(Profile!$F$2:$F$17521,Profile!$B$2:$B$17521,$B17,Profile!$C$2:$C$17521,K$8))*$C$6 -> 0 | L17: =(SUMIFS(Profile!$F$2:$F$17521,Profile!$B$2:$B$17521,$B17,Profile!$C$2:$C$17521,L$8))*$C$6 -> 0 | ... AZ17: =(SUMIFS(Profile!$F$2:$F$17521,Profile!$B$2:$B$17521,$B17,Profile!$C$2:$C$17521,AZ$8))*$C$6 -> 0 | BA17: =SUM(BB17:CW17) -> 0 | BB17: =(SUMIFS(Profile!$E$2:$E$17521,Profile!$B$2:$B$17521,$B17,Profile!$C$2:$C$17521,BB$8))*$C$9 -> 0 | BC17: =(SUMIFS(Profile!$E$2:$E$17521,Profile!$B$2:$B$17521,$B17,Profile!$C$2:$C$17521,BC$8))*$C$9 -> 0 | BD17: =(SUMIFS(Profile!$E$2:$E$17521,Profile!$B$2:$B$17521,$B17,Profile!$C$2:$C$17521,BD$8))*$C$9 -> 0 | BE17: =(SUMIFS(Profile!$E$2:$E$17521,Profile!$B$2:$B$17521,$B17,Profile!$C$2:$C$17521,BE$8))*$C$9 -> 0 | BF17: =(SUMIFS(Profile!$E$2:$E$17521,Profile!$B$2:$B$17521,$B17,Profile!$C$2:$C$17521,BF$8))*$C$9 -> 0 | BG17: =(SUMIFS(Profile!$E$2:$E$17521,Profile!$B$2:$B$17521,$B17,Profile!$C$2:$C$17521,BG$8))*$C$9 -> 0 | BH17: =(SUMIFS(Profile!$E$2:$E$17521,Profile!$B$2:$B$17521,$B17,Profile!$C$2:$C$17521,BH$8))*$C$9 -> 0 | BI17: =(SUMIFS(Profile!$E$2:$E$17521,Profile!$B$2:$B$17521,$B17,Profile!$C$2:$C$17521,BI$8))*$C$9 -> 0 | ... CW17: =(SUMIFS(Profile!$E$2:$E$17521,Profile!$B$2:$B$17521,$B17,Profile!$C$2:$C$17521,CW$8))*$C$9 -> 0 | CX17: =SUM(CY17:ET17) -> 0 | CY17: =MAX(BB17-E17,0) -> 0 | CZ17: =MAX(BC17-F17,0) -> 0 | DA17: =MAX(BD17-G17,0) -> 0 | DB17: =MAX(BE17-H17,0) -> 0 | DC17: =MAX(BF17-I17,0) -> 0 | DD17: =MAX(BG17-J17,0) -> 0 | DE17: =MAX(BH17-K17,0) -> 0 | DF17: =MAX(BI17-L17,0) -> 0 | ... ET17: =MAX(CW17-AZ17,0) -> 0 | EU17: =SUM(EV17:GQ17) -> 0 | EV17: =BB17-CY17 -> 0 | EW17: =BC17-CZ17 -> 0 | EX17: =BD17-DA17 -> 0 | EY17: =BE17-DB17 -> 0 | EZ17: =BF17-DC17 -> 0 | FA17: =BG17-DD17 -> 0 | FB17: =BH17-DE17 -> 0 | FC17: =BI17-DF17 -> 0 | ... GQ17: =CW17-ET17 -> 0 | GR17: =SUM(GS17:IN17) -> 0 | GS17: =E17-EV17 -> 0 | GT17: =F17-EW17 -> 0 | GU17: =G17-EX17 -> 0 | GV17: =H17-EY17 -> 0 | GW17: =I17-EZ17 -> 0 | GX17: =J17-FA17 -> 0 | GY17: =K17-FB17 -> 0 | GZ17: =L17-FC17 -> 0 | ... IN17: =AZ17-GQ17 -> 0 | IO17: =MAX(IP17:KK17)-IF(KK17<>0,KK17,MIN(IP17:KK17)) -> 0 | IP17: =MAX((MIN(CY17+KK16,$IO$7))-GS17,0) -> 0 | IQ17: =MAX((MIN(CZ17+IP17,$IO$7))-GT17,0) -> 0 | IR17: =MAX((MIN(DA17+IQ17,$IO$7))-GU17,0) -> 0 | IS17: =MAX((MIN(DB17+IR17,$IO$7))-GV17,0) -> 0 | IT17: =MAX((MIN(DC17+IS17,$IO$7))-GW17,0) -> 0 | IU17: =MAX((MIN(DD17+IT17,$IO$7))-GX17,0) -> 0 | IV17: =MAX((MIN(DE17+IU17,$IO$7))-GY17,0) -> 0 | IW17: =MAX((MIN(DF17+IV17,$IO$7))-GZ17,0) -> 0 | IX17: =MAX((MIN(DG17+IW17,$IO$7))-HA17,0) -> 0 | ... KK17: =MAX((MIN(ET17+KJ17,$IO$7))-IN17,0) -> 0
A18: 1 | B18: =B17+1 -> 8 | C18: =C17+1 -> 43473 | D18: =SUM(E18:AZ18) -> 0 | E18: =(SUMIFS(Profile!$F$2:$F$17521,Profile!$B$2:$B$17521,$B18,Profile!$C$2:$C$17521,E$8))*$C$6 -> 0 | F18: =(SUMIFS(Profile!$F$2:$F$17521,Profile!$B$2:$B$17521,$B18,Profile!$C$2:$C$17521,F$8))*$C$6 -> 0 | G18: =(SUMIFS(Profile!$F$2:$F$17521,Profile!$B$2:$B$17521,$B18,Profile!$C$2:$C$17521,G$8))*$C$6 -> 0 | H18: =(SUMIFS(Profile!$F$2:$F$17521,Profile!$B$2:$B$17521,$B18,Profile!$C$2:$C$17521,H$8))*$C$6 -> 0 | I18: =(SUMIFS(Profile!$F$2:$F$17521,Profile!$B$2:$B$17521,$B18,Profile!$C$2:$C$17521,I$8))*$C$6 -> 0 | J18: =(SUMIFS(Profile!$F$2:$F$17521,Profile!$B$2:$B$17521,$B18,Profile!$C$2:$C$17521,J$8))*$C$6 -> 0 | K18: =(SUMIFS(Profile!$F$2:$F$17521,Profile!$B$2:$B$17521,$B18,Profile!$C$2:$C$17521,K$8))*$C$6 -> 0 | L18: =(SUMIFS(Profile!$F$2:$F$17521,Profile!$B$2:$B$17521,$B18,Profile!$C$2:$C$17521,L$8))*$C$6 -> 0 | ... AZ18: =(SUMIFS(Profile!$F$2:$F$17521,Profile!$B$2:$B$17521,$B18,Profile!$C$2:$C$17521,AZ$8))*$C$6 -> 0 | BA18: =SUM(BB18:CW18) -> 0 | BB18: =(SUMIFS(Profile!$E$2:$E$17521,Profile!$B$2:$B$17521,$B18,Profile!$C$2:$C$17521,BB$8))*$C$9 -> 0 | BC18: =(SUMIFS(Profile!$E$2:$E$17521,Profile!$B$2:$B$17521,$B18,Profile!$C$2:$C$17521,BC$8))*$C$9 -> 0 | BD18: =(SUMIFS(Profile!$E$2:$E$17521,Profile!$B$2:$B$17521,$B18,Profile!$C$2:$C$17521,BD$8))*$C$9 -> 0 | BE18: =(SUMIFS(Profile!$E$2:$E$17521,Profile!$B$2:$B$17521,$B18,Profile!$C$2:$C$17521,BE$8))*$C$9 -> 0 | BF18: =(SUMIFS(Profile!$E$2:$E$17521,Profile!$B$2:$B$17521,$B18,Profile!$C$2:$C$17521,BF$8))*$C$9 -> 0 | BG18: =(SUMIFS(Profile!$E$2:$E$17521,Profile!$B$2:$B$17521,$B18,Profile!$C$2:$C$17521,BG$8))*$C$9 -> 0 | BH18: =(SUMIFS(Profile!$E$2:$E$17521,Profile!$B$2:$B$17521,$B18,Profile!$C$2:$C$17521,BH$8))*$C$9 -> 0 | BI18: =(SUMIFS(Profile!$E$2:$E$17521,Profile!$B$2:$B$17521,$B18,Profile!$C$2:$C$17521,BI$8))*$C$9 -> 0 | ... CW18: =(SUMIFS(Profile!$E$2:$E$17521,Profile!$B$2:$B$17521,$B18,Profile!$C$2:$C$17521,CW$8))*$C$9 -> 0 | CX18: =SUM(CY18:ET18) -> 0 | CY18: =MAX(BB18-E18,0) -> 0 | CZ18: =MAX(BC18-F18,0) -> 0 | DA18: =MAX(BD18-G18,0) -> 0 | DB18: =MAX(BE18-H18,0) -> 0 | DC18: =MAX(BF18-I18,0) -> 0 | DD18: =MAX(BG18-J18,0) -> 0 | DE18: =MAX(BH18-K18,0) -> 0 | DF18: =MAX(BI18-L18,0) -> 0 | ... ET18: =MAX(CW18-AZ18,0) -> 0 | EU18: =SUM(EV18:GQ18) -> 0 | EV18: =BB18-CY18 -> 0 | EW18: =BC18-CZ18 -> 0 | EX18: =BD18-DA18 -> 0 | EY18: =BE18-DB18 -> 0 | EZ18: =BF18-DC18 -> 0 | FA18: =BG18-DD18 -> 0 | FB18: =BH18-DE18 -> 0 | FC18: =BI18-DF18 -> 0 | ... GQ18: =CW18-ET18 -> 0 | GR18: =SUM(GS18:IN18) -> 0 | GS18: =E18-EV18 -> 0 | GT18: =F18-EW18 -> 0 | GU18: =G18-EX18 -> 0 | GV18: =H18-EY18 -> 0 | GW18: =I18-EZ18 -> 0 | GX18: =J18-FA18 -> 0 | GY18: =K18-FB18 -> 0 | GZ18: =L18-FC18 -> 0 | ... IN18: =AZ18-GQ18 -> 0 | IO18: =MAX(IP18:KK18)-IF(KK18<>0,KK18,MIN(IP18:KK18)) -> 0 | IP18: =MAX((MIN(CY18+KK17,$IO$7))-GS18,0) -> 0 | IQ18: =MAX((MIN(CZ18+IP18,$IO$7))-GT18,0) -> 0 | IR18: =MAX((MIN(DA18+IQ18,$IO$7))-GU18,0) -> 0 | IS18: =MAX((MIN(DB18+IR18,$IO$7))-GV18,0) -> 0 | IT18: =MAX((MIN(DC18+IS18,$IO$7))-GW18,0) -> 0 | IU18: =MAX((MIN(DD18+IT18,$IO$7))-GX18,0) -> 0 | IV18: =MAX((MIN(DE18+IU18,$IO$7))-GY18,0) -> 0 | IW18: =MAX((MIN(DF18+IV18,$IO$7))-GZ18,0) -> 0 | IX18: =MAX((MIN(DG18+IW18,$IO$7))-HA18,0) -> 0 | ... KK18: =MAX((MIN(ET18+KJ18,$IO$7))-IN18,0) -> 0
A19: 1 | B19: =B18+1 -> 9 | C19: =C18+1 -> 43474 | D19: =SUM(E19:AZ19) -> 0 | E19: =(SUMIFS(Profile!$F$2:$F$17521,Profile!$B$2:$B$17521,$B19,Profile!$C$2:$C$17521,E$8))*$C$6 -> 0 | F19: =(SUMIFS(Profile!$F$2:$F$17521,Profile!$B$2:$B$17521,$B19,Profile!$C$2:$C$17521,F$8))*$C$6 -> 0 | G19: =(SUMIFS(Profile!$F$2:$F$17521,Profile!$B$2:$B$17521,$B19,Profile!$C$2:$C$17521,G$8))*$C$6 -> 0 | H19: =(SUMIFS(Profile!$F$2:$F$17521,Profile!$B$2:$B$17521,$B19,Profile!$C$2:$C$17521,H$8))*$C$6 -> 0 | I19: =(SUMIFS(Profile!$F$2:$F$17521,Profile!$B$2:$B$17521,$B19,Profile!$C$2:$C$17521,I$8))*$C$6 -> 0 | J19: =(SUMIFS(Profile!$F$2:$F$17521,Profile!$B$2:$B$17521,$B19,Profile!$C$2:$C$17521,J$8))*$C$6 -> 0 | K19: =(SUMIFS(Profile!$F$2:$F$17521,Profile!$B$2:$B$17521,$B19,Profile!$C$2:$C$17521,K$8))*$C$6 -> 0 | L19: =(SUMIFS(Profile!$F$2:$F$17521,Profile!$B$2:$B$17521,$B19,Profile!$C$2:$C$17521,L$8))*$C$6 -> 0 | ... AZ19: =(SUMIFS(Profile!$F$2:$F$17521,Profile!$B$2:$B$17521,$B19,Profile!$C$2:$C$17521,AZ$8))*$C$6 -> 0 | BA19: =SUM(BB19:CW19) -> 0 | BB19: =(SUMIFS(Profile!$E$2:$E$17521,Profile!$B$2:$B$17521,$B19,Profile!$C$2:$C$17521,BB$8))*$C$9 -> 0 | BC19: =(SUMIFS(Profile!$E$2:$E$17521,Profile!$B$2:$B$17521,$B19,Profile!$C$2:$C$17521,BC$8))*$C$9 -> 0 | BD19: =(SUMIFS(Profile!$E$2:$E$17521,Profile!$B$2:$B$17521,$B19,Profile!$C$2:$C$17521,BD$8))*$C$9 -> 0 | BE19: =(SUMIFS(Profile!$E$2:$E$17521,Profile!$B$2:$B$17521,$B19,Profile!$C$2:$C$17521,BE$8))*$C$9 -> 0 | BF19: =(SUMIFS(Profile!$E$2:$E$17521,Profile!$B$2:$B$17521,$B19,Profile!$C$2:$C$17521,BF$8))*$C$9 -> 0 | BG19: =(SUMIFS(Profile!$E$2:$E$17521,Profile!$B$2:$B$17521,$B19,Profile!$C$2:$C$17521,BG$8))*$C$9 -> 0 | BH19: =(SUMIFS(Profile!$E$2:$E$17521,Profile!$B$2:$B$17521,$B19,Profile!$C$2:$C$17521,BH$8))*$C$9 -> 0 | BI19: =(SUMIFS(Profile!$E$2:$E$17521,Profile!$B$2:$B$17521,$B19,Profile!$C$2:$C$17521,BI$8))*$C$9 -> 0 | ... CW19: =(SUMIFS(Profile!$E$2:$E$17521,Profile!$B$2:$B$17521,$B19,Profile!$C$2:$C$17521,CW$8))*$C$9 -> 0 | CX19: =SUM(CY19:ET19) -> 0 | CY19: =MAX(BB19-E19,0) -> 0 | CZ19: =MAX(BC19-F19,0) -> 0 | DA19: =MAX(BD19-G19,0) -> 0 | DB19: =MAX(BE19-H19,0) -> 0 | DC19: =MAX(BF19-I19,0) -> 0 | DD19: =MAX(BG19-J19,0) -> 0 | DE19: =MAX(BH19-K19,0) -> 0 | DF19: =MAX(BI19-L19,0) -> 0 | ... ET19: =MAX(CW19-AZ19,0) -> 0 | EU19: =SUM(EV19:GQ19) -> 0 | EV19: =BB19-CY19 -> 0 | EW19: =BC19-CZ19 -> 0 | EX19: =BD19-DA19 -> 0 | EY19: =BE19-DB19 -> 0 | EZ19: =BF19-DC19 -> 0 | FA19: =BG19-DD19 -> 0 | FB19: =BH19-DE19 -> 0 | FC19: =BI19-DF19 -> 0 | ... GQ19: =CW19-ET19 -> 0 | GR19: =SUM(GS19:IN19) -> 0 | GS19: =E19-EV19 -> 0 | GT19: =F19-EW19 -> 0 | GU19: =G19-EX19 -> 0 | GV19: =H19-EY19 -> 0 | GW19: =I19-EZ19 -> 0 | GX19: =J19-FA19 -> 0 | GY19: =K19-FB19 -> 0 | GZ19: =L19-FC19 -> 0 | ... IN19: =AZ19-GQ19 -> 0 | IO19: =MAX(IP19:KK19)-IF(KK19<>0,KK19,MIN(IP19:KK19)) -> 0 | IP19: =MAX((MIN(CY19+KK18,$IO$7))-GS19,0) -> 0 | IQ19: =MAX((MIN(CZ19+IP19,$IO$7))-GT19,0) -> 0 | IR19: =MAX((MIN(DA19+IQ19,$IO$7))-GU19,0) -> 0 | IS19: =MAX((MIN(DB19+IR19,$IO$7))-GV19,0) -> 0 | IT19: =MAX((MIN(DC19+IS19,$IO$7))-GW19,0) -> 0 | IU19: =MAX((MIN(DD19+IT19,$IO$7))-GX19,0) -> 0 | IV19: =MAX((MIN(DE19+IU19,$IO$7))-GY19,0) -> 0 | IW19: =MAX((MIN(DF19+IV19,$IO$7))-GZ19,0) -> 0 | IX19: =MAX((MIN(DG19+IW19,$IO$7))-HA19,0) -> 0 | ... KK19: =MAX((MIN(ET19+KJ19,$IO$7))-IN19,0) -> 0
A20: 1 | B20: =B19+1 -> 10 | C20: =C19+1 -> 43475 | D20: =SUM(E20:AZ20) -> 0 | E20: =(SUMIFS(Profile!$F$2:$F$17521,Profile!$B$2:$B$17521,$B20,Profile!$C$2:$C$17521,E$8))*$C$6 -> 0 | F20: =(SUMIFS(Profile!$F$2:$F$17521,Profile!$B$2:$B$17521,$B20,Profile!$C$2:$C$17521,F$8))*$C$6 -> 0 | G20: =(SUMIFS(Profile!$F$2:$F$17521,Profile!$B$2:$B$17521,$B20,Profile!$C$2:$C$17521,G$8))*$C$6 -> 0 | H20: =(SUMIFS(Profile!$F$2:$F$17521,Profile!$B$2:$B$17521,$B20,Profile!$C$2:$C$17521,H$8))*$C$6 -> 0 | I20: =(SUMIFS(Profile!$F$2:$F$17521,Profile!$B$2:$B$17521,$B20,Profile!$C$2:$C$17521,I$8))*$C$6 -> 0 | J20: =(SUMIFS(Profile!$F$2:$F$17521,Profile!$B$2:$B$17521,$B20,Profile!$C$2:$C$17521,J$8))*$C$6 -> 0 | K20: =(SUMIFS(Profile!$F$2:$F$17521,Profile!$B$2:$B$17521,$B20,Profile!$C$2:$C$17521,K$8))*$C$6 -> 0 | L20: =(SUMIFS(Profile!$F$2:$F$17521,Profile!$B$2:$B$17521,$B20,Profile!$C$2:$C$17521,L$8))*$C$6 -> 0 | ... AZ20: =(SUMIFS(Profile!$F$2:$F$17521,Profile!$B$2:$B$17521,$B20,Profile!$C$2:$C$17521,AZ$8))*$C$6 -> 0 | BA20: =SUM(BB20:CW20) -> 0 | BB20: =(SUMIFS(Profile!$E$2:$E$17521,Profile!$B$2:$B$17521,$B20,Profile!$C$2:$C$17521,BB$8))*$C$9 -> 0 | BC20: =(SUMIFS(Profile!$E$2:$E$17521,Profile!$B$2:$B$17521,$B20,Profile!$C$2:$C$17521,BC$8))*$C$9 -> 0 | BD20: =(SUMIFS(Profile!$E$2:$E$17521,Profile!$B$2:$B$17521,$B20,Profile!$C$2:$C$17521,BD$8))*$C$9 -> 0 | BE20: =(SUMIFS(Profile!$E$2:$E$17521,Profile!$B$2:$B$17521,$B20,Profile!$C$2:$C$17521,BE$8))*$C$9 -> 0 | BF20: =(SUMIFS(Profile!$E$2:$E$17521,Profile!$B$2:$B$17521,$B20,Profile!$C$2:$C$17521,BF$8))*$C$9 -> 0 | BG20: =(SUMIFS(Profile!$E$2:$E$17521,Profile!$B$2:$B$17521,$B20,Profile!$C$2:$C$17521,BG$8))*$C$9 -> 0 | BH20: =(SUMIFS(Profile!$E$2:$E$17521,Profile!$B$2:$B$17521,$B20,Profile!$C$2:$C$17521,BH$8))*$C$9 -> 0 | BI20: =(SUMIFS(Profile!$E$2:$E$17521,Profile!$B$2:$B$17521,$B20,Profile!$C$2:$C$17521,BI$8))*$C$9 -> 0 | ... CW20: =(SUMIFS(Profile!$E$2:$E$17521,Profile!$B$2:$B$17521,$B20,Profile!$C$2:$C$17521,CW$8))*$C$9 -> 0 | CX20: =SUM(CY20:ET20) -> 0 | CY20: =MAX(BB20-E20,0) -> 0 | CZ20: =MAX(BC20-F20,0) -> 0 | DA20: =MAX(BD20-G20,0) -> 0 | DB20: =MAX(BE20-H20,0) -> 0 | DC20: =MAX(BF20-I20,0) -> 0 | DD20: =MAX(BG20-J20,0) -> 0 | DE20: =MAX(BH20-K20,0) -> 0 | DF20: =MAX(BI20-L20,0) -> 0 | ... ET20: =MAX(CW20-AZ20,0) -> 0 | EU20: =SUM(EV20:GQ20) -> 0 | EV20: =BB20-CY20 -> 0 | EW20: =BC20-CZ20 -> 0 | EX20: =BD20-DA20 -> 0 | EY20: =BE20-DB20 -> 0 | EZ20: =BF20-DC20 -> 0 | FA20: =BG20-DD20 -> 0 | FB20: =BH20-DE20 -> 0 | FC20: =BI20-DF20 -> 0 | ... GQ20: =CW20-ET20 -> 0 | GR20: =SUM(GS20:IN20) -> 0 | GS20: =E20-EV20 -> 0 | GT20: =F20-EW20 -> 0 | GU20: =G20-EX20 -> 0 | GV20: =H20-EY20 -> 0 | GW20: =I20-EZ20 -> 0 | GX20: =J20-FA20 -> 0 | GY20: =K20-FB20 -> 0 | GZ20: =L20-FC20 -> 0 | ... IN20: =AZ20-GQ20 -> 0 | IO20: =MAX(IP20:KK20)-IF(KK20<>0,KK20,MIN(IP20:KK20)) -> 0 | IP20: =MAX((MIN(CY20+KK19,$IO$7))-GS20,0) -> 0 | IQ20: =MAX((MIN(CZ20+IP20,$IO$7))-GT20,0) -> 0 | IR20: =MAX((MIN(DA20+IQ20,$IO$7))-GU20,0) -> 0 | IS20: =MAX((MIN(DB20+IR20,$IO$7))-GV20,0) -> 0 | IT20: =MAX((MIN(DC20+IS20,$IO$7))-GW20,0) -> 0 | IU20: =MAX((MIN(DD20+IT20,$IO$7))-GX20,0) -> 0 | IV20: =MAX((MIN(DE20+IU20,$IO$7))-GY20,0) -> 0 | IW20: =MAX((MIN(DF20+IV20,$IO$7))-GZ20,0) -> 0 | IX20: =MAX((MIN(DG20+IW20,$IO$7))-HA20,0) -> 0 | ... KK20: =MAX((MIN(ET20+KJ20,$IO$7))-IN20,0) -> 0
A21: 1 | B21: =B20+1 -> 11 | C21: =C20+1 -> 43476 | D21: =SUM(E21:AZ21) -> 0 | E21: =(SUMIFS(Profile!$F$2:$F$17521,Profile!$B$2:$B$17521,$B21,Profile!$C$2:$C$17521,E$8))*$C$6 -> 0 | F21: =(SUMIFS(Profile!$F$2:$F$17521,Profile!$B$2:$B$17521,$B21,Profile!$C$2:$C$17521,F$8))*$C$6 -> 0 | G21: =(SUMIFS(Profile!$F$2:$F$17521,Profile!$B$2:$B$17521,$B21,Profile!$C$2:$C$17521,G$8))*$C$6 -> 0 | H21: =(SUMIFS(Profile!$F$2:$F$17521,Profile!$B$2:$B$17521,$B21,Profile!$C$2:$C$17521,H$8))*$C$6 -> 0 | I21: =(SUMIFS(Profile!$F$2:$F$17521,Profile!$B$2:$B$17521,$B21,Profile!$C$2:$C$17521,I$8))*$C$6 -> 0 | J21: =(SUMIFS(Profile!$F$2:$F$17521,Profile!$B$2:$B$17521,$B21,Profile!$C$2:$C$17521,J$8))*$C$6 -> 0 | K21: =(SUMIFS(Profile!$F$2:$F$17521,Profile!$B$2:$B$17521,$B21,Profile!$C$2:$C$17521,K$8))*$C$6 -> 0 | L21: =(SUMIFS(Profile!$F$2:$F$17521,Profile!$B$2:$B$17521,$B21,Profile!$C$2:$C$17521,L$8))*$C$6 -> 0 | ... AZ21: =(SUMIFS(Profile!$F$2:$F$17521,Profile!$B$2:$B$17521,$B21,Profile!$C$2:$C$17521,AZ$8))*$C$6 -> 0 | BA21: =SUM(BB21:CW21) -> 0 | BB21: =(SUMIFS(Profile!$E$2:$E$17521,Profile!$B$2:$B$17521,$B21,Profile!$C$2:$C$17521,BB$8))*$C$9 -> 0 | BC21: =(SUMIFS(Profile!$E$2:$E$17521,Profile!$B$2:$B$17521,$B21,Profile!$C$2:$C$17521,BC$8))*$C$9 -> 0 | BD21: =(SUMIFS(Profile!$E$2:$E$17521,Profile!$B$2:$B$17521,$B21,Profile!$C$2:$C$17521,BD$8))*$C$9 -> 0 | BE21: =(SUMIFS(Profile!$E$2:$E$17521,Profile!$B$2:$B$17521,$B21,Profile!$C$2:$C$17521,BE$8))*$C$9 -> 0 | BF21: =(SUMIFS(Profile!$E$2:$E$17521,Profile!$B$2:$B$17521,$B21,Profile!$C$2:$C$17521,BF$8))*$C$9 -> 0 | BG21: =(SUMIFS(Profile!$E$2:$E$17521,Profile!$B$2:$B$17521,$B21,Profile!$C$2:$C$17521,BG$8))*$C$9 -> 0 | BH21: =(SUMIFS(Profile!$E$2:$E$17521,Profile!$B$2:$B$17521,$B21,Profile!$C$2:$C$17521,BH$8))*$C$9 -> 0 | BI21: =(SUMIFS(Profile!$E$2:$E$17521,Profile!$B$2:$B$17521,$B21,Profile!$C$2:$C$17521,BI$8))*$C$9 -> 0 | ... CW21: =(SUMIFS(Profile!$E$2:$E$17521,Profile!$B$2:$B$17521,$B21,Profile!$C$2:$C$17521,CW$8))*$C$9 -> 0 | CX21: =SUM(CY21:ET21) -> 0 | CY21: =MAX(BB21-E21,0) -> 0 | CZ21: =MAX(BC21-F21,0) -> 0 | DA21: =MAX(BD21-G21,0) -> 0 | DB21: =MAX(BE21-H21,0) -> 0 | DC21: =MAX(BF21-I21,0) -> 0 | DD21: =MAX(BG21-J21,0) -> 0 | DE21: =MAX(BH21-K21,0) -> 0 | DF21: =MAX(BI21-L21,0) -> 0 | ... ET21: =MAX(CW21-AZ21,0) -> 0 | EU21: =SUM(EV21:GQ21) -> 0 | EV21: =BB21-CY21 -> 0 | EW21: =BC21-CZ21 -> 0 | EX21: =BD21-DA21 -> 0 | EY21: =BE21-DB21 -> 0 | EZ21: =BF21-DC21 -> 0 | FA21: =BG21-DD21 -> 0 | FB21: =BH21-DE21 -> 0 | FC21: =BI21-DF21 -> 0 | ... GQ21: =CW21-ET21 -> 0 | GR21: =SUM(GS21:IN21) -> 0 | GS21: =E21-EV21 -> 0 | GT21: =F21-EW21 -> 0 | GU21: =G21-EX21 -> 0 | GV21: =H21-EY21 -> 0 | GW21: =I21-EZ21 -> 0 | GX21: =J21-FA21 -> 0 | GY21: =K21-FB21 -> 0 | GZ21: =L21-FC21 -> 0 | ... IN21: =AZ21-GQ21 -> 0 | IO21: =MAX(IP21:KK21)-IF(KK21<>0,KK21,MIN(IP21:KK21)) -> 0 | IP21: =MAX((MIN(CY21+KK20,$IO$7))-GS21,0) -> 0 | IQ21: =MAX((MIN(CZ21+IP21,$IO$7))-GT21,0) -> 0 | IR21: =MAX((MIN(DA21+IQ21,$IO$7))-GU21,0) -> 0 | IS21: =MAX((MIN(DB21+IR21,$IO$7))-GV21,0) -> 0 | IT21: =MAX((MIN(DC21+IS21,$IO$7))-GW21,0) -> 0 | IU21: =MAX((MIN(DD21+IT21,$IO$7))-GX21,0) -> 0 | IV21: =MAX((MIN(DE21+IU21,$IO$7))-GY21,0) -> 0 | IW21: =MAX((MIN(DF21+IV21,$IO$7))-GZ21,0) -> 0 | IX21: =MAX((MIN(DG21+IW21,$IO$7))-HA21,0) -> 0 | ... KK21: =MAX((MIN(ET21+KJ21,$IO$7))-IN21,0) -> 0
A22: 1 | B22: =B21+1 -> 12 | C22: =C21+1 -> 43477 | D22: =SUM(E22:AZ22) -> 0 | E22: =(SUMIFS(Profile!$F$2:$F$17521,Profile!$B$2:$B$17521,$B22,Profile!$C$2:$C$17521,E$8))*$C$6 -> 0 | F22: =(SUMIFS(Profile!$F$2:$F$17521,Profile!$B$2:$B$17521,$B22,Profile!$C$2:$C$17521,F$8))*$C$6 -> 0 | G22: =(SUMIFS(Profile!$F$2:$F$17521,Profile!$B$2:$B$17521,$B22,Profile!$C$2:$C$17521,G$8))*$C$6 -> 0 | H22: =(SUMIFS(Profile!$F$2:$F$17521,Profile!$B$2:$B$17521,$B22,Profile!$C$2:$C$17521,H$8))*$C$6 -> 0 | I22: =(SUMIFS(Profile!$F$2:$F$17521,Profile!$B$2:$B$17521,$B22,Profile!$C$2:$C$17521,I$8))*$C$6 -> 0 | J22: =(SUMIFS(Profile!$F$2:$F$17521,Profile!$B$2:$B$17521,$B22,Profile!$C$2:$C$17521,J$8))*$C$6 -> 0 | K22: =(SUMIFS(Profile!$F$2:$F$17521,Profile!$B$2:$B$17521,$B22,Profile!$C$2:$C$17521,K$8))*$C$6 -> 0 | L22: =(SUMIFS(Profile!$F$2:$F$17521,Profile!$B$2:$B$17521,$B22,Profile!$C$2:$C$17521,L$8))*$C$6 -> 0 | ... AZ22: =(SUMIFS(Profile!$F$2:$F$17521,Profile!$B$2:$B$17521,$B22,Profile!$C$2:$C$17521,AZ$8))*$C$6 -> 0 | BA22: =SUM(BB22:CW22) -> 0 | BB22: =(SUMIFS(Profile!$E$2:$E$17521,Profile!$B$2:$B$17521,$B22,Profile!$C$2:$C$17521,BB$8))*$C$9 -> 0 | BC22: =(SUMIFS(Profile!$E$2:$E$17521,Profile!$B$2:$B$17521,$B22,Profile!$C$2:$C$17521,BC$8))*$C$9 -> 0 | BD22: =(SUMIFS(Profile!$E$2:$E$17521,Profile!$B$2:$B$17521,$B22,Profile!$C$2:$C$17521,BD$8))*$C$9 -> 0 | BE22: =(SUMIFS(Profile!$E$2:$E$17521,Profile!$B$2:$B$17521,$B22,Profile!$C$2:$C$17521,BE$8))*$C$9 -> 0 | BF22: =(SUMIFS(Profile!$E$2:$E$17521,Profile!$B$2:$B$17521,$B22,Profile!$C$2:$C$17521,BF$8))*$C$9 -> 0 | BG22: =(SUMIFS(Profile!$E$2:$E$17521,Profile!$B$2:$B$17521,$B22,Profile!$C$2:$C$17521,BG$8))*$C$9 -> 0 | BH22: =(SUMIFS(Profile!$E$2:$E$17521,Profile!$B$2:$B$17521,$B22,Profile!$C$2:$C$17521,BH$8))*$C$9 -> 0 | BI22: =(SUMIFS(Profile!$E$2:$E$17521,Profile!$B$2:$B$17521,$B22,Profile!$C$2:$C$17521,BI$8))*$C$9 -> 0 | ... CW22: =(SUMIFS(Profile!$E$2:$E$17521,Profile!$B$2:$B$17521,$B22,Profile!$C$2:$C$17521,CW$8))*$C$9 -> 0 | CX22: =SUM(CY22:ET22) -> 0 | CY22: =MAX(BB22-E22,0) -> 0 | CZ22: =MAX(BC22-F22,0) -> 0 | DA22: =MAX(BD22-G22,0) -> 0 | DB22: =MAX(BE22-H22,0) -> 0 | DC22: =MAX(BF22-I22,0) -> 0 | DD22: =MAX(BG22-J22,0) -> 0 | DE22: =MAX(BH22-K22,0) -> 0 | DF22: =MAX(BI22-L22,0) -> 0 | ... ET22: =MAX(CW22-AZ22,0) -> 0 | EU22: =SUM(EV22:GQ22) -> 0 | EV22: =BB22-CY22 -> 0 | EW22: =BC22-CZ22 -> 0 | EX22: =BD22-DA22 -> 0 | EY22: =BE22-DB22 -> 0 | EZ22: =BF22-DC22 -> 0 | FA22: =BG22-DD22 -> 0 | FB22: =BH22-DE22 -> 0 | FC22: =BI22-DF22 -> 0 | ... GQ22: =CW22-ET22 -> 0 | GR22: =SUM(GS22:IN22) -> 0 | GS22: =E22-EV22 -> 0 | GT22: =F22-EW22 -> 0 | GU22: =G22-EX22 -> 0 | GV22: =H22-EY22 -> 0 | GW22: =I22-EZ22 -> 0 | GX22: =J22-FA22 -> 0 | GY22: =K22-FB22 -> 0 | GZ22: =L22-FC22 -> 0 | ... IN22: =AZ22-GQ22 -> 0 | IO22: =MAX(IP22:KK22)-IF(KK22<>0,KK22,MIN(IP22:KK22)) -> 0 | IP22: =MAX((MIN(CY22+KK21,$IO$7))-GS22,0) -> 0 | IQ22: =MAX((MIN(CZ22+IP22,$IO$7))-GT22,0) -> 0 | IR22: =MAX((MIN(DA22+IQ22,$IO$7))-GU22,0) -> 0 | IS22: =MAX((MIN(DB22+IR22,$IO$7))-GV22,0) -> 0 | IT22: =MAX((MIN(DC22+IS22,$IO$7))-GW22,0) -> 0 | IU22: =MAX((MIN(DD22+IT22,$IO$7))-GX22,0) -> 0 | IV22: =MAX((MIN(DE22+IU22,$IO$7))-GY22,0) -> 0 | IW22: =MAX((MIN(DF22+IV22,$IO$7))-GZ22,0) -> 0 | IX22: =MAX((MIN(DG22+IW22,$IO$7))-HA22,0) -> 0 | ... KK22: =MAX((MIN(ET22+KJ22,$IO$7))-IN22,0) -> 0
A23: 1 | B23: =B22+1 -> 13 | C23: =C22+1 -> 43478 | D23: =SUM(E23:AZ23) -> 0 | E23: =(SUMIFS(Profile!$F$2:$F$17521,Profile!$B$2:$B$17521,$B23,Profile!$C$2:$C$17521,E$8))*$C$6 -> 0 | F23: =(SUMIFS(Profile!$F$2:$F$17521,Profile!$B$2:$B$17521,$B23,Profile!$C$2:$C$17521,F$8))*$C$6 -> 0 | G23: =(SUMIFS(Profile!$F$2:$F$17521,Profile!$B$2:$B$17521,$B23,Profile!$C$2:$C$17521,G$8))*$C$6 -> 0 | H23: =(SUMIFS(Profile!$F$2:$F$17521,Profile!$B$2:$B$17521,$B23,Profile!$C$2:$C$17521,H$8))*$C$6 -> 0 | I23: =(SUMIFS(Profile!$F$2:$F$17521,Profile!$B$2:$B$17521,$B23,Profile!$C$2:$C$17521,I$8))*$C$6 -> 0 | J23: =(SUMIFS(Profile!$F$2:$F$17521,Profile!$B$2:$B$17521,$B23,Profile!$C$2:$C$17521,J$8))*$C$6 -> 0 | K23: =(SUMIFS(Profile!$F$2:$F$17521,Profile!$B$2:$B$17521,$B23,Profile!$C$2:$C$17521,K$8))*$C$6 -> 0 | L23: =(SUMIFS(Profile!$F$2:$F$17521,Profile!$B$2:$B$17521,$B23,Profile!$C$2:$C$17521,L$8))*$C$6 -> 0 | ... AZ23: =(SUMIFS(Profile!$F$2:$F$17521,Profile!$B$2:$B$17521,$B23,Profile!$C$2:$C$17521,AZ$8))*$C$6 -> 0 | BA23: =SUM(BB23:CW23) -> 0 | BB23: =(SUMIFS(Profile!$E$2:$E$17521,Profile!$B$2:$B$17521,$B23,Profile!$C$2:$C$17521,BB$8))*$C$9 -> 0 | BC23: =(SUMIFS(Profile!$E$2:$E$17521,Profile!$B$2:$B$17521,$B23,Profile!$C$2:$C$17521,BC$8))*$C$9 -> 0 | BD23: =(SUMIFS(Profile!$E$2:$E$17521,Profile!$B$2:$B$17521,$B23,Profile!$C$2:$C$17521,BD$8))*$C$9 -> 0 | BE23: =(SUMIFS(Profile!$E$2:$E$17521,Profile!$B$2:$B$17521,$B23,Profile!$C$2:$C$17521,BE$8))*$C$9 -> 0 | BF23: =(SUMIFS(Profile!$E$2:$E$17521,Profile!$B$2:$B$17521,$B23,Profile!$C$2:$C$17521,BF$8))*$C$9 -> 0 | BG23: =(SUMIFS(Profile!$E$2:$E$17521,Profile!$B$2:$B$17521,$B23,Profile!$C$2:$C$17521,BG$8))*$C$9 -> 0 | BH23: =(SUMIFS(Profile!$E$2:$E$17521,Profile!$B$2:$B$17521,$B23,Profile!$C$2:$C$17521,BH$8))*$C$9 -> 0 | BI23: =(SUMIFS(Profile!$E$2:$E$17521,Profile!$B$2:$B$17521,$B23,Profile!$C$2:$C$17521,BI$8))*$C$9 -> 0 | ... CW23: =(SUMIFS(Profile!$E$2:$E$17521,Profile!$B$2:$B$17521,$B23,Profile!$C$2:$C$17521,CW$8))*$C$9 -> 0 | CX23: =SUM(CY23:ET23) -> 0 | CY23: =MAX(BB23-E23,0) -> 0 | CZ23: =MAX(BC23-F23,0) -> 0 | DA23: =MAX(BD23-G23,0) -> 0 | DB23: =MAX(BE23-H23,0) -> 0 | DC23: =MAX(BF23-I23,0) -> 0 | DD23: =MAX(BG23-J23,0) -> 0 | DE23: =MAX(BH23-K23,0) -> 0 | DF23: =MAX(BI23-L23,0) -> 0 | ... ET23: =MAX(CW23-AZ23,0) -> 0 | EU23: =SUM(EV23:GQ23) -> 0 | EV23: =BB23-CY23 -> 0 | EW23: =BC23-CZ23 -> 0 | EX23: =BD23-DA23 -> 0 | EY23: =BE23-DB23 -> 0 | EZ23: =BF23-DC23 -> 0 | FA23: =BG23-DD23 -> 0 | FB23: =BH23-DE23 -> 0 | FC23: =BI23-DF23 -> 0 | ... GQ23: =CW23-ET23 -> 0 | GR23: =SUM(GS23:IN23) -> 0 | GS23: =E23-EV23 -> 0 | GT23: =F23-EW23 -> 0 | GU23: =G23-EX23 -> 0 | GV23: =H23-EY23 -> 0 | GW23: =I23-EZ23 -> 0 | GX23: =J23-FA23 -> 0 | GY23: =K23-FB23 -> 0 | GZ23: =L23-FC23 -> 0 | ... IN23: =AZ23-GQ23 -> 0 | IO23: =MAX(IP23:KK23)-IF(KK23<>0,KK23,MIN(IP23:KK23)) -> 0 | IP23: =MAX((MIN(CY23+KK22,$IO$7))-GS23,0) -> 0 | IQ23: =MAX((MIN(CZ23+IP23,$IO$7))-GT23,0) -> 0 | IR23: =MAX((MIN(DA23+IQ23,$IO$7))-GU23,0) -> 0 | IS23: =MAX((MIN(DB23+IR23,$IO$7))-GV23,0) -> 0 | IT23: =MAX((MIN(DC23+IS23,$IO$7))-GW23,0) -> 0 | IU23: =MAX((MIN(DD23+IT23,$IO$7))-GX23,0) -> 0 | IV23: =MAX((MIN(DE23+IU23,$IO$7))-GY23,0) -> 0 | IW23: =MAX((MIN(DF23+IV23,$IO$7))-GZ23,0) -> 0 | IX23: =MAX((MIN(DG23+IW23,$IO$7))-HA23,0) -> 0 | ... KK23: =MAX((MIN(ET23+KJ23,$IO$7))-IN23,0) -> 0
... A375: 12 | B375: =B374+1 -> 365 | C375: =C374+1 -> 43830 | D375: =SUM(E375:AZ375) -> 0 | E375: =(SUMIFS(Profile!$F$2:$F$17521,Profile!$B$2:$B$17521,$B375,Profile!$C$2:$C$17521,E$8))*$C$6 -> 0 | F375: =(SUMIFS(Profile!$F$2:$F$17521,Profile!$B$2:$B$17521,$B375,Profile!$C$2:$C$17521,F$8))*$C$6 -> 0 | G375: =(SUMIFS(Profile!$F$2:$F$17521,Profile!$B$2:$B$17521,$B375,Profile!$C$2:$C$17521,G$8))*$C$6 -> 0 | H375: =(SUMIFS(Profile!$F$2:$F$17521,Profile!$B$2:$B$17521,$B375,Profile!$C$2:$C$17521,H$8))*$C$6 -> 0 | I375: =(SUMIFS(Profile!$F$2:$F$17521,Profile!$B$2:$B$17521,$B375,Profile!$C$2:$C$17521,I$8))*$C$6 -> 0 | J375: =(SUMIFS(Profile!$F$2:$F$17521,Profile!$B$2:$B$17521,$B375,Profile!$C$2:$C$17521,J$8))*$C$6 -> 0 | K375: =(SUMIFS(Profile!$F$2:$F$17521,Profile!$B$2:$B$17521,$B375,Profile!$C$2:$C$17521,K$8))*$C$6 -> 0 | L375: =(SUMIFS(Profile!$F$2:$F$17521,Profile!$B$2:$B$17521,$B375,Profile!$C$2:$C$17521,L$8))*$C$6 -> 0 | ... AZ375: =(SUMIFS(Profile!$F$2:$F$17521,Profile!$B$2:$B$17521,$B375,Profile!$C$2:$C$17521,AZ$8))*$C$6 -> 0 | BA375: =SUM(BB375:CW375) -> 0 | BB375: =(SUMIFS(Profile!$E$2:$E$17521,Profile!$B$2:$B$17521,$B375,Profile!$C$2:$C$17521,BB$8))*$C$9 -> 0 | BC375: =(SUMIFS(Profile!$E$2:$E$17521,Profile!$B$2:$B$17521,$B375,Profile!$C$2:$C$17521,BC$8))*$C$9 -> 0 | BD375: =(SUMIFS(Profile!$E$2:$E$17521,Profile!$B$2:$B$17521,$B375,Profile!$C$2:$C$17521,BD$8))*$C$9 -> 0 | BE375: =(SUMIFS(Profile!$E$2:$E$17521,Profile!$B$2:$B$17521,$B375,Profile!$C$2:$C$17521,BE$8))*$C$9 -> 0 | BF375: =(SUMIFS(Profile!$E$2:$E$17521,Profile!$B$2:$B$17521,$B375,Profile!$C$2:$C$17521,BF$8))*$C$9 -> 0 | BG375: =(SUMIFS(Profile!$E$2:$E$17521,Profile!$B$2:$B$17521,$B375,Profile!$C$2:$C$17521,BG$8))*$C$9 -> 0 | BH375: =(SUMIFS(Profile!$E$2:$E$17521,Profile!$B$2:$B$17521,$B375,Profile!$C$2:$C$17521,BH$8))*$C$9 -> 0 | BI375: =(SUMIFS(Profile!$E$2:$E$17521,Profile!$B$2:$B$17521,$B375,Profile!$C$2:$C$17521,BI$8))*$C$9 -> 0 | ... CW375: =(SUMIFS(Profile!$E$2:$E$17521,Profile!$B$2:$B$17521,$B375,Profile!$C$2:$C$17521,CW$8))*$C$9 -> 0 | CX375: =SUM(CY375:ET375) -> 0 | CY375: =MAX(BB375-E375,0) -> 0 | CZ375: =MAX(BC375-F375,0) -> 0 | DA375: =MAX(BD375-G375,0) -> 0 | DB375: =MAX(BE375-H375,0) -> 0 | DC375: =MAX(BF375-I375,0) -> 0 | DD375: =MAX(BG375-J375,0) -> 0 | DE375: =MAX(BH375-K375,0) -> 0 | DF375: =MAX(BI375-L375,0) -> 0 | ... ET375: =MAX(CW375-AZ375,0) -> 0 | EU375: =SUM(EV375:GQ375) -> 0 | EV375: =BB375-CY375 -> 0 | EW375: =BC375-CZ375 -> 0 | EX375: =BD375-DA375 -> 0 | EY375: =BE375-DB375 -> 0 | EZ375: =BF375-DC375 -> 0 | FA375: =BG375-DD375 -> 0 | FB375: =BH375-DE375 -> 0 | FC375: =BI375-DF375 -> 0 | ... GQ375: =CW375-ET375 -> 0 | GR375: =SUM(GS375:IN375) -> 0 | GS375: =E375-EV375 -> 0 | GT375: =F375-EW375 -> 0 | GU375: =G375-EX375 -> 0 | GV375: =H375-EY375 -> 0 | GW375: =I375-EZ375 -> 0 | GX375: =J375-FA375 -> 0 | GY375: =K375-FB375 -> 0 | GZ375: =L375-FC375 -> 0 | ... IN375: =AZ375-GQ375 -> 0 | IO375: =MAX(IP375:KK375)-IF(KK375<>0,KK375,MIN(IP375:KK375)) -> 0 | IP375: =MAX((MIN(CY375+KK374,$IO$7))-GS375,0) -> 0 | IQ375: =MAX((MIN(CZ375+IP375,$IO$7))-GT375,0) -> 0 | IR375: =MAX((MIN(DA375+IQ375,$IO$7))-GU375,0) -> 0 | IS375: =MAX((MIN(DB375+IR375,$IO$7))-GV375,0) -> 0 | IT375: =MAX((MIN(DC375+IS375,$IO$7))-GW375,0) -> 0 | IU375: =MAX((MIN(DD375+IT375,$IO$7))-GX375,0) -> 0 | IV375: =MAX((MIN(DE375+IU375,$IO$7))-GY375,0) -> 0 | IW375: =MAX((MIN(DF375+IV375,$IO$7))-GZ375,0) -> 0 | IX375: =MAX((MIN(DG375+IW375,$IO$7))-HA375,0) -> 0 | ... KK375: =MAX((MIN(ET375+KJ375,$IO$7))-IN375,0) -> 0

Sheet MCS Irradiation Zones
C1: Inclination (variation from horizontal)
A2: Zone | B2: Slope | C2: 0 | D2: 5 | E2: 10 | F2: 15 | G2: 20 | H2: 25 | I2: 30 | J2: 35 | K2: 40 | L2: 45 | M2: 50 | N2: 55 | O2: 60 | P2: 65 | Q2: 70 | R2: 75 | S2: 80 | T2: 85 | U2: 90 | V2: 95 | W2: 100 | X2: 105 | Y2: 110 | Z2: 115 | AA2: 120 | AB2: 125 | AC2: 130 | AD2: 135 | AE2: 140 | AF2: 145 | AG2: 150 | AH2: 155 | AI2: 160 | AJ2: 165 | AK2: 170 | AL2: 175 | AN2: AB | AO2: 16
A3: 1 | B3: 0 | C3: 828 | D3: 828 | E3: 828 | F3: 828 | G3: 828 | H3: 828 | I3: 828 | J3: 828 | K3: 828 | L3: 828 | M3: 828 | N3: 828 | O3: 828 | P3: 828 | Q3: 828 | R3: 828 | S3: 828 | T3: 828 | U3: 828 | V3: 828 | W3: 828 | X3: 828 | Y3: 828 | Z3: 828 | AA3: 828 | AB3: 828 | AC3: 828 | AD3: 828 | AE3: 828 | AF3: 828 | AG3: 828 | AH3: 828 | AI3: 828 | AJ3: 828 | AK3: 828 | AL3: 828 | AN3: AL | AO3: 1
A4: 1 | B4: 1 | C4: 835 | D4: 835 | E4: 835 | F4: 835 | G4: 835 | H4: 835 | I4: 834 | J4: 834 | K4: 833 | L4: 833 | M4: 833 | N4: 832 | O4: 831 | P4: 831 | Q4: 830 | R4: 830 | S4: 829 | T4: 828 | U4: 828 | V4: 827 | W4: 826 | X4: 826 | Y4: 825 | Z4: 824 | AA4: 824 | AB4: 823 | AC4: 823 | AD4: 822 | AE4: 822 | AF4: 821 | AG4: 821 | AH4: 821 | AI4: 820 | AJ4: 820 | AK4: 820 | AL4: 820 | AN4: B | AO4: 6
A5: 1 | B5: 2 | C5: 843 | D5: 843 | E5: 843 | F5: 842 | G5: 842 | H5: 841 | I5: 841 | J5: 840 | K5: 839 | L5: 838 | M5: 837 | N5: 836 | O5: 835 | P5: 834 | Q5: 833 | R5: 831 | S5: 830 | T5: 829 | U5: 827 | V5: 826 | W5: 825 | X5: 823 | Y5: 822 | Z5: 821 | AA5: 820 | AB5: 819 | AC5: 818 | AD5: 817 | AE5: 816 | AF5: 815 | AG5: 814 | AH5: 813 | AI5: 813 | AJ5: 813 | AK5: 812 | AL5: 812 | AN5: BA | AO5: 5E
A6: 1 | B6: 3 | C6: 850 | D6: 850 | E6: 850 | F6: 849 | G6: 849 | H6: 848 | I6: 847 | J6: 846 | K6: 845 | L6: 843 | M6: 842 | N6: 840 | O6: 839 | P6: 837 | Q6: 835 | R6: 833 | S6: 831 | T6: 829 | U6: 827 | V6: 825 | W6: 823 | X6: 821 | Y6: 819 | Z6: 817 | AA6: 816 | AB6: 814 | AC6: 812 | AD6: 811 | AE6: 809 | AF6: 808 | AG6: 807 | AH6: 806 | AI6: 805 | AJ6: 805 | AK6: 804 | AL6: 804 | AN6: BB | AO6: 7E
A7: 1 | B7: 4 | C7: 857 | D7: 857 | E7: 857 | F7: 856 | G7: 855 | H7: 854 | I7: 853 | J7: 852 | K7: 850 | L7: 848 | M7: 846 | N7: 844 | O7: 842 | P7: 840 | Q7: 837 | R7: 835 | S7: 832 | T7: 830 | U7: 827 | V7: 824 | W7: 821 | X7: 819 | Y7: 816 | Z7: 814 | AA7: 811 | AB7: 809 | AC7: 807 | AD7: 805 | AE7: 803 | AF7: 801 | AG7: 800 | AH7: 799 | AI7: 798 | AJ7: 797 | AK7: 796 | AL7: 796 | AN7: BD | AO7: 11
A8: 1 | B8: 5 | C8: 864 | D8: 864 | E8: 864 | F8: 863 | G8: 862 | H8: 861 | I8: 859 | J8: 857 | K8: 855 | L8: 853 | M8: 851 | N8: 848 | O8: 845 | P8: 843 | Q8: 839 | R8: 836 | S8: 833 | T8: 830 | U8: 826 | V8: 823 | W8: 820 | X8: 816 | Y8: 813 | Z8: 810 | AA8: 807 | AB8: 804 | AC8: 802 | AD8: 799 | AE8: 797 | AF8: 795 | AG8: 793 | AH8: 791 | AI8: 790 | AJ8: 789 | AK8: 788 | AL8: 788 | AN8: BD23 | AO8: 10
A9: 1 | B9: 6 | C9: 871 | D9: 871 | E9: 870 | F9: 869 | G9: 868 | H9: 867 | I9: 865 | J9: 863 | K9: 861 | L9: 858 | M9: 855 | N9: 852 | O9: 849 | P9: 845 | Q9: 841 | R9: 838 | S9: 834 | T9: 830 | U9: 826 | V9: 822 | W9: 818 | X9: 814 | Y9: 810 | Z9: 806 | AA9: 803 | AB9: 799 | AC9: 796 | AD9: 793 | AE9: 790 | AF9: 788 | AG9: 786 | AH9: 784 | AI9: 782 | AJ9: 781 | AK9: 780 | AL9: 779 | AN9: BD24 | AO9: 10
A10: 1 | B10: 7 | C10: 878 | D10: 877 | E10: 877 | F10: 876 | G10: 874 | H10: 873 | I10: 871 | J10: 868 | K10: 866 | L10: 862 | M10: 859 | N10: 856 | O10: 852 | P10: 848 | Q10: 843 | R10: 839 | S10: 835 | T10: 830 | U10: 825 | V10: 821 | W10: 816 | X10: 811 | Y10: 807 | Z10: 803 | AA10: 798 | AB10: 794 | AC10: 791 | AD10: 787 | AE10: 784 | AF10: 781 | AG10: 778 | AH10: 776 | AI10: 774 | AJ10: 773 | AK10: 772 | AL10: 771 | AN10: BH | AO10: 3
A11: 1 | B11: 8 | C11: 884 | D11: 884 | E11: 883 | F11: 882 | G11: 881 | H11: 879 | I11: 876 | J11: 873 | K11: 870 | L11: 867 | M11: 863 | N11: 859 | O11: 855 | P11: 850 | Q11: 845 | R11: 840 | S11: 835 | T11: 830 | U11: 825 | V11: 819 | W11: 814 | X11: 809 | Y11: 804 | Z11: 799 | AA11: 794 | AB11: 789 | AC11: 785 | AD11: 781 | AE11: 777 | AF11: 774 | AG11: 771 | AH11: 768 | AI11: 766 | AJ11: 764 | AK11: 763 | AL11: 762 | AN11: BL | AO11: 7E
A12: 1 | B12: 9 | C12: 890 | D12: 890 | E12: 889 | F12: 888 | G12: 886 | H12: 884 | I12: 882 | J12: 878 | K12: 875 | L12: 871 | M12: 867 | N12: 862 | O12: 857 | P12: 852 | Q12: 847 | R12: 841 | S12: 836 | T12: 830 | U12: 824 | V12: 818 | W12: 812 | X12: 806 | Y12: 800 | Z12: 795 | AA12: 789 | AB12: 784 | AC12: 779 | AD12: 775 | AE12: 770 | AF12: 767 | AG12: 763 | AH12: 760 | AI12: 758 | AJ12: 756 | AK12: 755 | AL12: 754 | AN12: BN | AO12: 2
A13: 1 | B13: 10 | C13: 896 | D13: 896 | E13: 895 | F13: 894 | G13: 892 | H13: 890 | I13: 887 | J13: 883 | K13: 880 | L13: 875 | M13: 871 | N13: 866 | O13: 860 | P13: 855 | Q13: 849 | R13: 842 | S13: 836 | T13: 830 | U13: 823 | V13: 817 | W13: 810 | X13: 803 | Y13: 797 | Z13: 791 | AA13: 785 | AB13: 779 | AC13: 773 | AD13: 768 | AE13: 764 | AF13: 760 | AG13: 756 | AH13: 753 | AI13: 750 | AJ13: 748 | AK13: 746 | AL13: 745 | AN13: BR | AO13: 2
A14: 1 | B14: 11 | C14: 902 | D14: 902 | E14: 901 | F14: 900 | G14: 898 | H14: 895 | I14: 892 | J14: 888 | K14: 884 | L14: 879 | M14: 874 | N14: 869 | O14: 863 | P14: 857 | Q14: 850 | R14: 843 | S14: 836 | T14: 829 | U14: 822 | V14: 815 | W14: 808 | X14: 801 | Y14: 794 | Z14: 787 | AA14: 780 | AB14: 774 | AC14: 768 | AD14: 762 | AE14: 757 | AF14: 752 | AG14: 748 | AH14: 745 | AI14: 742 | AJ14: 739 | AK14: 738 | AL14: 737 | AN14: BS | AO14: 5E
A15: 1 | B15: 12 | C15: 908 | D15: 908 | E15: 907 | F15: 905 | G15: 903 | H15: 900 | I15: 897 | J15: 893 | K15: 888 | L15: 883 | M15: 878 | N15: 872 | O15: 865 | P15: 859 | Q15: 852 | R15: 844 | S15: 837 | T15: 829 | U15: 821 | V15: 813 | W15: 806 | X15: 798 | Y15: 790 | Z15: 783 | AA15: 775 | AB15: 769 | AC15: 762 | AD15: 756 | AE15: 750 | AF15: 745 | AG15: 741 | AH15: 737 | AI15: 734 | AJ15: 731 | AK15: 729 | AL15: 728 | AN15: BT | AO15: 21
A16: 1 | B16: 13 | C16: 914 | D16: 913 | E16: 912 | F16: 910 | G16: 908 | H16: 905 | I16: 901 | J16: 897 | K16: 892 | L16: 887 | M16: 881 | N16: 875 | O16: 868 | P16: 861 | Q16: 853 | R16: 845 | S16: 837 | T16: 829 | U16: 820 | V16: 812 | W16: 803 | X16: 795 | Y16: 787 | Z16: 779 | AA16: 771 | AB16: 763 | AC16: 756 | AD16: 750 | AE16: 743 | AF16: 738 | AG16: 733 | AH16: 729 | AI16: 726 | AJ16: 723 | AK16: 721 | AL16: 720 | AN16: CA | AO16: 8E
A17: 1 | B17: 14 | C17: 919 | D17: 919 | E17: 917 | F17: 916 | G17: 913 | H17: 910 | I17: 906 | J17: 901 | K17: 896 | L17: 890 | M17: 884 | N17: 877 | O17: 870 | P17: 862 | Q17: 854 | R17: 846 | S17: 837 | T17: 828 | U17: 819 | V17: 810 | W17: 801 | X17: 792 | Y17: 783 | Z17: 774 | AA17: 766 | AB17: 758 | AC17: 750 | AD17: 743 | AE17: 737 | AF17: 731 | AG17: 726 | AH17: 721 | AI17: 717 | AJ17: 715 | AK17: 713 | AL17: 711 | AN17: CB | AO17: 12
A18: 1 | B18: 15 | C18: 924 | D18: 924 | E18: 922 | F18: 921 | G18: 918 | H18: 914 | I18: 910 | J18: 905 | K18: 900 | L18: 894 | M18: 887 | N18: 880 | O18: 872 | P18: 864 | Q18: 855 | R18: 846 | S18: 837 | T18: 828 | U18: 818 | V18: 809 | W18: 799 | X18: 789 | Y18: 780 | Z18: 770 | AA18: 761 | AB18: 753 | AC18: 745 | AD18: 737 | AE18: 730 | AF18: 724 | AG18: 718 | AH18: 713 | AI18: 709 | AJ18: 707 | AK18: 704 | AL18: 703 | AN18: CF | AO18: 5W
A19: 1 | B19: 16 | C19: 929 | D19: 929 | E19: 927 | F19: 925 | G19: 922 | H19: 919 | I19: 914 | J19: 909 | K19: 903 | L19: 897 | M19: 890 | N19: 882 | O19: 874 | P19: 866 | Q19: 856 | R19: 847 | S19: 837 | T19: 827 | U19: 817 | V19: 807 | W19: 796 | X19: 786 | Y19: 776 | Z19: 766 | AA19: 757 | AB19: 747 | AC19: 739 | AD19: 731 | AE19: 723 | AF19: 716 | AG19: 711 | AH19: 706 | AI19: 702 | AJ19: 698 | AK19: 697 | AL19: 695 | AN19: CH | AO19: 7E
A20: 1 | B20: 17 | C20: 934 | D20: 933 | E20: 932 | F20: 930 | G20: 927 | H20: 923 | I20: 918 | J20: 913 | K20: 907 | L20: 900 | M20: 893 | N20: 885 | O20: 876 | P20: 867 | Q20: 857 | R20: 848 | S20: 837 | T20: 827 | U20: 816 | V20: 805 | W20: 794 | X20: 783 | Y20: 773 | Z20: 762 | AA20: 752 | AB20: 742 | AC20: 733 | AD20: 724 | AE20: 716 | AF20: 709 | AG20: 703 | AH20: 698 | AI20: 694 | AJ20: 691 | AK20: 688 | AL20: 687 | AN20: CH5 | AO20: 7W
A21: 1 | B21: 18 | C21: 938 | D21: 938 | E21: 936 | F21: 934 | G21: 931 | H21: 927 | I21: 922 | J21: 917 | K21: 910 | L21: 903 | M21: 895 | N21: 887 | O21: 878 | P21: 868 | Q21: 858 | R21: 848 | S21: 837 | T21: 826 | U21: 815 | V21: 803 | W21: 792 | X21: 780 | Y21: 769 | Z21: 758 | AA21: 747 | AB21: 737 | AC21: 727 | AD21: 718 | AE21: 710 | AF21: 702 | AG21: 696 | AH21: 690 | AI21: 686 | AJ21: 683 | AK21: 680 | AL21: 679 | AN21: CH6 | AO21: 7W
A22: 1 | B22: 19 | C22: 943 | D22: 942 | E22: 941 | F22: 938 | G22: 935 | H22: 931 | I22: 926 | J22: 920 | K22: 913 | L22: 906 | M22: 898 | N22: 889 | O22: 879 | P22: 870 | Q22: 859 | R22: 848 | S22: 837 | T22: 825 | U22: 813 | V22: 802 | W22: 790 | X22: 777 | Y22: 766 | Z22: 754 | AA22: 742 | AB22: 732 | AC22: 721 | AD22: 712 | AE22: 703 | AF22: 695 | AG22: 688 | AH22: 683 | AI22: 678 | AJ22: 675 | AK22: 672 | AL22: 671 | AN22: CH7 | AO22: 7W
A23: 1 | B23: 20 | C23: 947 | D23: 946 | E23: 945 | F23: 942 | G23: 939 | H23: 935 | I23: 929 | J23: 923 | K23: 916 | L23: 908 | M23: 900 | N23: 891 | O23: 881 | P23: 870 | Q23: 859 | R23: 848 | S23: 836 | T23: 824 | U23: 812 | V23: 799 | W23: 787 | X23: 774 | Y23: 762 | Z23: 750 | AA23: 738 | AB23: 726 | AC23: 716 | AD23: 705 | AE23: 696 | AF23: 688 | AG23: 681 | AH23: 675 | AI23: 671 | AJ23: 667 | AK23: 664 | AL23: 663 | AN23: CH8 | AO23: 7W
A24: 1 | B24: 21 | C24: 951 | D24: 950 | E24: 949 | F24: 946 | G24: 943 | H24: 938 | I24: 933 | J24: 926 | K24: 919 | L24: 911 | M24: 902 | N24: 893 | O24: 882 | P24: 871 | Q24: 860 | R24: 848 | S24: 836 | T24: 823 | U24: 811 | V24: 798 | W24: 784 | X24: 771 | Y24: 758 | Z24: 745 | AA24: 733 | AB24: 721 | AC24: 710 | AD24: 699 | AE24: 690 | AF24: 681 | AG24: 674 | AH24: 668 | AI24: 663 | AJ24: 659 | AK24: 657 | AL24: 655 | AN24: CM | AO24: 12
A25: 1 | B25: 22 | C25: 954 | D25: 954 | E25: 952 | F25: 950 | G25: 946 | H25: 941 | I25: 936 | J25: 929 | K25: 922 | L25: 913 | M25: 904 | N25: 894 | O25: 883 | P25: 872 | Q25: 860 | R25: 848 | S25: 835 | T25: 822 | U25: 809 | V25: 795 | W25: 782 | X25: 768 | Y25: 755 | Z25: 742 | AA25: 729 | AB25: 716 | AC25: 704 | AD25: 693 | AE25: 683 | AF25: 674 | AG25: 667 | AH25: 660 | AI25: 655 | AJ25: 651 | AK25: 648 | AL25: 646 | AN25: CM21 | AO25: 1
A26: 1 | B26: 23 | C26: 958 | D26: 957 | E26: 956 | F26: 953 | G26: 949 | H26: 944 | I26: 939 | J26: 932 | K26: 924 | L26: 915 | M26: 906 | N26: 896 | O26: 885 | P26: 873 | Q26: 861 | R26: 848 | S26: 835 | T26: 821 | U26: 807 | V26: 794 | W26: 779 | X26: 765 | Y26: 751 | Z26: 737 | AA26: 724 | AB26: 711 | AC26: 698 | AD26: 687 | AE26: 676 | AF26: 667 | AG26: 659 | AH26: 653 | AI26: 648 | AJ26: 643 | AK26: 640 | AL26: 638 | AN26: CM22 | AO26: 1
A27: 1 | B27: 24 | C27: 961 | D27: 961 | E27: 959 | F27: 956 | G27: 952 | H27: 947 | I27: 941 | J27: 934 | K27: 926 | L27: 917 | M27: 907 | N27: 897 | O27: 886 | P27: 873 | Q27: 861 | R27: 848 | S27: 834 | T27: 820 | U27: 806 | V27: 791 | W27: 777 | X27: 762 | Y27: 748 | Z27: 733 | AA27: 719 | AB27: 706 | AC27: 693 | AD27: 681 | AE27: 670 | AF27: 660 | AG27: 652 | AH27: 645 | AI27: 640 | AJ27: 635 | AK27: 632 | AL27: 630 | AN27: CM23 | AO27: 1
A28: 1 | B28: 25 | C28: 964 | D28: 964 | E28: 962 | F28: 959 | G28: 955 | H28: 950 | I28: 944 | J28: 937 | K28: 928 | L28: 919 | M28: 909 | N28: 898 | O28: 886 | P28: 874 | Q28: 861 | R28: 847 | S28: 833 | T28: 819 | U28: 804 | V28: 789 | W28: 774 | X28: 759 | Y28: 744 | Z28: 729 | AA28: 714 | AB28: 700 | AC28: 687 | AD28: 675 | AE28: 663 | AF28: 653 | AG28: 645 | AH28: 638 | AI28: 632 | AJ28: 627 | AK28: 623 | AL28: 621 | AN28: CO | AO28: 12
A29: 1 | B29: 26 | C29: 967 | D29: 967 | E29: 965 | F29: 962 | G29: 958 | H29: 953 | I29: 946 | J29: 939 | K29: 930 | L29: 921 | M29: 910 | N29: 899 | O29: 887 | P29: 874 | Q29: 861 | R29: 847 | S29: 833 | T29: 818 | U29: 802 | V29: 787 | W29: 772 | X29: 756 | Y29: 740 | Z29: 725 | AA29: 710 | AB29: 695 | AC29: 682 | AD29: 668 | AE29: 657 | AF29: 646 | AG29: 638 | AH29: 630 | AI29: 624 | AJ29: 619 | AK29: 615 | AL29: 614 | AN29: CR | AO29: 1
A30: 1 | B30: 27 | C30: 970 | D30: 969 | E30: 968 | F30: 965 | G30: 960 | H30: 955 | I30: 948 | J30: 941 | K30: 932 | L30: 922 | M30: 911 | N30: 900 | O30: 887 | P30: 874 | Q30: 861 | R30: 846 | S30: 831 | T30: 816 | U30: 801 | V30: 785 | W30: 769 | X30: 752 | Y30: 737 | Z30: 721 | AA30: 705 | AB30: 690 | AC30: 676 | AD30: 662 | AE30: 650 | AF30: 640 | AG30: 630 | AH30: 623 | AI30: 616 | AJ30: 611 | AK30: 608 | AL30: 605 | AN30: CT | AO30: 2
A31: 1 | B31: 28 | C31: 972 | D31: 972 | E31: 970 | F31: 967 | G31: 962 | H31: 957 | I31: 950 | J31: 942 | K31: 933 | L31: 923 | M31: 912 | N31: 900 | O31: 888 | P31: 874 | Q31: 860 | R31: 845 | S31: 830 | T31: 815 | U31: 799 | V31: 782 | W31: 766 | X31: 749 | Y31: 733 | Z31: 717 | AA31: 701 | AB31: 685 | AC31: 670 | AD31: 656 | AE31: 644 | AF31: 633 | AG31: 623 | AH31: 615 | AI31: 608 | AJ31: 603 | AK31: 599 | AL31: 597 | AN31: CV | AO31: 6
A32: 1 | B32: 29 | C32: 975 | D32: 974 | E32: 972 | F32: 969 | G32: 964 | H32: 959 | I32: 952 | J32: 944 | K32: 935 | L32: 924 | M32: 913 | N32: 901 | O32: 888 | P32: 874 | Q32: 860 | R32: 845 | S32: 829 | T32: 813 | U32: 797 | V32: 780 | W32: 763 | X32: 746 | Y32: 729 | Z32: 712 | AA32: 696 | AB32: 680 | AC32: 665 | AD32: 651 | AE32: 637 | AF32: 626 | AG32: 616 | AH32: 608 | AI32: 600 | AJ32: 595 | AK32: 591 | AL32: 589 | AN32: CW | AO32: 7E
A33: 1 | B33: 30 | C33: 977 | D33: 976 | E33: 974 | F33: 971 | G33: 966 | H33: 960 | I33: 953 | J33: 945 | K33: 936 | L33: 925 | M33: 914 | N33: 901 | O33: 888 | P33: 874 | Q33: 859 | R33: 844 | S33: 828 | T33: 811 | U33: 795 | V33: 777 | W33: 760 | X33: 743 | Y33: 725 | Z33: 708 | AA33: 691 | AB33: 675 | AC33: 659 | AD33: 644 | AE33: 631 | AF33: 619 | AG33: 609 | AH33: 600 | AI33: 593 | AJ33: 587 | AK33: 583 | AL33: 581 | AN33: DA | AO33: 2
A34: 1 | B34: 31 | C34: 979 | D34: 978 | E34: 976 | F34: 973 | G34: 968 | H34: 962 | I34: 955 | J34: 946 | K34: 937 | L34: 926 | M34: 914 | N34: 901 | O34: 888 | P34: 873 | Q34: 858 | R34: 843 | S34: 826 | T34: 810 | U34: 792 | V34: 775 | W34: 757 | X34: 739 | Y34: 722 | Z34: 704 | AA34: 687 | AB34: 670 | AC34: 654 | AD34: 639 | AE34: 625 | AF34: 612 | AG34: 602 | AH34: 593 | AI34: 585 | AJ34: 579 | AK34: 575 | AL34: 573 | AN34: DD | AO34: 15
A35: 1 | B35: 32 | C35: 980 | D35: 979 | E35: 977 | F35: 974 | G35: 969 | H35: 963 | I35: 956 | J35: 947 | K35: 937 | L35: 926 | M35: 914 | N35: 901 | O35: 888 | P35: 873 | Q35: 857 | R35: 841 | S35: 825 | T35: 808 | U35: 790 | V35: 772 | W35: 754 | X35: 736 | Y35: 718 | Z35: 700 | AA35: 682 | AB35: 665 | AC35: 648 | AD35: 633 | AE35: 618 | AF35: 606 | AG35: 595 | AH35: 585 | AI35: 577 | AJ35: 571 | AK35: 568 | AL35: 565 | AN35: DE | AO35: 6
A36: 1 | B36: 33 | C36: 982 | D36: 981 | E36: 979 | F36: 975 | G36: 970 | H36: 964 | I36: 957 | J36: 948 | K36: 938 | L36: 927 | M36: 914 | N36: 901 | O36: 887 | P36: 872 | Q36: 856 | R36: 840 | S36: 823 | T36: 806 | U36: 788 | V36: 769 | W36: 751 | X36: 733 | Y36: 714 | Z36: 696 | AA36: 678 | AB36: 660 | AC36: 643 | AD36: 627 | AE36: 612 | AF36: 599 | AG36: 588 | AH36: 578 | AI36: 570 | AJ36: 564 | AK36: 560 | AL36: 557 | AN36: DG | AO36: 8S
A37: 1 | B37: 34 | C37: 983 | D37: 982 | E37: 980 | F37: 976 | G37: 971 | H37: 965 | I37: 957 | J37: 948 | K37: 938 | L37: 927 | M37: 914 | N37: 901 | O37: 886 | P37: 871 | Q37: 855 | R37: 838 | S37: 821 | T37: 803 | U37: 785 | V37: 767 | W37: 748 | X37: 729 | Y37: 710 | Z37: 691 | AA37: 673 | AB37: 655 | AC37: 638 | AD37: 621 | AE37: 606 | AF37: 592 | AG37: 581 | AH37: 570 | AI37: 562 | AJ37: 556 | AK37: 551 | AL37: 548 | AN37: DH | AO37: 10
A38: 1 | B38: 35 | C38: 984 | D38: 983 | E38: 981 | F38: 977 | G38: 972 | H38: 966 | I38: 958 | J38: 949 | K38: 938 | L38: 927 | M38: 914 | N38: 900 | O38: 886 | P38: 870 | Q38: 854 | R38: 837 | S38: 819 | T38: 801 | U38: 783 | V38: 764 | W38: 745 | X38: 726 | Y38: 706 | Z38: 687 | AA38: 668 | AB38: 650 | AC38: 632 | AD38: 616 | AE38: 600 | AF38: 586 | AG38: 573 | AH38: 563 | AI38: 555 | AJ38: 548 | AK38: 543 | AL38: 540 | AN38: DH4 | AO38: 9E
A39: 1 | B39: 36 | C39: 984 | D39: 984 | E39: 981 | F39: 978 | G39: 973 | H39: 966 | I39: 958 | J39: 949 | K39: 938 | L39: 927 | M39: 914 | N39: 900 | O39: 885 | P39: 869 | Q39: 852 | R39: 835 | S39: 817 | T39: 799 | U39: 780 | V39: 761 | W39: 741 | X39: 722 | Y39: 702 | Z39: 683 | AA39: 664 | AB39: 645 | AC39: 627 | AD39: 610 | AE39: 594 | AF39: 579 | AG39: 566 | AH39: 556 | AI39: 547 | AJ39: 540 | AK39: 535 | AL39: 532 | AN39: DH5 | AO39: 9E
A40: 1 | B40: 37 | C40: 985 | D40: 984 | E40: 982 | F40: 978 | G40: 973 | H40: 966 | I40: 958 | J40: 949 | K40: 938 | L40: 926 | M40: 913 | N40: 899 | O40: 884 | P40: 868 | Q40: 851 | R40: 833 | S40: 815 | T40: 796 | U40: 777 | V40: 758 | W40: 738 | X40: 718 | Y40: 698 | Z40: 679 | AA40: 659 | AB40: 640 | AC40: 622 | AD40: 604 | AE40: 588 | AF40: 572 | AG40: 560 | AH40: 549 | AI40: 540 | AJ40: 533 | AK40: 528 | AL40: 524 | AN40: DL | AO40: 10
A41: 1 | B41: 38 | C41: 985 | D41: 984 | E41: 982 | F41: 978 | G41: 973 | H41: 966 | I41: 958 | J41: 949 | K41: 938 | L41: 925 | M41: 912 | N41: 898 | O41: 882 | P41: 866 | Q41: 849 | R41: 831 | S41: 813 | T41: 794 | U41: 775 | V41: 755 | W41: 734 | X41: 714 | Y41: 694 | Z41: 674 | AA41: 655 | AB41: 635 | AC41: 616 | AD41: 598 | AE41: 582 | AF41: 566 | AG41: 553 | AH41: 541 | AI41: 532 | AJ41: 525 | AK41: 520 | AL41: 517 | AN41: DN | AO41: 11
A42: 1 | B42: 39 | C42: 985 | D42: 984 | E42: 982 | F42: 978 | G42: 973 | H42: 966 | I42: 958 | J42: 948 | K42: 937 | L42: 925 | M42: 911 | N42: 897 | O42: 881 | P42: 864 | Q42: 847 | R42: 829 | S42: 810 | T42: 791 | U42: 771 | V42: 751 | W42: 731 | X42: 711 | Y42: 690 | Z42: 670 | AA42: 650 | AB42: 630 | AC42: 611 | AD42: 593 | AE42: 576 | AF42: 560 | AG42: 546 | AH42: 534 | AI42: 525 | AJ42: 517 | AK42: 512 | AL42: 509 | AN42: DT | AO42: 2
A43: 1 | B43: 40 | C43: 985 | D43: 984 | E43: 982 | F43: 978 | G43: 973 | H43: 966 | I43: 957 | J43: 947 | K43: 936 | L43: 924 | M43: 910 | N43: 895 | O43: 879 | P43: 863 | Q43: 845 | R43: 827 | S43: 808 | T43: 788 | U43: 768 | V43: 748 | W43: 727 | X43: 707 | Y43: 686 | Z43: 665 | AA43: 645 | AB43: 625 | AC43: 606 | AD43: 587 | AE43: 570 | AF43: 554 | AG43: 539 | AH43: 527 | AI43: 517 | AJ43: 510 | AK43: 505 | AL43: 501 | AN43: DY | AO43: 6
A44: 2 | B44: 0 | C44: 938 | D44: 938 | E44: 938 | F44: 938 | G44: 938 | H44: 938 | I44: 938 | J44: 938 | K44: 938 | L44: 938 | M44: 938 | N44: 938 | O44: 938 | P44: 938 | Q44: 938 | R44: 938 | S44: 938 | T44: 938 | U44: 938 | V44: 938 | W44: 938 | X44: 938 | Y44: 938 | Z44: 938 | AA44: 938 | AB44: 938 | AC44: 938 | AD44: 938 | AE44: 938 | AF44: 938 | AG44: 938 | AH44: 938 | AI44: 938 | AJ44: 938 | AK44: 938 | AL44: 938 | AN44: E | AO44: 1
A45: 2 | B45: 1 | C45: 947 | D45: 947 | E45: 947 | F45: 946 | G45: 946 | H45: 946 | I45: 945 | J45: 945 | K45: 944 | L45: 944 | M45: 943 | N45: 943 | O45: 942 | P45: 941 | Q45: 940 | R45: 940 | S45: 939 | T45: 938 | U45: 937 | V45: 936 | W45: 936 | X45: 935 | Y45: 934 | Z45: 933 | AA45: 932 | AB45: 932 | AC45: 931 | AD45: 930 | AE45: 930 | AF45: 929 | AG45: 929 | AH45: 929 | AI45: 928 | AJ45: 928 | AK45: 928 | AL45: 928 | AN45: EC | AO45: 1
A46: 2 | B46: 2 | C46: 956 | D46: 956 | E46: 956 | F46: 955 | G46: 955 | H46: 954 | I46: 953 | J46: 952 | K46: 951 | L46: 950 | M46: 949 | N46: 948 | O46: 946 | P46: 945 | Q46: 943 | R46: 942 | S46: 940 | T46: 939 | U46: 937 | V46: 935 | W46: 934 | X46: 932 | Y46: 930 | Z46: 929 | AA46: 927 | AB46: 926 | AC46: 925 | AD46: 924 | AE46: 922 | AF46: 921 | AG46: 920 | AH46: 920 | AI46: 919 | AJ46: 919 | AK46: 918 | AL46: 918 | AN46: EH | AO46: 15
A47: 2 | B47: 3 | C47: 965 | D47: 965 | E47: 964 | F47: 964 | G47: 963 | H47: 962 | I47: 961 | J47: 960 | K47: 958 | L47: 957 | M47: 955 | N47: 953 | O47: 951 | P47: 949 | Q47: 946 | R47: 944 | S47: 941 | T47: 939 | U47: 937 | V47: 934 | W47: 932 | X47: 929 | Y47: 927 | Z47: 925 | AA47: 922 | AB47: 920 | AC47: 918 | AD47: 916 | AE47: 915 | AF47: 913 | AG47: 912 | AH47: 911 | AI47: 910 | AJ47: 909 | AK47: 908 | AL47: 908 | AN47: EH43 | AO47: 9S
A48: 2 | B48: 4 | C48: 974 | D48: 973 | E48: 973 | F48: 972 | G48: 971 | H48: 970 | I48: 969 | J48: 967 | K48: 965 | L48: 963 | M48: 960 | N48: 958 | O48: 955 | P48: 952 | Q48: 949 | R48: 946 | S48: 943 | T48: 939 | U48: 936 | V48: 933 | W48: 929 | X48: 926 | Y48: 923 | Z48: 920 | AA48: 917 | AB48: 914 | AC48: 912 | AD48: 909 | AE48: 907 | AF48: 905 | AG48: 903 | AH48: 901 | AI48: 900 | AJ48: 899 | AK48: 898 | AL48: 898 | AN48: EH44 | AO48: 9S
A49: 2 | B49: 5 | C49: 982 | D49: 982 | E49: 981 | F49: 981 | G49: 979 | H49: 978 | I49: 976 | J49: 974 | K49: 971 | L49: 969 | M49: 966 | N49: 962 | O49: 959 | P49: 955 | Q49: 952 | R49: 948 | S49: 944 | T49: 940 | U49: 935 | V49: 931 | W49: 927 | X49: 923 | Y49: 919 | Z49: 915 | AA49: 912 | AB49: 908 | AC49: 905 | AD49: 902 | AE49: 899 | AF49: 896 | AG49: 894 | AH49: 892 | AI49: 891 | AJ49: 889 | AK49: 888 | AL49: 888 | AN49: EH45 | AO49: 9S
A50: 2 | B50: 6 | C50: 990 | D50: 990 | E50: 990 | F50: 989 | G50: 987 | H50: 985 | I50: 983 | J50: 980 | K50: 978 | L50: 974 | M50: 971 | N50: 967 | O50: 963 | P50: 958 | Q50: 954 | R50: 949 | S50: 944 | T50: 940 | U50: 935 | V50: 930 | W50: 925 | X50: 920 | Y50: 915 | Z50: 911 | AA50: 906 | AB50: 902 | AC50: 898 | AD50: 894 | AE50: 891 | AF50: 888 | AG50: 885 | AH50: 883 | AI50: 881 | AJ50: 879 | AK50: 878 | AL50: 877 | AN50: EH46 | AO50: 9S
A51: 2 | B51: 7 | C51: 999 | D51: 998 | E51: 998 | F51: 996 | G51: 995 | H51: 993 | I51: 990 | J51: 987 | K51: 984 | L51: 980 | M51: 976 | N51: 971 | O51: 967 | P51: 961 | Q51: 956 | R51: 951 | S51: 945 | T51: 940 | U51: 934 | V51: 928 | W51: 922 | X51: 917 | Y51: 911 | Z51: 906 | AA51: 901 | AB51: 896 | AC51: 891 | AD51: 887 | AE51: 883 | AF51: 879 | AG51: 876 | AH51: 873 | AI51: 871 | AJ51: 869 | AK51: 868 | AL51: 867 | AN51: EN | AO51: 1
A52: 2 | B52: 8 | C52: 1006 | D52: 1006 | E52: 1005 | F52: 1004 | G52: 1002 | H52: 1000 | I52: 997 | J52: 993 | K52: 990 | L52: 985 | M52: 981 | N52: 976 | O52: 970 | P52: 964 | Q52: 958 | R52: 952 | S52: 946 | T52: 939 | U52: 933 | V52: 926 | W52: 920 | X52: 913 | Y52: 907 | Z52: 901 | AA52: 895 | AB52: 889 | AC52: 884 | AD52: 879 | AE52: 874 | AF52: 870 | AG52: 867 | AH52: 863 | AI52: 861 | AJ52: 859 | AK52: 857 | AL52: 856 | AN52: EN9 | AO52: 12
A53: 2 | B53: 9 | C53: 1014 | D53: 1014 | E53: 1013 | F53: 1011 | G53: 1009 | H53: 1007 | I53: 1003 | J53: 1000 | K53: 995 | L53: 990 | M53: 985 | N53: 980 | O53: 974 | P53: 967 | Q53: 961 | R53: 954 | S53: 947 | T53: 939 | U53: 932 | V53: 925 | W53: 917 | X53: 910 | Y53: 903 | Z53: 896 | AA53: 889 | AB53: 883 | AC53: 877 | AD53: 871 | AE53: 866 | AF53: 861 | AG53: 857 | AH53: 854 | AI53: 851 | AJ53: 848 | AK53: 847 | AL53: 846 | AN53: EX | AO53: 4
A54: 2 | B54: 10 | C54: 1022 | D54: 1021 | E54: 1020 | F54: 1019 | G54: 1016 | H54: 1013 | I54: 1010 | J54: 1006 | K54: 1001 | L54: 996 | M54: 990 | N54: 983 | O54: 977 | P54: 970 | Q54: 962 | R54: 955 | S54: 947 | T54: 939 | U54: 931 | V54: 923 | W54: 915 | X54: 906 | Y54: 899 | Z54: 891 | AA54: 883 | AB54: 876 | AC54: 870 | AD54: 863 | AE54: 858 | AF54: 853 | AG54: 848 | AH54: 844 | AI54: 841 | AJ54: 838 | AK54: 836 | AL54: 835 | AN54: FK | AO54: 14
A55: 2 | B55: 11 | C55: 1029 | D55: 1029 | E55: 1027 | F55: 1026 | G55: 1023 | H55: 1020 | I55: 1016 | J55: 1011 | K55: 1006 | L55: 1000 | M55: 994 | N55: 987 | O55: 980 | P55: 972 | Q55: 964 | R55: 956 | S55: 947 | T55: 939 | U55: 930 | V55: 921 | W55: 912 | X55: 903 | Y55: 894 | Z55: 886 | AA55: 878 | AB55: 870 | AC55: 862 | AD55: 856 | AE55: 849 | AF55: 843 | AG55: 838 | AH55: 834 | AI55: 830 | AJ55: 828 | AK55: 826 | AL55: 824 | AN55: FY | AO55: 7E
A56: 2 | B56: 12 | C56: 1036 | D56: 1036 | E56: 1034 | F56: 1032 | G56: 1030 | H56: 1026 | I56: 1022 | J56: 1017 | K56: 1011 | L56: 1005 | M56: 998 | N56: 991 | O56: 983 | P56: 975 | Q56: 966 | R56: 957 | S56: 948 | T56: 938 | U56: 929 | V56: 919 | W56: 909 | X56: 899 | Y56: 890 | Z56: 881 | AA56: 872 | AB56: 863 | AC56: 855 | AD56: 848 | AE56: 841 | AF56: 834 | AG56: 829 | AH56: 824 | AI56: 820 | AJ56: 817 | AK56: 815 | AL56: 814 | AN56: G | AO56: 14
A57: 2 | B57: 13 | C57: 1043 | D57: 1042 | E57: 1041 | F57: 1039 | G57: 1036 | H57: 1032 | I57: 1028 | J57: 1022 | K57: 1016 | L57: 1010 | M57: 1002 | N57: 994 | O57: 986 | P57: 977 | Q57: 968 | R57: 958 | S57: 948 | T57: 938 | U57: 927 | V57: 917 | W57: 906 | X57: 896 | Y57: 886 | Z57: 876 | AA57: 866 | AB57: 857 | AC57: 848 | AD57: 840 | AE57: 832 | AF57: 825 | AG57: 819 | AH57: 814 | AI57: 810 | AJ57: 807 | AK57: 804 | AL57: 803 | AN57: GL | AO57: 5E
A58: 2 | B58: 14 | C58: 1049 | D58: 1049 | E58: 1047 | F58: 1045 | G58: 1042 | H58: 1038 | I58: 1033 | J58: 1028 | K58: 1021 | L58: 1014 | M58: 1006 | N58: 998 | O58: 989 | P58: 979 | Q58: 969 | R58: 959 | S58: 948 | T58: 937 | U58: 926 | V58: 915 | W58: 903 | X58: 892 | Y58: 881 | Z58: 870 | AA58: 860 | AB58: 850 | AC58: 840 | AD58: 832 | AE58: 824 | AF58: 816 | AG58: 810 | AH58: 804 | AI58: 800 | AJ58: 796 | AK58: 794 | AL58: 792 | AN58: GU | AO58: 1
A59: 2 | B59: 15 | C59: 1056 | D59: 1055 | E59: 1054 | F59: 1051 | G59: 1048 | H59: 1044 | I59: 1039 | J59: 1033 | K59: 1026 | L59: 1018 | M59: 1010 | N59: 1001 | O59: 991 | P59: 981 | Q59: 971 | R59: 960 | S59: 948 | T59: 936 | U59: 925 | V59: 912 | W59: 901 | X59: 889 | Y59: 877 | Z59: 865 | AA59: 854 | AB59: 843 | AC59: 833 | AD59: 824 | AE59: 815 | AF59: 807 | AG59: 800 | AH59: 795 | AI59: 790 | AJ59: 786 | AK59: 783 | AL59: 782 | AN59: GU11 | AO59: 3
A60: 2 | B60: 16 | C60: 1062 | D60: 1061 | E60: 1060 | F60: 1057 | G60: 1054 | H60: 1049 | I60: 1044 | J60: 1037 | K60: 1030 | L60: 1022 | M60: 1013 | N60: 1004 | O60: 994 | P60: 983 | Q60: 972 | R60: 960 | S60: 948 | T60: 936 | U60: 923 | V60: 910 | W60: 898 | X60: 885 | Y60: 872 | Z60: 860 | AA60: 848 | AB60: 837 | AC60: 826 | AD60: 816 | AE60: 807 | AF60: 798 | AG60: 791 | AH60: 785 | AI60: 780 | AJ60: 776 | AK60: 773 | AL60: 771 | AN60: GU12 | AO60: 3
A61: 2 | B61: 17 | C61: 1068 | D61: 1067 | E61: 1065 | F61: 1063 | G61: 1059 | H61: 1054 | I61: 1049 | J61: 1042 | K61: 1035 | L61: 1026 | M61: 1017 | N61: 1007 | O61: 996 | P61: 985 | Q61: 973 | R61: 961 | S61: 948 | T61: 935 | U61: 922 | V61: 908 | W61: 895 | X61: 881 | Y61: 868 | Z61: 855 | AA61: 842 | AB61: 830 | AC61: 819 | AD61: 808 | AE61: 798 | AF61: 789 | AG61: 782 | AH61: 775 | AI61: 770 | AJ61: 766 | AK61: 763 | AL61: 761 | AN61: GU14 | AO61: 3
A62: 2 | B62: 18 | C62: 1073 | D62: 1073 | E62: 1071 | F62: 1068 | G62: 1064 | H62: 1059 | I62: 1053 | J62: 1046 | K62: 1038 | L62: 1030 | M62: 1020 | N62: 1010 | O62: 998 | P62: 987 | Q62: 974 | R62: 961 | S62: 948 | T62: 934 | U62: 920 | V62: 906 | W62: 892 | X62: 877 | Y62: 863 | Z62: 850 | AA62: 836 | AB62: 823 | AC62: 811 | AD62: 800 | AE62: 789 | AF62: 780 | AG62: 772 | AH62: 765 | AI62: 760 | AJ62: 756 | AK62: 752 | AL62: 751 | AN62: GU28 | AO62: 2
A63: 2 | B63: 19 | C63: 1078 | D63: 1078 | E63: 1076 | F63: 1073 | G63: 1069 | H63: 1064 | I63: 1058 | J63: 1051 | K63: 1042 | L63: 1033 | M63: 1023 | N63: 1012 | O63: 1000 | P63: 988 | Q63: 975 | R63: 961 | S63: 948 | T63: 933 | U63: 918 | V63: 904 | W63: 889 | X63: 874 | Y63: 859 | Z63: 844 | AA63: 830 | AB63: 817 | AC63: 804 | AD63: 792 | AE63: 781 | AF63: 771 | AG63: 763 | AH63: 756 | AI63: 750 | AJ63: 746 | AK63: 743 | AL63: 741 | AN63: GU29 | AO63: 2
A64: 2 | B64: 20 | C64: 1084 | D64: 1083 | E64: 1081 | F64: 1078 | G64: 1074 | H64: 1069 | I64: 1062 | J64: 1055 | K64: 1046 | L64: 1036 | M64: 1026 | N64: 1014 | O64: 1002 | P64: 989 | Q64: 976 | R64: 962 | S64: 947 | T64: 932 | U64: 917 | V64: 901 | W64: 886 | X64: 870 | Y64: 854 | Z64: 839 | AA64: 824 | AB64: 810 | AC64: 797 | AD64: 784 | AE64: 773 | AF64: 762 | AG64: 754 | AH64: 746 | AI64: 740 | AJ64: 736 | AK64: 732 | AL64: 730 | AN64: GU30 | AO64: 3
A65: 2 | B65: 21 | C65: 1088 | D65: 1088 | E65: 1086 | F65: 1083 | G65: 1079 | H65: 1073 | I65: 1066 | J65: 1058 | K65: 1049 | L65: 1039 | M65: 1029 | N65: 1017 | O65: 1004 | P65: 990 | Q65: 977 | R65: 962 | S65: 947 | T65: 931 | U65: 915 | V65: 899 | W65: 883 | X65: 866 | Y65: 850 | Z65: 834 | AA65: 819 | AB65: 804 | AC65: 790 | AD65: 776 | AE65: 764 | AF65: 753 | AG65: 744 | AH65: 737 | AI65: 731 | AJ65: 726 | AK65: 722 | AL65: 720 | AN65: GU31 | AO65: 3
A66: 2 | B66: 22 | C66: 1093 | D66: 1092 | E66: 1090 | F66: 1087 | G66: 1083 | H66: 1077 | I66: 1070 | J66: 1062 | K66: 1053 | L66: 1042 | M66: 1031 | N66: 1019 | O66: 1005 | P66: 992 | Q66: 977 | R66: 962 | S66: 946 | T66: 930 | U66: 913 | V66: 897 | W66: 879 | X66: 863 | Y66: 846 | Z66: 829 | AA66: 813 | AB66: 797 | AC66: 782 | AD66: 768 | AE66: 756 | AF66: 745 | AG66: 735 | AH66: 727 | AI66: 721 | AJ66: 715 | AK66: 712 | AL66: 710 | AN66: GU32 | AO66: 3
A67: 2 | B67: 23 | C67: 1098 | D67: 1097 | E67: 1095 | F67: 1091 | G67: 1087 | H67: 1081 | I67: 1074 | J67: 1065 | K67: 1056 | L67: 1045 | M67: 1033 | N67: 1021 | O67: 1007 | P67: 992 | Q67: 977 | R67: 962 | S67: 945 | T67: 929 | U67: 911 | V67: 894 | W67: 876 | X67: 859 | Y67: 841 | Z67: 824 | AA67: 807 | AB67: 791 | AC67: 775 | AD67: 761 | AE67: 748 | AF67: 736 | AG67: 726 | AH67: 718 | AI67: 711 | AJ67: 706 | AK67: 701 | AL67: 699 | AN67: GU33 | AO67: 3
A68: 2 | B68: 24 | C68: 1102 | D68: 1101 | E68: 1099 | F68: 1095 | G68: 1091 | H68: 1084 | I68: 1077 | J68: 1068 | K68: 1058 | L68: 1047 | M68: 1035 | N68: 1022 | O68: 1008 | P68: 993 | Q68: 978 | R68: 962 | S68: 945 | T68: 927 | U68: 910 | V68: 891 | W68: 873 | X68: 855 | Y68: 836 | Z68: 819 | AA68: 801 | AB68: 784 | AC68: 768 | AD68: 753 | AE68: 739 | AF68: 727 | AG68: 717 | AH68: 708 | AI68: 701 | AJ68: 695 | AK68: 691 | AL68: 688 | AN68: GU34 | AO68: 3
A69: 2 | B69: 25 | C69: 1105 | D69: 1105 | E69: 1103 | F69: 1099 | G69: 1094 | H69: 1088 | I69: 1080 | J69: 1071 | K69: 1061 | L69: 1050 | M69: 1037 | N69: 1024 | O69: 1009 | P69: 994 | Q69: 978 | R69: 961 | S69: 944 | T69: 926 | U69: 907 | V69: 889 | W69: 870 | X69: 851 | Y69: 832 | Z69: 814 | AA69: 796 | AB69: 778 | AC69: 761 | AD69: 745 | AE69: 731 | AF69: 719 | AG69: 708 | AH69: 699 | AI69: 691 | AJ69: 685 | AK69: 680 | AL69: 678 | AN69: GU35 | AO69: 3
... A94: 3 | B94: 9 | C94: 923 | D94: 922 | E94: 922 | F94: 920 | G94: 918 | H94: 916 | I94: 913 | J94: 910 | K94: 907 | L94: 903 | M94: 898 | N94: 893 | O94: 888 | P94: 883 | Q94: 877 | R94: 871 | S94: 865 | T94: 859 | U94: 853 | V94: 846 | W94: 840 | X94: 834 | Y94: 828 | Z94: 822 | AA94: 816 | AB94: 811 | AC94: 805 | AD94: 801 | AE94: 796 | AF94: 792 | AG94: 788 | AH94: 785 | AI94: 783 | AJ94: 781 | AK94: 779 | AL94: 779 | AN94: KY | AO94: 15
A95: 3 | B95: 10 | C95: 929 | D95: 929 | E95: 928 | F95: 926 | G95: 924 | H95: 922 | I95: 919 | J95: 915 | K95: 911 | L95: 907 | M95: 902 | N95: 897 | O95: 891 | P95: 885 | Q95: 879 | R95: 872 | S95: 866 | T95: 859 | U95: 852 | V95: 845 | W95: 838 | X95: 831 | Y95: 824 | Z95: 818 | AA95: 811 | AB95: 805 | AC95: 799 | AD95: 794 | AE95: 789 | AF95: 785 | AG95: 781 | AH95: 777 | AI95: 774 | AJ95: 772 | AK95: 770 | AL95: 769 | AN95: L | AO95: 7E
A96: 3 | B96: 11 | C96: 935 | D96: 935 | E96: 934 | F96: 932 | G96: 930 | H96: 928 | I96: 924 | J96: 920 | K96: 916 | L96: 911 | M96: 906 | N96: 900 | O96: 894 | P96: 887 | Q96: 880 | R96: 873 | S96: 866 | T96: 858 | U96: 851 | V96: 843 | W96: 836 | X96: 828 | Y96: 821 | Z96: 813 | AA96: 806 | AB96: 800 | AC96: 793 | AD96: 787 | AE96: 782 | AF96: 777 | AG96: 773 | AH96: 769 | AI96: 766 | AJ96: 763 | AK96: 761 | AL96: 760 | AN96: LA | AO96: 7E
A97: 3 | B97: 12 | C97: 941 | D97: 941 | E97: 940 | F97: 938 | G97: 936 | H97: 933 | I97: 929 | J97: 925 | K97: 920 | L97: 915 | M97: 909 | N97: 903 | O97: 896 | P97: 889 | Q97: 882 | R97: 874 | S97: 866 | T97: 858 | U97: 850 | V97: 842 | W97: 833 | X97: 825 | Y97: 817 | Z97: 809 | AA97: 801 | AB97: 794 | AC97: 787 | AD97: 781 | AE97: 775 | AF97: 769 | AG97: 764 | AH97: 760 | AI97: 757 | AJ97: 754 | AK97: 752 | AL97: 751 | AN97: LA7 | AO97: 8E
A98: 3 | B98: 13 | C98: 947 | D98: 947 | E98: 946 | F98: 944 | G98: 941 | H98: 938 | I98: 934 | J98: 930 | K98: 925 | L98: 919 | M98: 913 | N98: 906 | O98: 899 | P98: 891 | Q98: 883 | R98: 875 | S98: 867 | T98: 858 | U98: 849 | V98: 840 | W98: 831 | X98: 822 | Y98: 813 | Z98: 805 | AA98: 796 | AB98: 788 | AC98: 781 | AD98: 774 | AE98: 767 | AF98: 762 | AG98: 756 | AH98: 752 | AI98: 748 | AJ98: 745 | AK98: 743 | AL98: 742 | AN98: LA8 | AO98: 8E
A99: 3 | B99: 14 | C99: 953 | D99: 952 | E99: 951 | F99: 949 | G99: 947 | H99: 943 | I99: 939 | J99: 934 | K99: 929 | L99: 923 | M99: 916 | N99: 909 | O99: 901 | P99: 893 | Q99: 885 | R99: 876 | S99: 867 | T99: 857 | U99: 848 | V99: 838 | W99: 829 | X99: 819 | Y99: 810 | Z99: 800 | AA99: 791 | AB99: 783 | AC99: 775 | AD99: 767 | AE99: 760 | AF99: 754 | AG99: 748 | AH99: 744 | AI99: 740 | AJ99: 737 | AK99: 734 | AL99: 733 | AN99: LA9 | AO99: 8E
A100: 3 | B100: 15 | C100: 958 | D100: 958 | E100: 956 | F100: 954 | G100: 952 | H100: 948 | I100: 944 | J100: 939 | K100: 933 | L100: 926 | M100: 919 | N100: 912 | O100: 904 | P100: 895 | Q100: 886 | R100: 877 | S100: 867 | T100: 857 | U100: 847 | V100: 836 | W100: 826 | X100: 816 | Y100: 806 | Z100: 796 | AA100: 786 | AB100: 777 | AC100: 769 | AD100: 761 | AE100: 753 | AF100: 746 | AG100: 740 | AH100: 735 | AI100: 731 | AJ100: 728 | AK100: 726 | AL100: 724 | AN100: LA10 | AO100: 8E
A101: 3 | B101: 16 | C101: 963 | D101: 963 | E101: 962 | F101: 959 | G101: 956 | H101: 953 | I101: 948 | J101: 943 | K101: 937 | L101: 930 | M101: 922 | N101: 914 | O101: 906 | P101: 897 | Q101: 887 | R101: 877 | S101: 867 | T101: 856 | U101: 846 | V101: 835 | W101: 824 | X101: 813 | Y101: 802 | Z101: 792 | AA101: 782 | AB101: 772 | AC101: 762 | AD101: 754 | AE101: 746 | AF101: 739 | AG101: 732 | AH101: 727 | AI101: 723 | AJ101: 719 | AK101: 717 | AL101: 716 | AN101: LA11 | AO101: 8E
A102: 3 | B102: 17 | C102: 968 | D102: 968 | E102: 967 | F102: 964 | G102: 961 | H102: 957 | I102: 952 | J102: 947 | K102: 940 | L102: 933 | M102: 925 | N102: 917 | O102: 908 | P102: 898 | Q102: 888 | R102: 878 | S102: 867 | T102: 856 | U102: 844 | V102: 833 | W102: 821 | X102: 810 | Y102: 799 | Z102: 787 | AA102: 777 | AB102: 766 | AC102: 756 | AD102: 747 | AE102: 739 | AF102: 731 | AG102: 725 | AH102: 719 | AI102: 714 | AJ102: 711 | AK102: 709 | AL102: 707 | AN102: LA12 | AO102: 8E
A103: 3 | B103: 18 | C103: 973 | D103: 973 | E103: 971 | F103: 969 | G103: 966 | H103: 961 | I103: 956 | J103: 950 | K103: 944 | L103: 936 | M103: 928 | N103: 919 | O103: 910 | P103: 900 | Q103: 889 | R103: 878 | S103: 866 | T103: 855 | U103: 843 | V103: 831 | W103: 819 | X103: 807 | Y103: 795 | Z103: 783 | AA103: 772 | AB103: 760 | AC103: 750 | AD103: 740 | AE103: 732 | AF103: 724 | AG103: 717 | AH103: 711 | AI103: 706 | AJ103: 703 | AK103: 700 | AL103: 698 | AN103: LA13 | AO103: 8E
A104: 3 | B104: 19 | C104: 978 | D104: 977 | E104: 976 | F104: 973 | G104: 970 | H104: 966 | I104: 960 | J104: 954 | K104: 947 | L104: 939 | M104: 931 | N104: 921 | O104: 911 | P104: 901 | Q104: 890 | R104: 878 | S104: 866 | T104: 854 | U104: 842 | V104: 829 | W104: 816 | X104: 804 | Y104: 791 | Z104: 778 | AA104: 767 | AB104: 755 | AC104: 744 | AD104: 734 | AE104: 724 | AF104: 716 | AG104: 709 | AH104: 703 | AI104: 698 | AJ104: 694 | AK104: 692 | AL104: 690 | AN104: LA14 | AO104: 8E
A105: 3 | B105: 20 | C105: 982 | D105: 982 | E105: 980 | F105: 977 | G105: 974 | H105: 969 | I105: 964 | J105: 957 | K105: 950 | L105: 942 | M105: 933 | N105: 923 | O105: 913 | P105: 902 | Q105: 890 | R105: 878 | S105: 866 | T105: 853 | U105: 840 | V105: 827 | W105: 814 | X105: 800 | Y105: 787 | Z105: 774 | AA105: 762 | AB105: 749 | AC105: 738 | AD105: 727 | AE105: 717 | AF105: 709 | AG105: 701 | AH105: 695 | AI105: 690 | AJ105: 686 | AK105: 683 | AL105: 681 | AN105: LA15 | AO105: 8E
A106: 3 | B106: 21 | C106: 986 | D106: 986 | E106: 984 | F106: 981 | G106: 978 | H106: 973 | I106: 967 | J106: 961 | K106: 953 | L106: 944 | M106: 935 | N106: 925 | O106: 914 | P106: 903 | Q106: 891 | R106: 879 | S106: 865 | T106: 852 | U106: 839 | V106: 825 | W106: 811 | X106: 797 | Y106: 784 | Z106: 770 | AA106: 757 | AB106: 744 | AC106: 732 | AD106: 721 | AE106: 710 | AF106: 701 | AG106: 693 | AH106: 687 | AI106: 682 | AJ106: 677 | AK106: 674 | AL106: 673 | AN106: LA16 | AO106: 8E
... A113: 3 | B113: 28 | C113: 1009 | D113: 1009 | E113: 1007 | F113: 1003 | G113: 999 | H113: 993 | I113: 986 | J113: 978 | K113: 968 | L113: 958 | M113: 946 | N113: 934 | O113: 920 | P113: 906 | Q113: 891 | R113: 876 | S113: 860 | T113: 843 | U113: 826 | V113: 809 | W113: 792 | X113: 774 | Y113: 757 | Z113: 740 | AA113: 723 | AB113: 706 | AC113: 690 | AD113: 675 | AE113: 662 | AF113: 650 | AG113: 640 | AH113: 631 | AI113: 624 | AJ113: 618 | AK113: 614 | AL113: 612 | AN113: LA23 | AO113: 8E
A114: 3 | B114: 29 | C114: 1012 | D114: 1011 | E114: 1009 | F114: 1006 | G114: 1001 | H114: 995 | I114: 988 | J114: 979 | K114: 970 | L114: 959 | M114: 947 | N114: 934 | O114: 921 | P114: 906 | Q114: 891 | R114: 875 | S114: 859 | T114: 842 | U114: 824 | V114: 807 | W114: 789 | X114: 771 | Y114: 753 | Z114: 735 | AA114: 718 | AB114: 701 | AC114: 685 | AD114: 669 | AE114: 655 | AF114: 643 | AG114: 632 | AH114: 623 | AI114: 616 | AJ114: 610 | AK114: 606 | AL114: 603 | AN114: LD | AO114: 13
A115: 3 | B115: 30 | C115: 1014 | D115: 1013 | E115: 1011 | F115: 1008 | G115: 1003 | H115: 997 | I115: 989 | J115: 981 | K115: 971 | L115: 960 | M115: 948 | N115: 935 | O115: 921 | P115: 906 | Q115: 890 | R115: 874 | S115: 857 | T115: 840 | U115: 822 | V115: 804 | W115: 786 | X115: 768 | Y115: 749 | Z115: 731 | AA115: 713 | AB115: 696 | AC115: 679 | AD115: 663 | AE115: 649 | AF115: 636 | AG115: 625 | AH115: 615 | AI115: 607 | AJ115: 602 | AK115: 597 | AL115: 595 | AN115: LE | AO115: 6
A116: 3 | B116: 31 | C116: 1016 | D116: 1015 | E116: 1013 | F116: 1009 | G116: 1005 | H116: 998 | I116: 991 | J116: 982 | K116: 972 | L116: 961 | M116: 948 | N116: 935 | O116: 921 | P116: 906 | Q116: 890 | R116: 873 | S116: 856 | T116: 838 | U116: 820 | V116: 802 | W116: 783 | X116: 764 | Y116: 745 | Z116: 726 | AA116: 708 | AB116: 690 | AC116: 673 | AD116: 657 | AE116: 642 | AF116: 629 | AG116: 617 | AH116: 607 | AI116: 599 | AJ116: 593 | AK116: 589 | AL116: 587 | AN116: LL | AO116: 7W
A117: 3 | B117: 32 | C117: 1017 | D117: 1017 | E117: 1015 | F117: 1011 | G117: 1006 | H117: 1000 | I117: 992 | J117: 983 | K117: 973 | L117: 961 | M117: 949 | N117: 935 | O117: 920 | P117: 905 | Q117: 889 | R117: 872 | S117: 854 | T117: 836 | U117: 818 | V117: 799 | W117: 780 | X117: 760 | Y117: 741 | Z117: 722 | AA117: 703 | AB117: 685 | AC117: 667 | AD117: 651 | AE117: 635 | AF117: 622 | AG117: 610 | AH117: 600 | AI117: 591 | AJ117: 585 | AK117: 580 | AL117: 578 | AN117: LL23 | AO117: 13
A118: 3 | B118: 33 | C118: 1019 | D118: 1018 | E118: 1016 | F118: 1012 | G118: 1007 | H118: 1001 | I118: 993 | J118: 984 | K118: 973 | L118: 961 | M118: 949 | N118: 935 | O118: 920 | P118: 904 | Q118: 888 | R118: 870 | S118: 852 | T118: 834 | U118: 815 | V118: 796 | W118: 777 | X118: 757 | Y118: 737 | Z118: 718 | AA118: 699 | AB118: 680 | AC118: 662 | AD118: 644 | AE118: 629 | AF118: 615 | AG118: 602 | AH118: 592 | AI118: 583 | AJ118: 577 | AK118: 572 | AL118: 569 | AN118: LL24 | AO118: 13
A119: 3 | B119: 34 | C119: 1020 | D119: 1019 | E119: 1017 | F119: 1013 | G119: 1008 | H119: 1002 | I119: 994 | J119: 984 | K119: 974 | L119: 962 | M119: 949 | N119: 934 | O119: 919 | P119: 903 | Q119: 887 | R119: 869 | S119: 851 | T119: 832 | U119: 813 | V119: 793 | W119: 773 | X119: 753 | Y119: 733 | Z119: 713 | AA119: 694 | AB119: 675 | AC119: 656 | AD119: 638 | AE119: 622 | AF119: 608 | AG119: 595 | AH119: 584 | AI119: 575 | AJ119: 568 | AK119: 564 | AL119: 560 | AN119: LL25 | AO119: 13
A120: 3 | B120: 35 | C120: 1021 | D120: 1020 | E120: 1018 | F120: 1014 | G120: 1009 | H120: 1002 | I120: 994 | J120: 985 | K120: 974 | L120: 962 | M120: 948 | N120: 934 | O120: 919 | P120: 902 | Q120: 885 | R120: 867 | S120: 849 | T120: 830 | U120: 810 | V120: 790 | W120: 770 | X120: 750 | Y120: 729 | Z120: 709 | AA120: 689 | AB120: 669 | AC120: 650 | AD120: 633 | AE120: 616 | AF120: 601 | AG120: 588 | AH120: 576 | AI120: 567 | AJ120: 560 | AK120: 555 | AL120: 552 | AN120: LL26 | AO120: 13
A121: 3 | B121: 36 | C121: 1022 | D121: 1021 | E121: 1019 | F121: 1015 | G121: 1010 | H121: 1003 | I121: 995 | J121: 985 | K121: 974 | L121: 962 | M121: 948 | N121: 933 | O121: 918 | P121: 901 | Q121: 884 | R121: 866 | S121: 846 | T121: 827 | U121: 807 | V121: 787 | W121: 767 | X121: 746 | Y121: 725 | Z121: 704 | AA121: 684 | AB121: 664 | AC121: 645 | AD121: 626 | AE121: 609 | AF121: 594 | AG121: 580 | AH121: 569 | AI121: 559 | AJ121: 552 | AK121: 547 | AL121: 543 | AN121: LL27 | AO121: 13
A122: 3 | B122: 37 | C122: 1022 | D122: 1022 | E122: 1019 | F122: 1015 | G122: 1010 | H122: 1003 | I122: 995 | J122: 985 | K122: 974 | L122: 961 | M122: 947 | N122: 932 | O122: 917 | P122: 900 | Q122: 882 | R122: 864 | S122: 844 | T122: 825 | U122: 804 | V122: 784 | W122: 763 | X122: 742 | Y122: 721 | Z122: 700 | AA122: 679 | AB122: 659 | AC122: 639 | AD122: 621 | AE122: 603 | AF122: 587 | AG122: 573 | AH122: 561 | AI122: 552 | AJ122: 544 | AK122: 538 | AL122: 535 | AN122: LL30 | AO122: 13
A123: 3 | B123: 38 | C123: 1023 | D123: 1022 | E123: 1020 | F123: 1016 | G123: 1010 | H123: 1003 | I123: 995 | J123: 985 | K123: 973 | L123: 960 | M123: 947 | N123: 931 | O123: 915 | P123: 898 | Q123: 880 | R123: 862 | S123: 842 | T123: 822 | U123: 802 | V123: 781 | W123: 759 | X123: 738 | Y123: 717 | Z123: 695 | AA123: 675 | AB123: 654 | AC123: 634 | AD123: 615 | AE123: 597 | AF123: 580 | AG123: 566 | AH123: 554 | AI123: 544 | AJ123: 536 | AK123: 530 | AL123: 527 | AN123: LL31 | AO123: 13
A124: 3 | B124: 39 | C124: 1023 | D124: 1022 | E124: 1020 | F124: 1016 | G124: 1010 | H124: 1003 | I124: 994 | J124: 984 | K124: 973 | L124: 960 | M124: 945 | N124: 930 | O124: 914 | P124: 897 | Q124: 878 | R124: 859 | S124: 840 | T124: 819 | U124: 798 | V124: 777 | W124: 756 | X124: 734 | Y124: 712 | Z124: 691 | AA124: 669 | AB124: 649 | AC124: 628 | AD124: 609 | AE124: 590 | AF124: 573 | AG124: 559 | AH124: 546 | AI124: 536 | AJ124: 528 | AK124: 522 | AL124: 519 | AN124: LL32 | AO124: 13
A125: 3 | B125: 40 | C125: 1023 | D125: 1022 | E125: 1019 | F125: 1015 | G125: 1010 | H125: 1002 | I125: 994 | J125: 983 | K125: 972 | L125: 959 | M125: 944 | N125: 929 | O125: 912 | P125: 895 | Q125: 876 | R125: 857 | S125: 837 | T125: 816 | U125: 795 | V125: 774 | W125: 752 | X125: 730 | Y125: 708 | Z125: 686 | AA125: 665 | AB125: 643 | AC125: 623 | AD125: 603 | AE125: 584 | AF125: 567 | AG125: 552 | AH125: 539 | AI125: 528 | AJ125: 520 | AK125: 514 | AL125: 511 | AN125: LL33 | AO125: 13
A126: 4 | B126: 0 | C126: 907 | D126: 907 | E126: 907 | F126: 907 | G126: 907 | H126: 907 | I126: 907 | J126: 907 | K126: 907 | L126: 907 | M126: 907 | N126: 907 | O126: 907 | P126: 907 | Q126: 907 | R126: 907 | S126: 907 | T126: 907 | U126: 907 | V126: 907 | W126: 907 | X126: 907 | Y126: 907 | Z126: 907 | AA126: 907 | AB126: 907 | AC126: 907 | AD126: 907 | AE126: 907 | AF126: 907 | AG126: 907 | AH126: 907 | AI126: 907 | AJ126: 907 | AK126: 907 | AL126: 907 | AN126: LL34 | AO126: 13
A127: 4 | B127: 1 | C127: 916 | D127: 916 | E127: 916 | F127: 915 | G127: 915 | H127: 915 | I127: 914 | J127: 914 | K127: 914 | L127: 913 | M127: 912 | N127: 912 | O127: 911 | P127: 910 | Q127: 910 | R127: 909 | S127: 908 | T127: 907 | U127: 907 | V127: 906 | W127: 905 | X127: 904 | Y127: 904 | Z127: 903 | AA127: 902 | AB127: 902 | AC127: 901 | AD127: 900 | AE127: 900 | AF127: 899 | AG127: 899 | AH127: 899 | AI127: 898 | AJ127: 898 | AK127: 898 | AL127: 898 | AN127: LL35 | AO127: 13
A128: 4 | B128: 2 | C128: 924 | D128: 924 | E128: 924 | F128: 924 | G128: 923 | H128: 923 | I128: 922 | J128: 921 | K128: 920 | L128: 919 | M128: 918 | N128: 917 | O128: 915 | P128: 914 | Q128: 913 | R128: 911 | S128: 910 | T128: 908 | U128: 907 | V128: 905 | W128: 903 | X128: 902 | Y128: 900 | Z128: 899 | AA128: 897 | AB128: 896 | AC128: 895 | AD128: 894 | AE128: 893 | AF128: 892 | AG128: 891 | AH128: 890 | AI128: 890 | AJ128: 889 | AK128: 889 | AL128: 888 | AN128: LL36 | AO128: 13
... A166: 4 | B166: 40 | C166: 1093 | D166: 1092 | E166: 1089 | F166: 1085 | G166: 1079 | H166: 1072 | I166: 1063 | J166: 1052 | K166: 1039 | L166: 1025 | M166: 1010 | N166: 993 | O166: 975 | P166: 956 | Q166: 936 | R166: 915 | S166: 893 | T166: 871 | U166: 847 | V166: 823 | W166: 799 | X166: 774 | Y166: 750 | Z166: 725 | AA166: 701 | AB166: 676 | AC166: 653 | AD166: 630 | AE166: 608 | AF166: 588 | AG166: 570 | AH166: 555 | AI166: 543 | AJ166: 533 | AK166: 527 | AL166: 522 | AN166: LL74 | AO166: 13
A167: 5E | B167: 0 | C167: 820 | D167: 820 | E167: 820 | F167: 820 | G167: 820 | H167: 820 | I167: 820 | J167: 820 | K167: 820 | L167: 820 | M167: 820 | N167: 820 | O167: 820 | P167: 820 | Q167: 820 | R167: 820 | S167: 820 | T167: 820 | U167: 820 | V167: 820 | W167: 820 | X167: 820 | Y167: 820 | Z167: 820 | AA167: 820 | AB167: 820 | AC167: 820 | AD167: 820 | AE167: 820 | AF167: 820 | AG167: 820 | AH167: 820 | AI167: 820 | AJ167: 820 | AK167: 820 | AL167: 820 | AN167: LL75 | AO167: 13
...

Sheet Lookup Data
A2: Item | B2: Type | C2: Cost | D2: Vat Rate
A3: None | B3: None | C3: 0 | D3: 0
A4: Sofar Solar 4000 HYD Hybrid Inverter | B4: Uplift | C4: =699.5-Costing!F14 -> 451.1 | D4: 0.05
A5: Sofar Solar 5000 HYD Hybrid Inverter | B5: Uplift | C5: =764.4-Costing!F14 -> 516 | D5: 0.05
A6: Sofar Solar 6000 HYD Hybrid Inverter | B6: Uplift | C6: =799.68-Costing!F14 -> 551.28 | D6: 0.05
A7: Grid Application - Sub 5kW System | B7: Addition | C7: 160 | D7: 0.2
A8: Grid Application - Over 5kW System | B8: Addition | C8: 650 | D8: 0.2
A9: String Inverter - AC Coupled - Sub 8 Panels | B9: Addition | C9: 277 | D9: 0.05
A10: Immersun - Non Display | B10: Addition | C10: 358.9 | D10: 0.2
A11: Immersun - Full Display | B11: Addition | C11: 476.79 | D11: 0.2
A12: Pod Point Car Charger - 7 kW | B12: Addition | C12: 440 | D12: 0.2
A13: EV Box Car Charger - 7kW | B13: Addition | C13: 279 | D13: 0.2
A14: Q Cell 345W Modules | B14: Uplift | C14: =Costing!C2*(105.4-Costing!M13) -> 352 | D14: 0.05
